Workbook

Sheet Raw_Data
A1: Order ID | B1: Order Date | C1: Customer ID | D1: Type | E1: SKU | F1: Category | G1: Product Name | H1: Unit Price | I1: Qty | J1: Total | K1: Discount Code | L1: Disc % | M1: Payment | N1: Source | O1: City | P1: State | Q1: Warehouse | R1: Del Date | S1: Status | T1: Return? | U1: Reason | V1: Ret Rec | W1: Refund | AB1: Duplicate_Count
A2: UT-100001 | B2: 45566 | C2: CUST_10001 | D2: New | E2: TOP-CAS-M | F2: Tops | G2: Classic Cotton Tee | H2: 1299 | I2: 2 | J2: 2598 | L2: 0 | M2: UPI | N2: Website | O2: Mumbai | P2: Maharashtra | Q2: Mumbai | R2: 45570 | S2: Delivered | T2: No | W2: Not Applicable | AA2: =COUNTBLANK(U2:U347) -> 166 | AB2: =COUNTIF(A$2:A$347,A2) -> 1 | AC2: =LEN(S2)-LEN(TRIM(S2)) -> 0 | AD2: =LEN(E2)-LEN(SUBSTITUTE(E2,"-","")) -> 2 | AE2: =IF(I2>10,"FLAG","OK") -> OK | AF2: =IF(OR(H2<=0,H2>10000),"FLAG","OK") -> OK | AG2: =IF(OR(L2<0,L2>100),"FLAG","OK") -> OK | AH2: =ROUND((H2*I2)*(1-L2/100),0) -> 2598 | AI2: =IF(AG2=J2,"OK","ERROR") -> ERROR | AJ2: =IF(R2<B2,"ERROR","OK") -> OK | AK2: =IF(AND(S2="Cancelled",R2<>""),"ERROR","OK") -> OK | AL2: =IF(AND(T2="Yes",U2=""),"ERROR","OK") -> OK | AM2: =IF(V2<R2,"ERROR","OK") -> ERROR | AN2: =IF(AND(I2>0,MOD(I2,1)=0),"OK","ERROR") -> OK | AO2: =IF(OR(B2="",B2<DATE(2024,10,1),B2>DATE(2024,12,31)),"ERROR","OK") -> OK | AP2: =IF(OR(B2<DATE(2024,10,1),B2>DATE(2024,12,31)),"ERROR","OK") -> OK | AQ2: =IF(OR(S2="Delivered",S2="Cancelled",S2="RTO",S2="In Transit"),"OK","ERROR") -> OK
A3: UT-100002 | B3: 45566 | C3: CUST_10002 | D3: Returning | E3: DRS-FRM-S | F3: Dresses | G3: Floral Midi Dress | H3: 2499 | I3: 1 | J3: 2499 | K3: DIWALI20 | L3: 20 | M3: Credit Card | N3: Mobile App | O3: Delhi | P3: Delhi | Q3: Delhi | R3: 45569 | S3: Delivered | T3: Yes | U3: Size Issue | V3: 45580 | W3: Processed | AA3: =COUNTBLANK(R2:R347) -> 18 | AB3: =COUNTIF(A$2:A$347,A3) -> 1 | AC3: =LEN(S3)-LEN(TRIM(S3)) -> 0 | AD3: =LEN(E3)-LEN(SUBSTITUTE(E3,"-","")) -> 2 | AE3: =IF(I3>10,"FLAG","OK") -> OK | AF3: =IF(OR(H3<=0,H3>10000),"FLAG","OK") -> OK | AG3: =IF(OR(L3<0,L3>100),"FLAG","OK") -> OK | AI3: =IF(AG3=J3,"OK","ERROR") -> ERROR | AJ3: =IF(R3<B3,"ERROR","OK") -> OK | AK3: =IF(AND(S3="Cancelled",R3<>""),"ERROR","OK") -> OK | AL3: =IF(AND(T3="Yes",U3=""),"ERROR","OK") -> OK | AM3: =IF(V3<R3,"ERROR","OK") -> OK | AN3: =IF(AND(I3>0,MOD(I3,1)=0),"OK","ERROR") -> OK | AO3: =IF(OR(B3="",B3<DATE(2024,10,1),B3>DATE(2024,12,31)),"ERROR","OK") -> OK | AP3: =IF(OR(B3<DATE(2024,10,1),B3>DATE(2024,12,31)),"ERROR","OK") -> OK | AQ3: =IF(OR(S3="Delivered",S3="Cancelled",S3="RTO",S3="In Transit"),"OK","ERROR") -> OK
A4: UT-100003 | B4: 45301 | C4: CUST_10003 | D4: new | E4: BOT-JNS-L | F4: Bottoms | G4: Slim Fit Jeans | H4: 1899 | I4: 1 | J4: 1899 | L4: 0 | M4: COD | N4: Website | O4: Bangalore | P4: Karnataka | Q4: Bangalore | R4: 45571 | S4: Delivered | T4: No | W4: Not Applicable | AA4: =COUNTBLANK(K2:K347) -> 206 | AB4: =COUNTIF(A$2:A$347,A4) -> 1 | AC4: =LEN(S4)-LEN(TRIM(S4)) -> 0 | AD4: =LEN(E4)-LEN(SUBSTITUTE(E4,"-","")) -> 2 | AE4: =IF(I4>10,"FLAG","OK") -> OK | AF4: =IF(OR(H4<=0,H4>10000),"FLAG","OK") -> OK | AG4: =IF(OR(L4<0,L4>100),"FLAG","OK") -> OK | AI4: =IF(AG4=J4,"OK","ERROR") -> ERROR | AJ4: =IF(R4<B4,"ERROR","OK") -> OK | AK4: =IF(AND(S4="Cancelled",R4<>""),"ERROR","OK") -> OK | AL4: =IF(AND(T4="Yes",U4=""),"ERROR","OK") -> OK | AM4: =IF(V4<R4,"ERROR","OK") -> ERROR | AN4: =IF(AND(I4>0,MOD(I4,1)=0),"OK","ERROR") -> OK | AO4: =IF(OR(B4="",B4<DATE(2024,10,1),B4>DATE(2024,12,31)),"ERROR","OK") -> ERROR | AP4: =IF(OR(B4<DATE(2024,10,1),B4>DATE(2024,12,31)),"ERROR","OK") -> ERROR | AQ4: =IF(OR(S4="Delivered",S4="Cancelled",S4="RTO",S4="In Transit"),"OK","ERROR") -> OK
A5: UT-100004 | B5: 45566 | C5: CUST_10004 | D5: New | E5: OUT-JKT-XL | F5: Outerwear | G5: Denim Jacket | H5: 3499 | I5: 1 | J5: 3499 | K5: FIRST15 | L5: 15 | M5: Debit Card | N5: Instagram Shop | O5: Chennai | P5: Tamil Nadu | Q5: Mumbai | R5: 45573 | S5: Delivered | T5: Yes | U5: Quality Defect | V5: 45585 | W5: Processed | AA5: =COUNTBLANK(V2:V347) -> 166 | AB5: =COUNTIF(A$2:A$347,A5) -> 1 | AC5: =LEN(S5)-LEN(TRIM(S5)) -> 0 | AD5: =LEN(E5)-LEN(SUBSTITUTE(E5,"-","")) -> 2 | AE5: =IF(I5>10,"FLAG","OK") -> OK | AF5: =IF(OR(H5<=0,H5>10000),"FLAG","OK") -> OK | AG5: =IF(OR(L5<0,L5>100),"FLAG","OK") -> OK | AI5: =IF(AG5=J5,"OK","ERROR") -> ERROR | AJ5: =IF(R5<B5,"ERROR","OK") -> OK | AK5: =IF(AND(S5="Cancelled",R5<>""),"ERROR","OK") -> OK | AL5: =IF(AND(T5="Yes",U5=""),"ERROR","OK") -> OK | AM5: =IF(V5<R5,"ERROR","OK") -> OK | AN5: =IF(AND(I5>0,MOD(I5,1)=0),"OK","ERROR") -> OK | AO5: =IF(OR(B5="",B5<DATE(2024,10,1),B5>DATE(2024,12,31)),"ERROR","OK") -> OK | AP5: =IF(OR(B5<DATE(2024,10,1),B5>DATE(2024,12,31)),"ERROR","OK") -> OK | AQ5: =IF(OR(S5="Delivered",S5="Cancelled",S5="RTO",S5="In Transit"),"OK","ERROR") -> OK
A6: UT-100005 | B6: 45566 | C6: CUST_10001 | D6: New | E6: ACC-SCF-OS | F6: Accessories | G6: Silk Scarf | H6: 799 | I6: 3 | J6: 2397 | L6: 0 | M6: UPI | N6: Website | O6: Mumbai | P6: Maharashtra | Q6: Mumbai | R6: 45571 | S6: Delivered | T6: No | W6: Not Applicable | AB6: =COUNTIF(A$2:A$347,A6) -> 1 | AC6: =LEN(S6)-LEN(TRIM(S6)) -> 0 | AD6: =LEN(E6)-LEN(SUBSTITUTE(E6,"-","")) -> 2 | AE6: =IF(I6>10,"FLAG","OK") -> OK | AF6: =IF(OR(H6<=0,H6>10000),"FLAG","OK") -> OK | AG6: =IF(OR(L6<0,L6>100),"FLAG","OK") -> OK | AI6: =IF(AG6=J6,"OK","ERROR") -> ERROR | AJ6: =IF(R6<B6,"ERROR","OK") -> OK | AK6: =IF(AND(S6="Cancelled",R6<>""),"ERROR","OK") -> OK | AL6: =IF(AND(T6="Yes",U6=""),"ERROR","OK") -> OK | AM6: =IF(V6<R6,"ERROR","OK") -> ERROR | AN6: =IF(AND(I6>0,MOD(I6,1)=0),"OK","ERROR") -> OK | AO6: =IF(OR(B6="",B6<DATE(2024,10,1),B6>DATE(2024,12,31)),"ERROR","OK") -> OK | AP6: =IF(OR(B6<DATE(2024,10,1),B6>DATE(2024,12,31)),"ERROR","OK") -> OK | AQ6: =IF(OR(S6="Delivered",S6="Cancelled",S6="RTO",S6="In Transit"),"OK","ERROR") -> OK
A7: UT-100006 | B7: 45567 | C7: CUST_10005 | D7: Returning | E7: TOP-FRM-S | F7: Tops | G7: Printed Blouse | H7: 1599 | I7: 2 | J7: 3198 | L7: 0 | M7: Credit Card | N7: Mobile App | O7: Hyderabad | P7: Telangana | Q7: Bangalore | R7: 45572 | S7: Delivered | T7: Yes | U7: Changed Mind | V7: 45583 | W7: Processed | AB7: =COUNTIF(A$2:A$347,A7) -> 1 | AC7: =LEN(S7)-LEN(TRIM(S7)) -> 0 | AD7: =LEN(E7)-LEN(SUBSTITUTE(E7,"-","")) -> 2 | AE7: =IF(I7>10,"FLAG","OK") -> OK | AF7: =IF(OR(H7<=0,H7>10000),"FLAG","OK") -> OK | AG7: =IF(OR(L7<0,L7>100),"FLAG","OK") -> OK | AI7: =IF(AG7=J7,"OK","ERROR") -> ERROR | AJ7: =IF(R7<B7,"ERROR","OK") -> OK | AK7: =IF(AND(S7="Cancelled",R7<>""),"ERROR","OK") -> OK | AL7: =IF(AND(T7="Yes",U7=""),"ERROR","OK") -> OK | AM7: =IF(V7<R7,"ERROR","OK") -> OK | AN7: =IF(AND(I7>0,MOD(I7,1)=0),"OK","ERROR") -> OK | AO7: =IF(OR(B7="",B7<DATE(2024,10,1),B7>DATE(2024,12,31)),"ERROR","OK") -> OK | AP7: =IF(OR(B7<DATE(2024,10,1),B7>DATE(2024,12,31)),"ERROR","OK") -> OK | AQ7: =IF(OR(S7="Delivered",S7="Cancelled",S7="RTO",S7="In Transit"),"OK","ERROR") -> OK
A8: UT-100007 | B8: 45567 | C8: CUST_10006 | D8: New | E8: DRS-CAS-M | F8: Dresses | G8: A-Line Dress | H8: 2199 | I8: 1 | J8: 2199 | K8: DIWALI20 | L8: 20 | M8: COD | N8: Website | O8: Pune | P8: Maharashtra | Q8: Mumbai | S8: Cancelled | T8: No | W8: Not Applicable | AB8: =COUNTIF(A$2:A$347,A8) -> 1 | AC8: =LEN(S8)-LEN(TRIM(S8)) -> 0 | AD8: =LEN(E8)-LEN(SUBSTITUTE(E8,"-","")) -> 2 | AE8: =IF(I8>10,"FLAG","OK") -> OK | AF8: =IF(OR(H8<=0,H8>10000),"FLAG","OK") -> OK | AG8: =IF(OR(L8<0,L8>100),"FLAG","OK") -> OK | AI8: =IF(AG8=J8,"OK","ERROR") -> ERROR | AJ8: =IF(R8<B8,"ERROR","OK") -> ERROR | AK8: =IF(AND(S8="Cancelled",R8<>""),"ERROR","OK") -> OK | AL8: =IF(AND(T8="Yes",U8=""),"ERROR","OK") -> OK | AM8: =IF(V8<R8,"ERROR","OK") -> OK | AN8: =IF(AND(I8>0,MOD(I8,1)=0),"OK","ERROR") -> OK | AO8: =IF(OR(B8="",B8<DATE(2024,10,1),B8>DATE(2024,12,31)),"ERROR","OK") -> OK | AP8: =IF(OR(B8<DATE(2024,10,1),B8>DATE(2024,12,31)),"ERROR","OK") -> OK | AQ8: =IF(OR(S8="Delivered",S8="Cancelled",S8="RTO",S8="In Transit"),"OK","ERROR") -> OK
A9: UT-100008 | B9: 45567 | C9: CUST_10007 | D9: New | E9: BOT-TRS-L | F9: Bottoms | G9: Formal Trousers | H9: 2299 | I9: 1 | J9: 2299 | L9: 0 | M9: UPI | N9: Mobile App | O9: Kolkata | P9: West Bengal | Q9: Delhi | R9: 45575 | S9: Delivered | T9: No | W9: Not Applicable | AB9: =COUNTIF(A$2:A$347,A9) -> 1 | AC9: =LEN(S9)-LEN(TRIM(S9)) -> 0 | AD9: =LEN(E9)-LEN(SUBSTITUTE(E9,"-","")) -> 2 | AE9: =IF(I9>10,"FLAG","OK") -> OK | AF9: =IF(OR(H9<=0,H9>10000),"FLAG","OK") -> OK | AG9: =IF(OR(L9<0,L9>100),"FLAG","OK") -> OK | AI9: =IF(AG9=J9,"OK","ERROR") -> ERROR | AJ9: =IF(R9<B9,"ERROR","OK") -> OK | AK9: =IF(AND(S9="Cancelled",R9<>""),"ERROR","OK") -> OK | AL9: =IF(AND(T9="Yes",U9=""),"ERROR","OK") -> OK | AM9: =IF(V9<R9,"ERROR","OK") -> ERROR | AN9: =IF(AND(I9>0,MOD(I9,1)=0),"OK","ERROR") -> OK | AO9: =IF(OR(B9="",B9<DATE(2024,10,1),B9>DATE(2024,12,31)),"ERROR","OK") -> OK | AP9: =IF(OR(B9<DATE(2024,10,1),B9>DATE(2024,12,31)),"ERROR","OK") -> OK | AQ9: =IF(OR(S9="Delivered",S9="Cancelled",S9="RTO",S9="In Transit"),"OK","ERROR") -> OK
A10: UT-100009 | B10: 45567 | C10: CUST_10008 | D10: Returning | E10: TOP-CAS-XL | F10: Tops | G10: Oversized Tee | H10: 1399 | I10: 5 | J10: 6995 | L10: 0 | M10: Credit Card | N10: Website | O10: Ahmedabad | P10: Gujarat | Q10: Mumbai | R10: 45574 | S10: Delivered | T10: Yes | U10: Size Issue | V10: 45587 | W10: Processed | AB10: =COUNTIF(A$2:A$347,A10) -> 1 | AC10: =LEN(S10)-LEN(TRIM(S10)) -> 0 | AD10: =LEN(E10)-LEN(SUBSTITUTE(E10,"-","")) -> 2 | AE10: =IF(I10>10,"FLAG","OK") -> OK | AF10: =IF(OR(H10<=0,H10>10000),"FLAG","OK") -> OK | AG10: =IF(OR(L10<0,L10>100),"FLAG","OK") -> OK | AI10: =IF(AG10=J10,"OK","ERROR") -> ERROR | AJ10: =IF(R10<B10,"ERROR","OK") -> OK | AK10: =IF(AND(S10="Cancelled",R10<>""),"ERROR","OK") -> OK | AL10: =IF(AND(T10="Yes",U10=""),"ERROR","OK") -> OK | AM10: =IF(V10<R10,"ERROR","OK") -> OK | AN10: =IF(AND(I10>0,MOD(I10,1)=0),"OK","ERROR") -> OK | AO10: =IF(OR(B10="",B10<DATE(2024,10,1),B10>DATE(2024,12,31)),"ERROR","OK") -> OK | AP10: =IF(OR(B10<DATE(2024,10,1),B10>DATE(2024,12,31)),"ERROR","OK") -> OK | AQ10: =IF(OR(S10="Delivered",S10="Cancelled",S10="RTO",S10="In Transit"),"OK","ERROR") -> OK
A11: UT-100010 | B11: 45567 | C11: CUST_10009 | D11: New | E11: OUT-BLZ-M | F11: Outerwear | G11: Casual Blazer | H11: 4999 | I11: -1 | J11: 4999 | L11: 0 | M11: Debit Card | N11: Instagram Shop | O11: Jaipur | P11: Rajasthan | Q11: Delhi | R11: 45576 | S11: Delivered | T11: Yes | U11: Wrong Item | V11: 45590 | W11: Pending | AB11: =COUNTIF(A$2:A$347,A11) -> 1 | AC11: =LEN(S11)-LEN(TRIM(S11)) -> 0 | AD11: =LEN(E11)-LEN(SUBSTITUTE(E11,"-","")) -> 2 | AE11: =IF(I11>10,"FLAG","OK") -> OK | AF11: =IF(OR(H11<=0,H11>10000),"FLAG","OK") -> OK | AG11: =IF(OR(L11<0,L11>100),"FLAG","OK") -> OK | AI11: =IF(AG11=J11,"OK","ERROR") -> ERROR | AJ11: =IF(R11<B11,"ERROR","OK") -> OK | AK11: =IF(AND(S11="Cancelled",R11<>""),"ERROR","OK") -> OK | AL11: =IF(AND(T11="Yes",U11=""),"ERROR","OK") -> OK | AM11: =IF(V11<R11,"ERROR","OK") -> OK | AN11: =IF(AND(I11>0,MOD(I11,1)=0),"OK","ERROR") -> ERROR | AO11: =IF(OR(B11="",B11<DATE(2024,10,1),B11>DATE(2024,12,31)),"ERROR","OK") -> OK | AP11: =IF(OR(B11<DATE(2024,10,1),B11>DATE(2024,12,31)),"ERROR","OK") -> OK | AQ11: =IF(OR(S11="Delivered",S11="Cancelled",S11="RTO",S11="In Transit"),"OK","ERROR") -> OK
A12: UT-100011 | B12: 45568 | C12: CUST_10010 | D12: New | E12: ACC-BAG-OS | F12: Accessories | G12: Tote Bag | H12: 1299 | I12: 2 | J12: 2598 | K12: FLAT10 | L12: 10 | M12: Wallet | N12: Website | O12: Lucknow | P12: Uttar Pradesh | Q12: Delhi | R12: 45575 | S12: Delivered | T12: No | W12: Not Applicable | AB12: =COUNTIF(A$2:A$347,A12) -> 1 | AC12: =LEN(S12)-LEN(TRIM(S12)) -> 0 | AD12: =LEN(E12)-LEN(SUBSTITUTE(E12,"-","")) -> 2 | AE12: =IF(I12>10,"FLAG","OK") -> OK | AF12: =IF(OR(H12<=0,H12>10000),"FLAG","OK") -> OK | AG12: =IF(OR(L12<0,L12>100),"FLAG","OK") -> OK | AI12: =IF(AG12=J12,"OK","ERROR") -> ERROR | AJ12: =IF(R12<B12,"ERROR","OK") -> OK | AK12: =IF(AND(S12="Cancelled",R12<>""),"ERROR","OK") -> OK | AL12: =IF(AND(T12="Yes",U12=""),"ERROR","OK") -> OK | AM12: =IF(V12<R12,"ERROR","OK") -> ERROR | AN12: =IF(AND(I12>0,MOD(I12,1)=0),"OK","ERROR") -> OK | AO12: =IF(OR(B12="",B12<DATE(2024,10,1),B12>DATE(2024,12,31)),"ERROR","OK") -> OK | AP12: =IF(OR(B12<DATE(2024,10,1),B12>DATE(2024,12,31)),"ERROR","OK") -> OK | AQ12: =IF(OR(S12="Delivered",S12="Cancelled",S12="RTO",S12="In Transit"),"OK","ERROR") -> OK
A13: UT-100012 | B13: 45568 | C13: CUST_10011 | D13: New | E13: DRS-PRT-S | F13: Dresses | G13: Party Dress | H13: 3299 | I13: 1 | J13: 3299 | L13: 0 | M13: COD | N13: Mobile App | O13: Chandigarh | P13: Punjab | Q13: Delhi | S13: RTO | T13: No | W13: Not Applicable | AB13: =COUNTIF(A$2:A$347,A13) -> 1 | AC13: =LEN(S13)-LEN(TRIM(S13)) -> 0 | AD13: =LEN(E13)-LEN(SUBSTITUTE(E13,"-","")) -> 2 | AE13: =IF(I13>10,"FLAG","OK") -> OK | AF13: =IF(OR(H13<=0,H13>10000),"FLAG","OK") -> OK | AG13: =IF(OR(L13<0,L13>100),"FLAG","OK") -> OK | AI13: =IF(AG13=J13,"OK","ERROR") -> ERROR | AJ13: =IF(R13<B13,"ERROR","OK") -> ERROR | AK13: =IF(AND(S13="Cancelled",R13<>""),"ERROR","OK") -> OK | AL13: =IF(AND(T13="Yes",U13=""),"ERROR","OK") -> OK | AM13: =IF(V13<R13,"ERROR","OK") -> OK | AN13: =IF(AND(I13>0,MOD(I13,1)=0),"OK","ERROR") -> OK | AO13: =IF(OR(B13="",B13<DATE(2024,10,1),B13>DATE(2024,12,31)),"ERROR","OK") -> OK | AP13: =IF(OR(B13<DATE(2024,10,1),B13>DATE(2024,12,31)),"ERROR","OK") -> OK | AQ13: =IF(OR(S13="Delivered",S13="Cancelled",S13="RTO",S13="In Transit"),"OK","ERROR") -> OK
A14: UT-100013 | B14: 45568 | C14: CUST_10012 | D14: Returning | E14: TOP-SLK-M | F14: Tops | G14: Silk Blouse | H14: 2499 | I14: 1 | J14: 2499 | L14: 0 | M14: Credit Card | N14: Website | O14: Mumbai | P14: Maharashtra | Q14: Mumbai | R14: 45574 | S14: Delivered | T14: No | W14: Not Applicable | AB14: =COUNTIF(A$2:A$347,A14) -> 1 | AC14: =LEN(S14)-LEN(TRIM(S14)) -> 0 | AD14: =LEN(E14)-LEN(SUBSTITUTE(E14,"-","")) -> 2 | AE14: =IF(I14>10,"FLAG","OK") -> OK | AF14: =IF(OR(H14<=0,H14>10000),"FLAG","OK") -> OK | AG14: =IF(OR(L14<0,L14>100),"FLAG","OK") -> OK | AI14: =IF(AG14=J14,"OK","ERROR") -> ERROR | AJ14: =IF(R14<B14,"ERROR","OK") -> OK | AK14: =IF(AND(S14="Cancelled",R14<>""),"ERROR","OK") -> OK | AL14: =IF(AND(T14="Yes",U14=""),"ERROR","OK") -> OK | AM14: =IF(V14<R14,"ERROR","OK") -> ERROR | AN14: =IF(AND(I14>0,MOD(I14,1)=0),"OK","ERROR") -> OK | AO14: =IF(OR(B14="",B14<DATE(2024,10,1),B14>DATE(2024,12,31)),"ERROR","OK") -> OK | AP14: =IF(OR(B14<DATE(2024,10,1),B14>DATE(2024,12,31)),"ERROR","OK") -> OK | AQ14: =IF(OR(S14="Delivered",S14="Cancelled",S14="RTO",S14="In Transit"),"OK","ERROR") -> OK
A15: UT-100014 | B15: 45568 | C15: CUST_10013 | D15: New | E15: BOT-SKT-S | F15: Bottoms | G15: Pleated Skirt | H15: 1799 | I15: 2 | J15: 3598 | K15: DIWALI20 | L15: 20 | M15: UPI | N15: Instagram Shop | O15: Delhi | P15: Delhi | Q15: Delhi | R15: 45576 | S15: Delivered | T15: Yes | U15: Size Issue | V15: 45593 | W15: Processed | AB15: =COUNTIF(A$2:A$347,A15) -> 1 | AC15: =LEN(S15)-LEN(TRIM(S15)) -> 0 | AD15: =LEN(E15)-LEN(SUBSTITUTE(E15,"-","")) -> 2 | AE15: =IF(I15>10,"FLAG","OK") -> OK | AF15: =IF(OR(H15<=0,H15>10000),"FLAG","OK") -> OK | AG15: =IF(OR(L15<0,L15>100),"FLAG","OK") -> OK | AI15: =IF(AG15=J15,"OK","ERROR") -> ERROR | AJ15: =IF(R15<B15,"ERROR","OK") -> OK | AK15: =IF(AND(S15="Cancelled",R15<>""),"ERROR","OK") -> OK | AL15: =IF(AND(T15="Yes",U15=""),"ERROR","OK") -> OK | AM15: =IF(V15<R15,"ERROR","OK") -> OK | AN15: =IF(AND(I15>0,MOD(I15,1)=0),"OK","ERROR") -> OK | AO15: =IF(OR(B15="",B15<DATE(2024,10,1),B15>DATE(2024,12,31)),"ERROR","OK") -> OK | AP15: =IF(OR(B15<DATE(2024,10,1),B15>DATE(2024,12,31)),"ERROR","OK") -> OK | AQ15: =IF(OR(S15="Delivered",S15="Cancelled",S15="RTO",S15="In Transit"),"OK","ERROR") -> OK
A16: UT-100015 | B16: 45568 | C16: CUST_10014 | D16: New | E16: OUT-CRD-L | F16: Outerwear | G16: Knit Cardigan | H16: 2799 | I16: 1 | J16: 2799 | L16: 0 | M16: Debit Card | N16: Mobile App | O16: Bangalore | P16: Karnataka | Q16: Bangalore | R16: 45577 | S16: Delivered | T16: No | W16: Not Applicable | AB16: =COUNTIF(A$2:A$347,A16) -> 1 | AC16: =LEN(S16)-LEN(TRIM(S16)) -> 0 | AD16: =LEN(E16)-LEN(SUBSTITUTE(E16,"-","")) -> 2 | AE16: =IF(I16>10,"FLAG","OK") -> OK | AF16: =IF(OR(H16<=0,H16>10000),"FLAG","OK") -> OK | AG16: =IF(OR(L16<0,L16>100),"FLAG","OK") -> OK | AI16: =IF(AG16=J16,"OK","ERROR") -> ERROR | AJ16: =IF(R16<B16,"ERROR","OK") -> OK | AK16: =IF(AND(S16="Cancelled",R16<>""),"ERROR","OK") -> OK | AL16: =IF(AND(T16="Yes",U16=""),"ERROR","OK") -> OK | AM16: =IF(V16<R16,"ERROR","OK") -> ERROR | AN16: =IF(AND(I16>0,MOD(I16,1)=0),"OK","ERROR") -> OK | AO16: =IF(OR(B16="",B16<DATE(2024,10,1),B16>DATE(2024,12,31)),"ERROR","OK") -> OK | AP16: =IF(OR(B16<DATE(2024,10,1),B16>DATE(2024,12,31)),"ERROR","OK") -> OK | AQ16: =IF(OR(S16="Delivered",S16="Cancelled",S16="RTO",S16="In Transit"),"OK","ERROR") -> OK
A17: UT-100016 | B17: 45569 | C17: CUST_10015 | D17: Returning | E17: ACC-JWL-OS | F17: Accessories | G17: Statement Earrings | H17: 599 | I17: 4 | J17: 2396 | L17: 0 | M17: COD | N17: Website | O17: Noida | P17: Uttar Pradesh | Q17: Delhi | R17: 45579 | S17: Delivered | T17: Yes | U17: Damaged in Transit | V17: 45591 | W17: Processed | AB17: =COUNTIF(A$2:A$347,A17) -> 1 | AC17: =LEN(S17)-LEN(TRIM(S17)) -> 0 | AD17: =LEN(E17)-LEN(SUBSTITUTE(E17,"-","")) -> 2 | AE17: =IF(I17>10,"FLAG","OK") -> OK | AF17: =IF(OR(H17<=0,H17>10000),"FLAG","OK") -> OK | AG17: =IF(OR(L17<0,L17>100),"FLAG","OK") -> OK | AI17: =IF(AG17=J17,"OK","ERROR") -> ERROR | AJ17: =IF(R17<B17,"ERROR","OK") -> OK | AK17: =IF(AND(S17="Cancelled",R17<>""),"ERROR","OK") -> OK | AL17: =IF(AND(T17="Yes",U17=""),"ERROR","OK") -> OK | AM17: =IF(V17<R17,"ERROR","OK") -> OK | AN17: =IF(AND(I17>0,MOD(I17,1)=0),"OK","ERROR") -> OK | AO17: =IF(OR(B17="",B17<DATE(2024,10,1),B17>DATE(2024,12,31)),"ERROR","OK") -> OK | AP17: =IF(OR(B17<DATE(2024,10,1),B17>DATE(2024,12,31)),"ERROR","OK") -> OK | AQ17: =IF(OR(S17="Delivered",S17="Cancelled",S17="RTO",S17="In Transit"),"OK","ERROR") -> OK
A18: UT-100017 | B18: 45569 | C18: CUST_10016 | D18: New | E18: TOP-CRP-XS | F18: Tops | G18: Crop Top | H18: 999 | I18: 1 | J18: 999 | K18: FIRST15 | L18: 15 | M18: UPI | N18: Mobile App | O18: Gurgaon | P18: Haryana | Q18: Delhi | R18: 45577 | S18: Delievered | T18: No | W18: Not Applicable | AB18: =COUNTIF(A$2:A$347,A18) -> 1 | AC18: =LEN(S18)-LEN(TRIM(S18)) -> 0 | AD18: =LEN(E18)-LEN(SUBSTITUTE(E18,"-","")) -> 2 | AE18: =IF(I18>10,"FLAG","OK") -> OK | AF18: =IF(OR(H18<=0,H18>10000),"FLAG","OK") -> OK | AG18: =IF(OR(L18<0,L18>100),"FLAG","OK") -> OK | AI18: =IF(AG18=J18,"OK","ERROR") -> ERROR | AJ18: =IF(R18<B18,"ERROR","OK") -> OK | AK18: =IF(AND(S18="Cancelled",R18<>""),"ERROR","OK") -> OK | AL18: =IF(AND(T18="Yes",U18=""),"ERROR","OK") -> OK | AM18: =IF(V18<R18,"ERROR","OK") -> ERROR | AN18: =IF(AND(I18>0,MOD(I18,1)=0),"OK","ERROR") -> OK | AO18: =IF(OR(B18="",B18<DATE(2024,10,1),B18>DATE(2024,12,31)),"ERROR","OK") -> OK | AP18: =IF(OR(B18<DATE(2024,10,1),B18>DATE(2024,12,31)),"ERROR","OK") -> OK | AQ18: =IF(OR(S18="Delivered",S18="Cancelled",S18="RTO",S18="In Transit"),"OK","ERROR") -> ERROR
A19: UT-100018 | B19: 45569 | C19: CUST_10017 | D19: New | E19: DRS-MAX-M | F19: Dresses | G19: Maxi Dress | H19: 2899 | I19: 1 | J19: 2899 | L19: 0 | M19: Credit Card | N19: Website | O19: Indore | P19: Madhya Pradesh | Q19: Mumbai | R19: 45579 | S19: Delivered | T19: No | W19: Not Applicable | AB19: =COUNTIF(A$2:A$347,A19) -> 1 | AC19: =LEN(S19)-LEN(TRIM(S19)) -> 0 | AD19: =LEN(E19)-LEN(SUBSTITUTE(E19,"-","")) -> 2 | AE19: =IF(I19>10,"FLAG","OK") -> OK | AF19: =IF(OR(H19<=0,H19>10000),"FLAG","OK") -> OK | AG19: =IF(OR(L19<0,L19>100),"FLAG","OK") -> OK | AI19: =IF(AG19=J19,"OK","ERROR") -> ERROR | AJ19: =IF(R19<B19,"ERROR","OK") -> OK | AK19: =IF(AND(S19="Cancelled",R19<>""),"ERROR","OK") -> OK | AL19: =IF(AND(T19="Yes",U19=""),"ERROR","OK") -> OK | AM19: =IF(V19<R19,"ERROR","OK") -> ERROR | AN19: =IF(AND(I19>0,MOD(I19,1)=0),"OK","ERROR") -> OK | AO19: =IF(OR(B19="",B19<DATE(2024,10,1),B19>DATE(2024,12,31)),"ERROR","OK") -> OK | AP19: =IF(OR(B19<DATE(2024,10,1),B19>DATE(2024,12,31)),"ERROR","OK") -> OK | AQ19: =IF(OR(S19="Delivered",S19="Cancelled",S19="RTO",S19="In Transit"),"OK","ERROR") -> OK
A20: UT-100019 | B20: 45569 | C20: CUST_10018 | D20: Returning | E20: BOT-JGR-M | F20: Bottoms | G20: Joggers | H20: 1499 | I20: 2 | J20: 2998 | L20: 0 | M20: Wallet | N20: Instagram Shop | O20: Surat | P20: Gujarat | Q20: Mumbai | R20: 45578 | S20: Delivered | T20: Yes | U20: Size Issue | V20: 45595 | W20: Processed | AB20: =COUNTIF(A$2:A$347,A20) -> 1 | AC20: =LEN(S20)-LEN(TRIM(S20)) -> 0 | AD20: =LEN(E20)-LEN(SUBSTITUTE(E20,"-","")) -> 2 | AE20: =IF(I20>10,"FLAG","OK") -> OK | AF20: =IF(OR(H20<=0,H20>10000),"FLAG","OK") -> OK | AG20: =IF(OR(L20<0,L20>100),"FLAG","OK") -> OK | AI20: =IF(AG20=J20,"OK","ERROR") -> ERROR | AJ20: =IF(R20<B20,"ERROR","OK") -> OK | AK20: =IF(AND(S20="Cancelled",R20<>""),"ERROR","OK") -> OK | AL20: =IF(AND(T20="Yes",U20=""),"ERROR","OK") -> OK | AM20: =IF(V20<R20,"ERROR","OK") -> OK | AN20: =IF(AND(I20>0,MOD(I20,1)=0),"OK","ERROR") -> OK | AO20: =IF(OR(B20="",B20<DATE(2024,10,1),B20>DATE(2024,12,31)),"ERROR","OK") -> OK | AP20: =IF(OR(B20<DATE(2024,10,1),B20>DATE(2024,12,31)),"ERROR","OK") -> OK | AQ20: =IF(OR(S20="Delivered",S20="Cancelled",S20="RTO",S20="In Transit"),"OK","ERROR") -> OK
A21: UT-100020 | B21: 45570 | C21: CUST_10019 | D21: New | E21: OUT-VST-S | F21: Outerwear | G21: Puffer Vest | H21: 3999 | I21: 1 | J21: 3999 | K21: DIWALI20 | L21: 20 | M21: COD | N21: Website | O21: Patna | P21: Bihar | Q21: Delhi | S21: RTO | T21: No | W21: Not Applicable | AB21: =COUNTIF(A$2:A$347,A21) -> 1 | AC21: =LEN(S21)-LEN(TRIM(S21)) -> 0 | AD21: =LEN(E21)-LEN(SUBSTITUTE(E21,"-","")) -> 2 | AE21: =IF(I21>10,"FLAG","OK") -> OK | AF21: =IF(OR(H21<=0,H21>10000),"FLAG","OK") -> OK | AG21: =IF(OR(L21<0,L21>100),"FLAG","OK") -> OK | AI21: =IF(AG21=J21,"OK","ERROR") -> ERROR | AJ21: =IF(R21<B21,"ERROR","OK") -> ERROR | AK21: =IF(AND(S21="Cancelled",R21<>""),"ERROR","OK") -> OK | AL21: =IF(AND(T21="Yes",U21=""),"ERROR","OK") -> OK | AM21: =IF(V21<R21,"ERROR","OK") -> OK | AN21: =IF(AND(I21>0,MOD(I21,1)=0),"OK","ERROR") -> OK | AO21: =IF(OR(B21="",B21<DATE(2024,10,1),B21>DATE(2024,12,31)),"ERROR","OK") -> OK | AP21: =IF(OR(B21<DATE(2024,10,1),B21>DATE(2024,12,31)),"ERROR","OK") -> OK | AQ21: =IF(OR(S21="Delivered",S21="Cancelled",S21="RTO",S21="In Transit"),"OK","ERROR") -> OK
A22: UT-100021 | B22: 45570 | C22: CUST_10020 | D22: New | E22: TOP-TUN-L | F22: Tops | G22: Tunic Top | H22: 1699 | I22: 1 | J22: 1699 | L22: 0 | M22: UPI | N22: Mobile App | O22: Bhopal | P22: Madhya Pradesh | Q22: Mumbai | R22: 45580 | S22: Delivered | T22: No | W22: Not Applicable | AB22: =COUNTIF(A$2:A$347,A22) -> 1 | AC22: =LEN(S22)-LEN(TRIM(S22)) -> 0 | AD22: =LEN(E22)-LEN(SUBSTITUTE(E22,"-","")) -> 2 | AE22: =IF(I22>10,"FLAG","OK") -> OK | AF22: =IF(OR(H22<=0,H22>10000),"FLAG","OK") -> OK | AG22: =IF(OR(L22<0,L22>100),"FLAG","OK") -> OK | AI22: =IF(AG22=J22,"OK","ERROR") -> ERROR | AJ22: =IF(R22<B22,"ERROR","OK") -> OK | AK22: =IF(AND(S22="Cancelled",R22<>""),"ERROR","OK") -> OK | AL22: =IF(AND(T22="Yes",U22=""),"ERROR","OK") -> OK | AM22: =IF(V22<R22,"ERROR","OK") -> ERROR | AN22: =IF(AND(I22>0,MOD(I22,1)=0),"OK","ERROR") -> OK | AO22: =IF(OR(B22="",B22<DATE(2024,10,1),B22>DATE(2024,12,31)),"ERROR","OK") -> OK | AP22: =IF(OR(B22<DATE(2024,10,1),B22>DATE(2024,12,31)),"ERROR","OK") -> OK | AQ22: =IF(OR(S22="Delivered",S22="Cancelled",S22="RTO",S22="In Transit"),"OK","ERROR") -> OK
A23: UT-100022 | B23: 45570 | C23: CUST_10021 | D23: Returning | E23: DRS-SHT-XS | F23: Dresses | G23: Shirt Dress | H23: 2399 | I23: 1 | J23: 2399 | L23: 0 | M23: Credit Card | N23: Website | O23: Nagpur | P23: Maharashtra | Q23: Mumbai | R23: 45581 | S23: Delivered | T23: Yes | U23: Quality Defect | V23: 45598 | W23: Processed | AB23: =COUNTIF(A$2:A$347,A23) -> 1 | AC23: =LEN(S23)-LEN(TRIM(S23)) -> 0 | AD23: =LEN(E23)-LEN(SUBSTITUTE(E23,"-","")) -> 2 | AE23: =IF(I23>10,"FLAG","OK") -> OK | AF23: =IF(OR(H23<=0,H23>10000),"FLAG","OK") -> OK | AG23: =IF(OR(L23<0,L23>100),"FLAG","OK") -> OK | AI23: =IF(AG23=J23,"OK","ERROR") -> ERROR | AJ23: =IF(R23<B23,"ERROR","OK") -> OK | AK23: =IF(AND(S23="Cancelled",R23<>""),"ERROR","OK") -> OK | AL23: =IF(AND(T23="Yes",U23=""),"ERROR","OK") -> OK | AM23: =IF(V23<R23,"ERROR","OK") -> OK | AN23: =IF(AND(I23>0,MOD(I23,1)=0),"OK","ERROR") -> OK | AO23: =IF(OR(B23="",B23<DATE(2024,10,1),B23>DATE(2024,12,31)),"ERROR","OK") -> OK | AP23: =IF(OR(B23<DATE(2024,10,1),B23>DATE(2024,12,31)),"ERROR","OK") -> OK | AQ23: =IF(OR(S23="Delivered",S23="Cancelled",S23="RTO",S23="In Transit"),"OK","ERROR") -> OK
A24: UT-100023 | B24: 45570 | C24: CUST_10022 | D24: New | E24: ACC-BLT-M | F24: Accessories | G24: Leather Belt | H24: 899 | I24: 1 | J24: 899 | K24: FLAT10 | L24: 10 | M24: Debit Card | N24: Mobile App | O24: Coimbatore | P24: Tamil Nadu | Q24: Bangalore | R24: 45582 | S24: Delivered | T24: No | W24: Not Applicable | AB24: =COUNTIF(A$2:A$347,A24) -> 1 | AC24: =LEN(S24)-LEN(TRIM(S24)) -> 0 | AD24: =LEN(E24)-LEN(SUBSTITUTE(E24,"-","")) -> 2 | AE24: =IF(I24>10,"FLAG","OK") -> OK | AF24: =IF(OR(H24<=0,H24>10000),"FLAG","OK") -> OK | AG24: =IF(OR(L24<0,L24>100),"FLAG","OK") -> OK | AI24: =IF(AG24=J24,"OK","ERROR") -> ERROR | AJ24: =IF(R24<B24,"ERROR","OK") -> OK | AK24: =IF(AND(S24="Cancelled",R24<>""),"ERROR","OK") -> OK | AL24: =IF(AND(T24="Yes",U24=""),"ERROR","OK") -> OK | AM24: =IF(V24<R24,"ERROR","OK") -> ERROR | AN24: =IF(AND(I24>0,MOD(I24,1)=0),"OK","ERROR") -> OK | AO24: =IF(OR(B24="",B24<DATE(2024,10,1),B24>DATE(2024,12,31)),"ERROR","OK") -> OK | AP24: =IF(OR(B24<DATE(2024,10,1),B24>DATE(2024,12,31)),"ERROR","OK") -> OK | AQ24: =IF(OR(S24="Delivered",S24="Cancelled",S24="RTO",S24="In Transit"),"OK","ERROR") -> OK
A25: UT-100024 | B25: 45571 | C25: CUST_10023 | D25: New | E25: BOT-SHT-M | F25: Bottoms | G25: Cotton Shorts | H25: 1199 | I25: 3 | J25: 3597 | L25: 0 | M25: COD | N25: Instagram Shop | O25: Kochi | P25: Kerala | Q25: Bangalore | R25: 45583 | S25: Delivered | T25: Yes | U25: Changed Mind | V25: 45601 | W25: Processed | AB25: =COUNTIF(A$2:A$347,A25) -> 1 | AC25: =LEN(S25)-LEN(TRIM(S25)) -> 0 | AD25: =LEN(E25)-LEN(SUBSTITUTE(E25,"-","")) -> 2 | AE25: =IF(I25>10,"FLAG","OK") -> OK | AF25: =IF(OR(H25<=0,H25>10000),"FLAG","OK") -> OK | AG25: =IF(OR(L25<0,L25>100),"FLAG","OK") -> OK | AI25: =IF(AG25=J25,"OK","ERROR") -> ERROR | AJ25: =IF(R25<B25,"ERROR","OK") -> OK | AK25: =IF(AND(S25="Cancelled",R25<>""),"ERROR","OK") -> OK | AL25: =IF(AND(T25="Yes",U25=""),"ERROR","OK") -> OK | AM25: =IF(V25<R25,"ERROR","OK") -> OK | AN25: =IF(AND(I25>0,MOD(I25,1)=0),"OK","ERROR") -> OK | AO25: =IF(OR(B25="",B25<DATE(2024,10,1),B25>DATE(2024,12,31)),"ERROR","OK") -> OK | AP25: =IF(OR(B25<DATE(2024,10,1),B25>DATE(2024,12,31)),"ERROR","OK") -> OK | AQ25: =IF(OR(S25="Delivered",S25="Cancelled",S25="RTO",S25="In Transit"),"OK","ERROR") -> OK
A26: UT-100025 | B26: 45571 | C26: CUST_10024 | D26: New | E26: TOP-PLO-L | F26: Tops | G26: Polo Shirt | H26: 1799 | I26: 2 | J26: 3598 | L26: 0 | M26: UPI | N26: Website | O26: Vizag | P26: Andhra Pradesh | Q26: Bangalore | R26: 45582 | S26: Delivered | T26: No | W26: Not Applicable | AB26: =COUNTIF(A$2:A$347,A26) -> 1 | AC26: =LEN(S26)-LEN(TRIM(S26)) -> 0 | AD26: =LEN(E26)-LEN(SUBSTITUTE(E26,"-","")) -> 2 | AE26: =IF(I26>10,"FLAG","OK") -> OK | AF26: =IF(OR(H26<=0,H26>10000),"FLAG","OK") -> OK | AG26: =IF(OR(L26<0,L26>100),"FLAG","OK") -> OK | AI26: =IF(AG26=J26,"OK","ERROR") -> ERROR | AJ26: =IF(R26<B26,"ERROR","OK") -> OK | AK26: =IF(AND(S26="Cancelled",R26<>""),"ERROR","OK") -> OK | AL26: =IF(AND(T26="Yes",U26=""),"ERROR","OK") -> OK | AM26: =IF(V26<R26,"ERROR","OK") -> ERROR | AN26: =IF(AND(I26>0,MOD(I26,1)=0),"OK","ERROR") -> OK | AO26: =IF(OR(B26="",B26<DATE(2024,10,1),B26>DATE(2024,12,31)),"ERROR","OK") -> OK | AP26: =IF(OR(B26<DATE(2024,10,1),B26>DATE(2024,12,31)),"ERROR","OK") -> OK | AQ26: =IF(OR(S26="Delivered",S26="Cancelled",S26="RTO",S26="In Transit"),"OK","ERROR") -> OK
A27: UT-100026 | B27: 45571 | C27: CUST_10025 | D27: New | E27: DRS-WRK-M | F27: Dresses | G27: Work Dress | H27: 2699 | I27: 1 | J27: 2699 | L27: 0 | M27: Credit Card | N27: Mobile App | O27: Thiruvananthapuram | P27: Kerala | Q27: Bangalore | R27: 45583 | S27: Delivered | T27: No | W27: Not Applicable | AB27: =COUNTIF(A$2:A$347,A27) -> 1 | AC27: =LEN(S27)-LEN(TRIM(S27)) -> 0 | AD27: =LEN(E27)-LEN(SUBSTITUTE(E27,"-","")) -> 2 | AE27: =IF(I27>10,"FLAG","OK") -> OK | AF27: =IF(OR(H27<=0,H27>10000),"FLAG","OK") -> OK | AG27: =IF(OR(L27<0,L27>100),"FLAG","OK") -> OK | AI27: =IF(AG27=J27,"OK","ERROR") -> ERROR | AJ27: =IF(R27<B27,"ERROR","OK") -> OK | AK27: =IF(AND(S27="Cancelled",R27<>""),"ERROR","OK") -> OK | AL27: =IF(AND(T27="Yes",U27=""),"ERROR","OK") -> OK | AM27: =IF(V27<R27,"ERROR","OK") -> ERROR | AN27: =IF(AND(I27>0,MOD(I27,1)=0),"OK","ERROR") -> OK | AO27: =IF(OR(B27="",B27<DATE(2024,10,1),B27>DATE(2024,12,31)),"ERROR","OK") -> OK | AP27: =IF(OR(B27<DATE(2024,10,1),B27>DATE(2024,12,31)),"ERROR","OK") -> OK | AQ27: =IF(OR(S27="Delivered",S27="Cancelled",S27="RTO",S27="In Transit"),"OK","ERROR") -> OK
A28: UT-100027 | B28: 45571 | C28: CUST_10026 | D28: Returning | E28: OUT-TRN-L | F28: Outerwear | G28: Trench Coat | H28: 4599 | I28: 1 | J28: 4599 | K28: FLAT10 | L28: 10 | M28: Debit Card | N28: Website | O28: Mysore | P28: Karnataka | Q28: Bangalore | R28: 45584 | S28: Delivered | T28: Yes | U28: Size Issue | V28: 45604 | W28: Processed | AB28: =COUNTIF(A$2:A$347,A28) -> 1 | AC28: =LEN(S28)-LEN(TRIM(S28)) -> 0 | AD28: =LEN(E28)-LEN(SUBSTITUTE(E28,"-","")) -> 2 | AE28: =IF(I28>10,"FLAG","OK") -> OK | AF28: =IF(OR(H28<=0,H28>10000),"FLAG","OK") -> OK | AG28: =IF(OR(L28<0,L28>100),"FLAG","OK") -> OK | AI28: =IF(AG28=J28,"OK","ERROR") -> ERROR | AJ28: =IF(R28<B28,"ERROR","OK") -> OK | AK28: =IF(AND(S28="Cancelled",R28<>""),"ERROR","OK") -> OK | AL28: =IF(AND(T28="Yes",U28=""),"ERROR","OK") -> OK | AM28: =IF(V28<R28,"ERROR","OK") -> OK | AN28: =IF(AND(I28>0,MOD(I28,1)=0),"OK","ERROR") -> OK | AO28: =IF(OR(B28="",B28<DATE(2024,10,1),B28>DATE(2024,12,31)),"ERROR","OK") -> OK | AP28: =IF(OR(B28<DATE(2024,10,1),B28>DATE(2024,12,31)),"ERROR","OK") -> OK | AQ28: =IF(OR(S28="Delivered",S28="Cancelled",S28="RTO",S28="In Transit"),"OK","ERROR") -> OK
A29: UT-100028 | B29: 45572 | C29: CUST_10027 | D29: New | E29: ACC-HAT-OS | F29: Accessories | G29: Fedora Hat | H29: 1099 | I29: 1 | J29: 1099 | L29: 0 | M29: UPI | N29: Instagram Shop | O29: Vadodara | P29: Gujarat | Q29: Mumbai | R29: 45585 | S29: Delivered | T29: No | W29: Not Applicable | AB29: =COUNTIF(A$2:A$347,A29) -> 1 | AC29: =LEN(S29)-LEN(TRIM(S29)) -> 0 | AD29: =LEN(E29)-LEN(SUBSTITUTE(E29,"-","")) -> 2 | AE29: =IF(I29>10,"FLAG","OK") -> OK | AF29: =IF(OR(H29<=0,H29>10000),"FLAG","OK") -> OK | AG29: =IF(OR(L29<0,L29>100),"FLAG","OK") -> OK | AI29: =IF(AG29=J29,"OK","ERROR") -> ERROR | AJ29: =IF(R29<B29,"ERROR","OK") -> OK | AK29: =IF(AND(S29="Cancelled",R29<>""),"ERROR","OK") -> OK | AL29: =IF(AND(T29="Yes",U29=""),"ERROR","OK") -> OK | AM29: =IF(V29<R29,"ERROR","OK") -> ERROR | AN29: =IF(AND(I29>0,MOD(I29,1)=0),"OK","ERROR") -> OK | AO29: =IF(OR(B29="",B29<DATE(2024,10,1),B29>DATE(2024,12,31)),"ERROR","OK") -> OK | AP29: =IF(OR(B29<DATE(2024,10,1),B29>DATE(2024,12,31)),"ERROR","OK") -> OK | AQ29: =IF(OR(S29="Delivered",S29="Cancelled",S29="RTO",S29="In Transit"),"OK","ERROR") -> OK
A30: UT-100029 | B30: 45572 | C30: CUST_10028 | D30: New | E30: TOP-DNM-M | F30: Tops | G30: Denim Shirt | H30: 1899 | I30: 1 | J30: 1899 | L30: 0 | M30: COD | N30: Mobile App | O30: Rajkot | P30: Gujarat | Q30: Mumbai | S30: RTO | T30: No | W30: Not Applicable | AB30: =COUNTIF(A$2:A$347,A30) -> 1 | AC30: =LEN(S30)-LEN(TRIM(S30)) -> 0 | AD30: =LEN(E30)-LEN(SUBSTITUTE(E30,"-","")) -> 2 | AE30: =IF(I30>10,"FLAG","OK") -> OK | AF30: =IF(OR(H30<=0,H30>10000),"FLAG","OK") -> OK | AG30: =IF(OR(L30<0,L30>100),"FLAG","OK") -> OK | AI30: =IF(AG30=J30,"OK","ERROR") -> ERROR | AJ30: =IF(R30<B30,"ERROR","OK") -> ERROR | AK30: =IF(AND(S30="Cancelled",R30<>""),"ERROR","OK") -> OK | AL30: =IF(AND(T30="Yes",U30=""),"ERROR","OK") -> OK | AM30: =IF(V30<R30,"ERROR","OK") -> OK | AN30: =IF(AND(I30>0,MOD(I30,1)=0),"OK","ERROR") -> OK | AO30: =IF(OR(B30="",B30<DATE(2024,10,1),B30>DATE(2024,12,31)),"ERROR","OK") -> OK | AP30: =IF(OR(B30<DATE(2024,10,1),B30>DATE(2024,12,31)),"ERROR","OK") -> OK | AQ30: =IF(OR(S30="Delivered",S30="Cancelled",S30="RTO",S30="In Transit"),"OK","ERROR") -> OK
A31: UT-100030 | B31: 45572 | C31: CUST_10029 | D31: New | E31: BOT-CRG-L | F31: Bottoms | G31: Cargo Pants | H31: 2199 | I31: 1 | J31: 2199 | K31: DIWALI20 | L31: 20 | M31: Credit Card | N31: Website | O31: Kanpur | P31: Uttar Pradesh | Q31: Delhi | R31: 45585 | S31: Delivered | T31: No | W31: Not Applicable | AB31: =COUNTIF(A$2:A$347,A31) -> 1 | AC31: =LEN(S31)-LEN(TRIM(S31)) -> 0 | AD31: =LEN(E31)-LEN(SUBSTITUTE(E31,"-","")) -> 2 | AE31: =IF(I31>10,"FLAG","OK") -> OK | AF31: =IF(OR(H31<=0,H31>10000),"FLAG","OK") -> OK | AG31: =IF(OR(L31<0,L31>100),"FLAG","OK") -> OK | AI31: =IF(AG31=J31,"OK","ERROR") -> ERROR | AJ31: =IF(R31<B31,"ERROR","OK") -> OK | AK31: =IF(AND(S31="Cancelled",R31<>""),"ERROR","OK") -> OK | AL31: =IF(AND(T31="Yes",U31=""),"ERROR","OK") -> OK | AM31: =IF(V31<R31,"ERROR","OK") -> ERROR | AN31: =IF(AND(I31>0,MOD(I31,1)=0),"OK","ERROR") -> OK | AO31: =IF(OR(B31="",B31<DATE(2024,10,1),B31>DATE(2024,12,31)),"ERROR","OK") -> OK | AP31: =IF(OR(B31<DATE(2024,10,1),B31>DATE(2024,12,31)),"ERROR","OK") -> OK | AQ31: =IF(OR(S31="Delivered",S31="Cancelled",S31="RTO",S31="In Transit"),"OK","ERROR") -> OK
A32: UT-100031 | B32: 45572 | C32: CUST_10030 | D32: Returning | E32: DRS-EVE-S | F32: Dresses | G32: Evening Gown | H32: 5499 | I32: 1 | J32: 5499 | L32: 0 | M32: Credit Card | N32: Mobile App | O32: Mumbai | P32: Maharashtra | Q32: Mumbai | R32: 45586 | S32: Delivered | T32: Yes | U32: Size Issue | V32: 45606 | W32: Processed | AB32: =COUNTIF(A$2:A$347,A32) -> 1 | AC32: =LEN(S32)-LEN(TRIM(S32)) -> 0 | AD32: =LEN(E32)-LEN(SUBSTITUTE(E32,"-","")) -> 2 | AE32: =IF(I32>10,"FLAG","OK") -> OK | AF32: =IF(OR(H32<=0,H32>10000),"FLAG","OK") -> OK | AG32: =IF(OR(L32<0,L32>100),"FLAG","OK") -> OK | AI32: =IF(AG32=J32,"OK","ERROR") -> ERROR | AJ32: =IF(R32<B32,"ERROR","OK") -> OK | AK32: =IF(AND(S32="Cancelled",R32<>""),"ERROR","OK") -> OK | AL32: =IF(AND(T32="Yes",U32=""),"ERROR","OK") -> OK | AM32: =IF(V32<R32,"ERROR","OK") -> OK | AN32: =IF(AND(I32>0,MOD(I32,1)=0),"OK","ERROR") -> OK | AO32: =IF(OR(B32="",B32<DATE(2024,10,1),B32>DATE(2024,12,31)),"ERROR","OK") -> OK | AP32: =IF(OR(B32<DATE(2024,10,1),B32>DATE(2024,12,31)),"ERROR","OK") -> OK | AQ32: =IF(OR(S32="Delivered",S32="Cancelled",S32="RTO",S32="In Transit"),"OK","ERROR") -> OK
A33: UT-100032 | B33: 45573 | C33: CUST_10031 | D33: New | E33: TOP-BAS-M | F33: Tops | G33: Basic Tank | H33: 899 | I33: 2 | J33: 1798 | L33: 0 | M33: UPI | N33: Website | O33: Delhi | P33: Delhi | Q33: Delhi | R33: 45579 | S33: Delivered | T33: No | W33: Not Applicable | AB33: =COUNTIF(A$2:A$347,A33) -> 1 | AC33: =LEN(S33)-LEN(TRIM(S33)) -> 0 | AD33: =LEN(E33)-LEN(SUBSTITUTE(E33,"-","")) -> 2 | AE33: =IF(I33>10,"FLAG","OK") -> OK | AF33: =IF(OR(H33<=0,H33>10000),"FLAG","OK") -> OK | AG33: =IF(OR(L33<0,L33>100),"FLAG","OK") -> OK | AI33: =IF(AG33=J33,"OK","ERROR") -> ERROR | AJ33: =IF(R33<B33,"ERROR","OK") -> OK | AK33: =IF(AND(S33="Cancelled",R33<>""),"ERROR","OK") -> OK | AL33: =IF(AND(T33="Yes",U33=""),"ERROR","OK") -> OK | AM33: =IF(V33<R33,"ERROR","OK") -> ERROR | AN33: =IF(AND(I33>0,MOD(I33,1)=0),"OK","ERROR") -> OK | AO33: =IF(OR(B33="",B33<DATE(2024,10,1),B33>DATE(2024,12,31)),"ERROR","OK") -> OK | AP33: =IF(OR(B33<DATE(2024,10,1),B33>DATE(2024,12,31)),"ERROR","OK") -> OK | AQ33: =IF(OR(S33="Delivered",S33="Cancelled",S33="RTO",S33="In Transit"),"OK","ERROR") -> OK
A34: UT-100033 | B34: 45573 | C34: CUST_10032 | D34: New | E34: OUT-WOL-L | F34: Outerwear | G34: Wool Coat | H34: 6999 | I34: 1 | J34: 6999 | K34: FIRST15 | L34: 15 | M34: Debit Card | N34: Instagram Shop | O34: Kolkata | P34: West Bengal | Q34: Delhi | R34: 45581 | S34: Delivered | T34: Yes | U34: Quality Defect | V34: 45601 | W34: Processed | AB34: =COUNTIF(A$2:A$347,A34) -> 1 | AC34: =LEN(S34)-LEN(TRIM(S34)) -> 0 | AD34: =LEN(E34)-LEN(SUBSTITUTE(E34,"-","")) -> 2 | AE34: =IF(I34>10,"FLAG","OK") -> OK | AF34: =IF(OR(H34<=0,H34>10000),"FLAG","OK") -> OK | AG34: =IF(OR(L34<0,L34>100),"FLAG","OK") -> OK | AI34: =IF(AG34=J34,"OK","ERROR") -> ERROR | AJ34: =IF(R34<B34,"ERROR","OK") -> OK | AK34: =IF(AND(S34="Cancelled",R34<>""),"ERROR","OK") -> OK | AL34: =IF(AND(T34="Yes",U34=""),"ERROR","OK") -> OK | AM34: =IF(V34<R34,"ERROR","OK") -> OK | AN34: =IF(AND(I34>0,MOD(I34,1)=0),"OK","ERROR") -> OK | AO34: =IF(OR(B34="",B34<DATE(2024,10,1),B34>DATE(2024,12,31)),"ERROR","OK") -> OK | AP34: =IF(OR(B34<DATE(2024,10,1),B34>DATE(2024,12,31)),"ERROR","OK") -> OK | AQ34: =IF(OR(S34="Delivered",S34="Cancelled",S34="RTO",S34="In Transit"),"OK","ERROR") -> OK
A35: UT-100034 | B35: 45573 | C35: CUST_10033 | D35: Returning | E35: ACC-WCH-OS | F35: Accessories | G35: Fashion Watch | H35: 2999 | I35: 1 | J35: 2999 | L35: 0 | M35: Credit Card | N35: Mobile App | O35: Chennai | P35: Tamil Nadu | Q35: Bangalore | R35: 45580 | S35: Delivered | T35: No | W35: Not Applicable | AB35: =COUNTIF(A$2:A$347,A35) -> 1 | AC35: =LEN(S35)-LEN(TRIM(S35)) -> 0 | AD35: =LEN(E35)-LEN(SUBSTITUTE(E35,"-","")) -> 2 | AE35: =IF(I35>10,"FLAG","OK") -> OK | AF35: =IF(OR(H35<=0,H35>10000),"FLAG","OK") -> OK | AG35: =IF(OR(L35<0,L35>100),"FLAG","OK") -> OK | AI35: =IF(AG35=J35,"OK","ERROR") -> ERROR | AJ35: =IF(R35<B35,"ERROR","OK") -> OK | AK35: =IF(AND(S35="Cancelled",R35<>""),"ERROR","OK") -> OK | AL35: =IF(AND(T35="Yes",U35=""),"ERROR","OK") -> OK | AM35: =IF(V35<R35,"ERROR","OK") -> ERROR | AN35: =IF(AND(I35>0,MOD(I35,1)=0),"OK","ERROR") -> OK | AO35: =IF(OR(B35="",B35<DATE(2024,10,1),B35>DATE(2024,12,31)),"ERROR","OK") -> OK | AP35: =IF(OR(B35<DATE(2024,10,1),B35>DATE(2024,12,31)),"ERROR","OK") -> OK | AQ35: =IF(OR(S35="Delivered",S35="Cancelled",S35="RTO",S35="In Transit"),"OK","ERROR") -> OK
A36: UT-100035 | B36: 45573 | C36: CUST_10034 | D36: New | E36: BOT-DNM-S | F36: Bottoms | G36: Denim Shorts | H36: 1599 | I36: 1 | J36: 1599 | L36: 0 | M36: COD | N36: Website | O36: Hyderabad | P36: Telangana | Q36: Bangalore | R36: 45582 | S36: Delivered | T36: Yes | U36: Size Issue | V36: 45604 | W36: Processed | AB36: =COUNTIF(A$2:A$347,A36) -> 1 | AC36: =LEN(S36)-LEN(TRIM(S36)) -> 0 | AD36: =LEN(E36)-LEN(SUBSTITUTE(E36,"-","")) -> 2 | AE36: =IF(I36>10,"FLAG","OK") -> OK | AF36: =IF(OR(H36<=0,H36>10000),"FLAG","OK") -> OK | AG36: =IF(OR(L36<0,L36>100),"FLAG","OK") -> OK | AI36: =IF(AG36=J36,"OK","ERROR") -> ERROR | AJ36: =IF(R36<B36,"ERROR","OK") -> OK | AK36: =IF(AND(S36="Cancelled",R36<>""),"ERROR","OK") -> OK | AL36: =IF(AND(T36="Yes",U36=""),"ERROR","OK") -> OK | AM36: =IF(V36<R36,"ERROR","OK") -> OK | AN36: =IF(AND(I36>0,MOD(I36,1)=0),"OK","ERROR") -> OK | AO36: =IF(OR(B36="",B36<DATE(2024,10,1),B36>DATE(2024,12,31)),"ERROR","OK") -> OK | AP36: =IF(OR(B36<DATE(2024,10,1),B36>DATE(2024,12,31)),"ERROR","OK") -> OK | AQ36: =IF(OR(S36="Delivered",S36="Cancelled",S36="RTO",S36="In Transit"),"OK","ERROR") -> OK
A37: UT-100036 | B37: 45574 | C37: CUST_10035 | D37: New | E37: DRS-SUN-M | F37: Dresses | G37: Sundress | H37: 1999 | I37: 1 | J37: 1999 | K37: DIWALI20 | L37: 20 | M37: Wallet | N37: Mobile App | O37: Pune | P37: Maharashtra | Q37: Mumbai | R37: 45581 | S37: Delivered | T37: No | W37: Not Applicable | AB37: =COUNTIF(A$2:A$347,A37) -> 1 | AC37: =LEN(S37)-LEN(TRIM(S37)) -> 0 | AD37: =LEN(E37)-LEN(SUBSTITUTE(E37,"-","")) -> 2 | AE37: =IF(I37>10,"FLAG","OK") -> OK | AF37: =IF(OR(H37<=0,H37>10000),"FLAG","OK") -> OK | AG37: =IF(OR(L37<0,L37>100),"FLAG","OK") -> OK | AI37: =IF(AG37=J37,"OK","ERROR") -> ERROR | AJ37: =IF(R37<B37,"ERROR","OK") -> OK | AK37: =IF(AND(S37="Cancelled",R37<>""),"ERROR","OK") -> OK | AL37: =IF(AND(T37="Yes",U37=""),"ERROR","OK") -> OK | AM37: =IF(V37<R37,"ERROR","OK") -> ERROR | AN37: =IF(AND(I37>0,MOD(I37,1)=0),"OK","ERROR") -> OK | AO37: =IF(OR(B37="",B37<DATE(2024,10,1),B37>DATE(2024,12,31)),"ERROR","OK") -> OK | AP37: =IF(OR(B37<DATE(2024,10,1),B37>DATE(2024,12,31)),"ERROR","OK") -> OK | AQ37: =IF(OR(S37="Delivered",S37="Cancelled",S37="RTO",S37="In Transit"),"OK","ERROR") -> OK
A38: UT-100037 | B38: 45574 | C38: CUST_10036 | D38: New | E38: TOP-RFL-S | F38: Tops | G38: Ruffle Top | H38: 1799 | I38: 1 | J38: 1799 | L38: 0 | M38: UPI | N38: Instagram Shop | O38: Ahmedabad | P38: Gujarat | Q38: Mumbai | R38: 45582 | S38: Delivered | T38: Yes | U38: Changed Mind | V38: 45608 | W38: Processed | AB38: =COUNTIF(A$2:A$347,A38) -> 1 | AC38: =LEN(S38)-LEN(TRIM(S38)) -> 0 | AD38: =LEN(E38)-LEN(SUBSTITUTE(E38,"-","")) -> 2 | AE38: =IF(I38>10,"FLAG","OK") -> OK | AF38: =IF(OR(H38<=0,H38>10000),"FLAG","OK") -> OK | AG38: =IF(OR(L38<0,L38>100),"FLAG","OK") -> OK | AI38: =IF(AG38=J38,"OK","ERROR") -> ERROR | AJ38: =IF(R38<B38,"ERROR","OK") -> OK | AK38: =IF(AND(S38="Cancelled",R38<>""),"ERROR","OK") -> OK | AL38: =IF(AND(T38="Yes",U38=""),"ERROR","OK") -> OK | AM38: =IF(V38<R38,"ERROR","OK") -> OK | AN38: =IF(AND(I38>0,MOD(I38,1)=0),"OK","ERROR") -> OK | AO38: =IF(OR(B38="",B38<DATE(2024,10,1),B38>DATE(2024,12,31)),"ERROR","OK") -> OK | AP38: =IF(OR(B38<DATE(2024,10,1),B38>DATE(2024,12,31)),"ERROR","OK") -> OK | AQ38: =IF(OR(S38="Delivered",S38="Cancelled",S38="RTO",S38="In Transit"),"OK","ERROR") -> OK
A39: UT-100038 | B39: 45574 | C39: CUST_10037 | D39: Returning | E39: OUT-LTH-M | F39: Outerwear | G39: Leather Jacket | H39: 7999 | I39: 1 | J39: 7999 | L39: 0 | M39: Credit Card | N39: Website | O39: Jaipur | P39: Rajasthan | Q39: Delhi | R39: 45583 | S39: Delivered | T39: No | W39: Not Applicable | AB39: =COUNTIF(A$2:A$347,A39) -> 1 | AC39: =LEN(S39)-LEN(TRIM(S39)) -> 0 | AD39: =LEN(E39)-LEN(SUBSTITUTE(E39,"-","")) -> 2 | AE39: =IF(I39>10,"FLAG","OK") -> OK | AF39: =IF(OR(H39<=0,H39>10000),"FLAG","OK") -> OK | AG39: =IF(OR(L39<0,L39>100),"FLAG","OK") -> OK | AI39: =IF(AG39=J39,"OK","ERROR") -> ERROR | AJ39: =IF(R39<B39,"ERROR","OK") -> OK | AK39: =IF(AND(S39="Cancelled",R39<>""),"ERROR","OK") -> OK | AL39: =IF(AND(T39="Yes",U39=""),"ERROR","OK") -> OK | AM39: =IF(V39<R39,"ERROR","OK") -> ERROR | AN39: =IF(AND(I39>0,MOD(I39,1)=0),"OK","ERROR") -> OK | AO39: =IF(OR(B39="",B39<DATE(2024,10,1),B39>DATE(2024,12,31)),"ERROR","OK") -> OK | AP39: =IF(OR(B39<DATE(2024,10,1),B39>DATE(2024,12,31)),"ERROR","OK") -> OK | AQ39: =IF(OR(S39="Delivered",S39="Cancelled",S39="RTO",S39="In Transit"),"OK","ERROR") -> OK
A40: UT-100039 | B40: 45574 | C40: CUST_10038 | D40: New | E40: ACC-SNG-OS | F40: Accessories | G40: Sunglasses | H40: 1499 | I40: 1 | J40: 1499 | K40: FLAT10 | L40: 10 | M40: Debit Card | N40: Mobile App | O40: Lucknow | P40: Uttar Pradesh | Q40: Delhi | R40: 45582 | S40: Delivered | T40: No | W40: Not Applicable | AB40: =COUNTIF(A$2:A$347,A40) -> 1 | AC40: =LEN(S40)-LEN(TRIM(S40)) -> 0 | AD40: =LEN(E40)-LEN(SUBSTITUTE(E40,"-","")) -> 2 | AE40: =IF(I40>10,"FLAG","OK") -> OK | AF40: =IF(OR(H40<=0,H40>10000),"FLAG","OK") -> OK | AG40: =IF(OR(L40<0,L40>100),"FLAG","OK") -> OK | AI40: =IF(AG40=J40,"OK","ERROR") -> ERROR | AJ40: =IF(R40<B40,"ERROR","OK") -> OK | AK40: =IF(AND(S40="Cancelled",R40<>""),"ERROR","OK") -> OK | AL40: =IF(AND(T40="Yes",U40=""),"ERROR","OK") -> OK | AM40: =IF(V40<R40,"ERROR","OK") -> ERROR | AN40: =IF(AND(I40>0,MOD(I40,1)=0),"OK","ERROR") -> OK | AO40: =IF(OR(B40="",B40<DATE(2024,10,1),B40>DATE(2024,12,31)),"ERROR","OK") -> OK | AP40: =IF(OR(B40<DATE(2024,10,1),B40>DATE(2024,12,31)),"ERROR","OK") -> OK | AQ40: =IF(OR(S40="Delivered",S40="Cancelled",S40="RTO",S40="In Transit"),"OK","ERROR") -> OK
A41: UT-100040 | B41: 45575 | C41: CUST_10039 | D41: New | E41: BOT-PLZ-L | F41: Bottoms | G41: Palazzo Pants | H41: 1699 | I41: 1 | J41: 1699 | L41: 0 | M41: COD | N41: Website | O41: Bangalore | P41: Karnataka | Q41: Bangalore | R41: 45584 | S41: Delivered | T41: Yes | U41: Size Issue | V41: 45606 | W41: Processed | AB41: =COUNTIF(A$2:A$347,A41) -> 1 | AC41: =LEN(S41)-LEN(TRIM(S41)) -> 0 | AD41: =LEN(E41)-LEN(SUBSTITUTE(E41,"-","")) -> 2 | AE41: =IF(I41>10,"FLAG","OK") -> OK | AF41: =IF(OR(H41<=0,H41>10000),"FLAG","OK") -> OK | AG41: =IF(OR(L41<0,L41>100),"FLAG","OK") -> OK | AI41: =IF(AG41=J41,"OK","ERROR") -> ERROR | AJ41: =IF(R41<B41,"ERROR","OK") -> OK | AK41: =IF(AND(S41="Cancelled",R41<>""),"ERROR","OK") -> OK | AL41: =IF(AND(T41="Yes",U41=""),"ERROR","OK") -> OK | AM41: =IF(V41<R41,"ERROR","OK") -> OK | AN41: =IF(AND(I41>0,MOD(I41,1)=0),"OK","ERROR") -> OK | AO41: =IF(OR(B41="",B41<DATE(2024,10,1),B41>DATE(2024,12,31)),"ERROR","OK") -> OK | AP41: =IF(OR(B41<DATE(2024,10,1),B41>DATE(2024,12,31)),"ERROR","OK") -> OK | AQ41: =IF(OR(S41="Delivered",S41="Cancelled",S41="RTO",S41="In Transit"),"OK","ERROR") -> OK
A42: UT-100041 | B42: 45575 | C42: CUST_10040 | D42: New | E42: DRS-BDC-S | F42: Dresses | G42: Bodycon Dress | H42: 2299 | I42: 1 | J42: 2299 | L42: 0 | M42: UPI | N42: Instagram Shop | O42: Mumbai | P42: Maharashtra | Q42: Mumbai | R42: 45583 | S42: Delivered | T42: No | W42: Not Applicable | AB42: =COUNTIF(A$2:A$347,A42) -> 1 | AC42: =LEN(S42)-LEN(TRIM(S42)) -> 0 | AD42: =LEN(E42)-LEN(SUBSTITUTE(E42,"-","")) -> 2 | AE42: =IF(I42>10,"FLAG","OK") -> OK | AF42: =IF(OR(H42<=0,H42>10000),"FLAG","OK") -> OK | AG42: =IF(OR(L42<0,L42>100),"FLAG","OK") -> OK | AI42: =IF(AG42=J42,"OK","ERROR") -> ERROR | AJ42: =IF(R42<B42,"ERROR","OK") -> OK | AK42: =IF(AND(S42="Cancelled",R42<>""),"ERROR","OK") -> OK | AL42: =IF(AND(T42="Yes",U42=""),"ERROR","OK") -> OK | AM42: =IF(V42<R42,"ERROR","OK") -> ERROR | AN42: =IF(AND(I42>0,MOD(I42,1)=0),"OK","ERROR") -> OK | AO42: =IF(OR(B42="",B42<DATE(2024,10,1),B42>DATE(2024,12,31)),"ERROR","OK") -> OK | AP42: =IF(OR(B42<DATE(2024,10,1),B42>DATE(2024,12,31)),"ERROR","OK") -> OK | AQ42: =IF(OR(S42="Delivered",S42="Cancelled",S42="RTO",S42="In Transit"),"OK","ERROR") -> OK
A43: UT-100042 | B43: 45575 | C43: CUST_10041 | D43: Returning | E43: TOP-OFF-M | F43: Tops | G43: Off-Shoulder Top | H43: 1599 | I43: 2 | J43: 3198 | K43: DIWALI20 | L43: 20 | M43: Credit Card | N43: Mobile App | O43: Delhi | P43: Delhi | Q43: Delhi | R43: 45582 | S43: Delivered | T43: Yes | U43: Wrong Item | V43: 45604 | W43: Processed | AB43: =COUNTIF(A$2:A$347,A43) -> 1 | AC43: =LEN(S43)-LEN(TRIM(S43)) -> 0 | AD43: =LEN(E43)-LEN(SUBSTITUTE(E43,"-","")) -> 2 | AE43: =IF(I43>10,"FLAG","OK") -> OK | AF43: =IF(OR(H43<=0,H43>10000),"FLAG","OK") -> OK | AG43: =IF(OR(L43<0,L43>100),"FLAG","OK") -> OK | AI43: =IF(AG43=J43,"OK","ERROR") -> ERROR | AJ43: =IF(R43<B43,"ERROR","OK") -> OK | AK43: =IF(AND(S43="Cancelled",R43<>""),"ERROR","OK") -> OK | AL43: =IF(AND(T43="Yes",U43=""),"ERROR","OK") -> OK | AM43: =IF(V43<R43,"ERROR","OK") -> OK | AN43: =IF(AND(I43>0,MOD(I43,1)=0),"OK","ERROR") -> OK | AO43: =IF(OR(B43="",B43<DATE(2024,10,1),B43>DATE(2024,12,31)),"ERROR","OK") -> OK | AP43: =IF(OR(B43<DATE(2024,10,1),B43>DATE(2024,12,31)),"ERROR","OK") -> OK | AQ43: =IF(OR(S43="Delivered",S43="Cancelled",S43="RTO",S43="In Transit"),"OK","ERROR") -> OK
A44: UT-100043 | B44: 45575 | C44: CUST_10042 | D44: New | E44: OUT-DNM-L | F44: Outerwear | G44: Denim Vest | H44: 2499 | I44: 1 | J44: 2499 | L44: 0 | M44: Wallet | N44: Website | O44: Chandigarh | P44: Punjab | Q44: Delhi | R44: 45585 | S44: Delivered | T44: No | W44: Not Applicable | AB44: =COUNTIF(A$2:A$347,A44) -> 1 | AC44: =LEN(S44)-LEN(TRIM(S44)) -> 0 | AD44: =LEN(E44)-LEN(SUBSTITUTE(E44,"-","")) -> 2 | AE44: =IF(I44>10,"FLAG","OK") -> OK | AF44: =IF(OR(H44<=0,H44>10000),"FLAG","OK") -> OK | AG44: =IF(OR(L44<0,L44>100),"FLAG","OK") -> OK | AI44: =IF(AG44=J44,"OK","ERROR") -> ERROR | AJ44: =IF(R44<B44,"ERROR","OK") -> OK | AK44: =IF(AND(S44="Cancelled",R44<>""),"ERROR","OK") -> OK | AL44: =IF(AND(T44="Yes",U44=""),"ERROR","OK") -> OK | AM44: =IF(V44<R44,"ERROR","OK") -> ERROR | AN44: =IF(AND(I44>0,MOD(I44,1)=0),"OK","ERROR") -> OK | AO44: =IF(OR(B44="",B44<DATE(2024,10,1),B44>DATE(2024,12,31)),"ERROR","OK") -> OK | AP44: =IF(OR(B44<DATE(2024,10,1),B44>DATE(2024,12,31)),"ERROR","OK") -> OK | AQ44: =IF(OR(S44="Delivered",S44="Cancelled",S44="RTO",S44="In Transit"),"OK","ERROR") -> OK
A45: UT-100044 | B45: 45576 | C45: CUST_10043 | D45: New | E45: ACC-HBG-OS | F45: Accessories | G45: Hobo Bag | H45: 1899 | I45: 1 | J45: 1899 | L45: 0 | M45: Debit Card | N45: Instagram Shop | O45: Noida | P45: Uttar Pradesh | Q45: Delhi | R45: 45586 | S45: Delivered | T45: Yes | U45: Damaged in Transit | V45: 45608 | W45: Processed | AB45: =COUNTIF(A$2:A$347,A45) -> 1 | AC45: =LEN(S45)-LEN(TRIM(S45)) -> 0 | AD45: =LEN(E45)-LEN(SUBSTITUTE(E45,"-","")) -> 2 | AE45: =IF(I45>10,"FLAG","OK") -> OK | AF45: =IF(OR(H45<=0,H45>10000),"FLAG","OK") -> OK | AG45: =IF(OR(L45<0,L45>100),"FLAG","OK") -> OK | AI45: =IF(AG45=J45,"OK","ERROR") -> ERROR | AJ45: =IF(R45<B45,"ERROR","OK") -> OK | AK45: =IF(AND(S45="Cancelled",R45<>""),"ERROR","OK") -> OK | AL45: =IF(AND(T45="Yes",U45=""),"ERROR","OK") -> OK | AM45: =IF(V45<R45,"ERROR","OK") -> OK | AN45: =IF(AND(I45>0,MOD(I45,1)=0),"OK","ERROR") -> OK | AO45: =IF(OR(B45="",B45<DATE(2024,10,1),B45>DATE(2024,12,31)),"ERROR","OK") -> OK | AP45: =IF(OR(B45<DATE(2024,10,1),B45>DATE(2024,12,31)),"ERROR","OK") -> OK | AQ45: =IF(OR(S45="Delivered",S45="Cancelled",S45="RTO",S45="In Transit"),"OK","ERROR") -> OK
A46: UT-100045 | B46: 45576 | C46: CUST_10044 | D46: New | E46: BOT-CHP-M | F46: Bottoms | G46: Chino Pants | H46: 1999 | I46: 1 | J46: 1999 | K46: FIRST15 | L46: 15 | M46: UPI | N46: Mobile App | O46: Gurgaon | P46: Haryana | Q46: Delhi | R46: 45584 | S46: Delivered | T46: No | W46: Not Applicable | AB46: =COUNTIF(A$2:A$347,A46) -> 1 | AC46: =LEN(S46)-LEN(TRIM(S46)) -> 0 | AD46: =LEN(E46)-LEN(SUBSTITUTE(E46,"-","")) -> 2 | AE46: =IF(I46>10,"FLAG","OK") -> OK | AF46: =IF(OR(H46<=0,H46>10000),"FLAG","OK") -> OK | AG46: =IF(OR(L46<0,L46>100),"FLAG","OK") -> OK | AI46: =IF(AG46=J46,"OK","ERROR") -> ERROR | AJ46: =IF(R46<B46,"ERROR","OK") -> OK | AK46: =IF(AND(S46="Cancelled",R46<>""),"ERROR","OK") -> OK | AL46: =IF(AND(T46="Yes",U46=""),"ERROR","OK") -> OK | AM46: =IF(V46<R46,"ERROR","OK") -> ERROR | AN46: =IF(AND(I46>0,MOD(I46,1)=0),"OK","ERROR") -> OK | AO46: =IF(OR(B46="",B46<DATE(2024,10,1),B46>DATE(2024,12,31)),"ERROR","OK") -> OK | AP46: =IF(OR(B46<DATE(2024,10,1),B46>DATE(2024,12,31)),"ERROR","OK") -> OK | AQ46: =IF(OR(S46="Delivered",S46="Cancelled",S46="RTO",S46="In Transit"),"OK","ERROR") -> OK
A47: UT-100046 | B47: 45576 | C47: CUST_10045 | D47: Returning | E47: DRS-WRP-M | F47: Dresses | G47: Wrap Dress | H47: 2599 | I47: 1 | J47: 2599 | L47: 0 | M47: Credit Card | N47: Website | O47: Indore | P47: Madhya Pradesh | Q47: Mumbai | R47: 45585 | S47: Delivered | T47: No | W47: Not Applicable | AB47: =COUNTIF(A$2:A$347,A47) -> 1 | AC47: =LEN(S47)-LEN(TRIM(S47)) -> 0 | AD47: =LEN(E47)-LEN(SUBSTITUTE(E47,"-","")) -> 2 | AE47: =IF(I47>10,"FLAG","OK") -> OK | AF47: =IF(OR(H47<=0,H47>10000),"FLAG","OK") -> OK | AG47: =IF(OR(L47<0,L47>100),"FLAG","OK") -> OK | AI47: =IF(AG47=J47,"OK","ERROR") -> ERROR | AJ47: =IF(R47<B47,"ERROR","OK") -> OK | AK47: =IF(AND(S47="Cancelled",R47<>""),"ERROR","OK") -> OK | AL47: =IF(AND(T47="Yes",U47=""),"ERROR","OK") -> OK | AM47: =IF(V47<R47,"ERROR","OK") -> ERROR | AN47: =IF(AND(I47>0,MOD(I47,1)=0),"OK","ERROR") -> OK | AO47: =IF(OR(B47="",B47<DATE(2024,10,1),B47>DATE(2024,12,31)),"ERROR","OK") -> OK | AP47: =IF(OR(B47<DATE(2024,10,1),B47>DATE(2024,12,31)),"ERROR","OK") -> OK | AQ47: =IF(OR(S47="Delivered",S47="Cancelled",S47="RTO",S47="In Transit"),"OK","ERROR") -> OK
A48: UT-100047 | B48: 45576 | C48: CUST_10046 | D48: New | E48: TOP-STR-S | F48: Tops | G48: Striped Tee | H48: 1299 | I48: 1 | J48: 1299 | L48: 0 | M48: COD | N48: Instagram Shop | O48: Surat | P48: Gujarat | Q48: Mumbai | S48: RTO | T48: No | W48: Not Applicable | AB48: =COUNTIF(A$2:A$347,A48) -> 1 | AC48: =LEN(S48)-LEN(TRIM(S48)) -> 0 | AD48: =LEN(E48)-LEN(SUBSTITUTE(E48,"-","")) -> 2 | AE48: =IF(I48>10,"FLAG","OK") -> OK | AF48: =IF(OR(H48<=0,H48>10000),"FLAG","OK") -> OK | AG48: =IF(OR(L48<0,L48>100),"FLAG","OK") -> OK | AI48: =IF(AG48=J48,"OK","ERROR") -> ERROR | AJ48: =IF(R48<B48,"ERROR","OK") -> ERROR | AK48: =IF(AND(S48="Cancelled",R48<>""),"ERROR","OK") -> OK | AL48: =IF(AND(T48="Yes",U48=""),"ERROR","OK") -> OK | AM48: =IF(V48<R48,"ERROR","OK") -> OK | AN48: =IF(AND(I48>0,MOD(I48,1)=0),"OK","ERROR") -> OK | AO48: =IF(OR(B48="",B48<DATE(2024,10,1),B48>DATE(2024,12,31)),"ERROR","OK") -> OK | AP48: =IF(OR(B48<DATE(2024,10,1),B48>DATE(2024,12,31)),"ERROR","OK") -> OK | AQ48: =IF(OR(S48="Delivered",S48="Cancelled",S48="RTO",S48="In Transit"),"OK","ERROR") -> OK
A49: UT-100048 | B49: 45577 | C49: CUST_10047 | D49: New | E49: OUT-PRK-XL | F49: Outerwear | G49: Parka Jacket | H49: 5999 | I49: 1 | J49: 5999 | K49: DIWALI20 | L49: 20 | M49: Credit Card | N49: Mobile App | O49: Patna | P49: Bihar | Q49: Delhi | R49: 45587 | S49: Delivered | T49: Yes | U49: Size Issue | V49: 45611 | W49: Processed | AB49: =COUNTIF(A$2:A$347,A49) -> 1 | AC49: =LEN(S49)-LEN(TRIM(S49)) -> 0 | AD49: =LEN(E49)-LEN(SUBSTITUTE(E49,"-","")) -> 2 | AE49: =IF(I49>10,"FLAG","OK") -> OK | AF49: =IF(OR(H49<=0,H49>10000),"FLAG","OK") -> OK | AG49: =IF(OR(L49<0,L49>100),"FLAG","OK") -> OK | AI49: =IF(AG49=J49,"OK","ERROR") -> ERROR | AJ49: =IF(R49<B49,"ERROR","OK") -> OK | AK49: =IF(AND(S49="Cancelled",R49<>""),"ERROR","OK") -> OK | AL49: =IF(AND(T49="Yes",U49=""),"ERROR","OK") -> OK | AM49: =IF(V49<R49,"ERROR","OK") -> OK | AN49: =IF(AND(I49>0,MOD(I49,1)=0),"OK","ERROR") -> OK | AO49: =IF(OR(B49="",B49<DATE(2024,10,1),B49>DATE(2024,12,31)),"ERROR","OK") -> OK | AP49: =IF(OR(B49<DATE(2024,10,1),B49>DATE(2024,12,31)),"ERROR","OK") -> OK | AQ49: =IF(OR(S49="Delivered",S49="Cancelled",S49="RTO",S49="In Transit"),"OK","ERROR") -> OK
A50: UT-100049 | B50: 45577 | C50: CUST_10048 | D50: New | E50: ACC-EAR-OS | F50: Accessories | G50: Hoop Earrings | H50: 799 | I50: 2 | J50: 1598 | L50: 0 | M50: UPI | N50: Website | O50: Bhopal | P50: Madhya Pradesh | Q50: Mumbai | R50: 45585 | S50: Delivered | T50: No | W50: Not Applicable | AB50: =COUNTIF(A$2:A$347,A50) -> 1 | AC50: =LEN(S50)-LEN(TRIM(S50)) -> 0 | AD50: =LEN(E50)-LEN(SUBSTITUTE(E50,"-","")) -> 2 | AE50: =IF(I50>10,"FLAG","OK") -> OK | AF50: =IF(OR(H50<=0,H50>10000),"FLAG","OK") -> OK | AG50: =IF(OR(L50<0,L50>100),"FLAG","OK") -> OK | AI50: =IF(AG50=J50,"OK","ERROR") -> ERROR | AJ50: =IF(R50<B50,"ERROR","OK") -> OK | AK50: =IF(AND(S50="Cancelled",R50<>""),"ERROR","OK") -> OK | AL50: =IF(AND(T50="Yes",U50=""),"ERROR","OK") -> OK | AM50: =IF(V50<R50,"ERROR","OK") -> ERROR | AN50: =IF(AND(I50>0,MOD(I50,1)=0),"OK","ERROR") -> OK | AO50: =IF(OR(B50="",B50<DATE(2024,10,1),B50>DATE(2024,12,31)),"ERROR","OK") -> OK | AP50: =IF(OR(B50<DATE(2024,10,1),B50>DATE(2024,12,31)),"ERROR","OK") -> OK | AQ50: =IF(OR(S50="Delivered",S50="Cancelled",S50="RTO",S50="In Transit"),"OK","ERROR") -> OK
A51: UT-100050 | B51: 45577 | C51: CUST_10049 | D51: Returning | E51: BOT-LGN-S | F51: Bottoms | G51: Leggings | H51: 999 | I51: 2 | J51: 1998 | L51: 0 | M51: Wallet | N51: Mobile App | O51: Nagpur | P51: Maharashtra | Q51: Mumbai | R51: 45584 | S51: Delivered | T51: No | W51: Not Applicable | AB51: =COUNTIF(A$2:A$347,A51) -> 1 | AC51: =LEN(S51)-LEN(TRIM(S51)) -> 0 | AD51: =LEN(E51)-LEN(SUBSTITUTE(E51,"-","")) -> 2 | AE51: =IF(I51>10,"FLAG","OK") -> OK | AF51: =IF(OR(H51<=0,H51>10000),"FLAG","OK") -> OK | AG51: =IF(OR(L51<0,L51>100),"FLAG","OK") -> OK | AI51: =IF(AG51=J51,"OK","ERROR") -> ERROR | AJ51: =IF(R51<B51,"ERROR","OK") -> OK | AK51: =IF(AND(S51="Cancelled",R51<>""),"ERROR","OK") -> OK | AL51: =IF(AND(T51="Yes",U51=""),"ERROR","OK") -> OK | AM51: =IF(V51<R51,"ERROR","OK") -> ERROR | AN51: =IF(AND(I51>0,MOD(I51,1)=0),"OK","ERROR") -> OK | AO51: =IF(OR(B51="",B51<DATE(2024,10,1),B51>DATE(2024,12,31)),"ERROR","OK") -> OK | AP51: =IF(OR(B51<DATE(2024,10,1),B51>DATE(2024,12,31)),"ERROR","OK") -> OK | AQ51: =IF(OR(S51="Delivered",S51="Cancelled",S51="RTO",S51="In Transit"),"OK","ERROR") -> OK
A52: UT-100051 | B52: 45577 | C52: CUST_10050 | D52: New | E52: DRS-CTN-L | F52: Dresses | G52: Cotton Dress | H52: 1899 | I52: 1 | J52: 1899 | L52: 0 | M52: Debit Card | N52: Instagram Shop | O52: Coimbatore | P52: Tamil Nadu | Q52: Bangalore | R52: 45587 | S52: Delivered | T52: Yes | U52: Quality Defect | V52: 45610 | W52: Processed | AB52: =COUNTIF(A$2:A$347,A52) -> 1 | AC52: =LEN(S52)-LEN(TRIM(S52)) -> 0 | AD52: =LEN(E52)-LEN(SUBSTITUTE(E52,"-","")) -> 2 | AE52: =IF(I52>10,"FLAG","OK") -> OK | AF52: =IF(OR(H52<=0,H52>10000),"FLAG","OK") -> OK | AG52: =IF(OR(L52<0,L52>100),"FLAG","OK") -> OK | AI52: =IF(AG52=J52,"OK","ERROR") -> ERROR | AJ52: =IF(R52<B52,"ERROR","OK") -> OK | AK52: =IF(AND(S52="Cancelled",R52<>""),"ERROR","OK") -> OK | AL52: =IF(AND(T52="Yes",U52=""),"ERROR","OK") -> OK | AM52: =IF(V52<R52,"ERROR","OK") -> OK | AN52: =IF(AND(I52>0,MOD(I52,1)=0),"OK","ERROR") -> OK | AO52: =IF(OR(B52="",B52<DATE(2024,10,1),B52>DATE(2024,12,31)),"ERROR","OK") -> OK | AP52: =IF(OR(B52<DATE(2024,10,1),B52>DATE(2024,12,31)),"ERROR","OK") -> OK | AQ52: =IF(OR(S52="Delivered",S52="Cancelled",S52="RTO",S52="In Transit"),"OK","ERROR") -> OK
A53: UT-100052 | B53: 45578 | C53: CUST_10051 | D53: New | E53: TOP-LCE-M | F53: Tops | G53: Lace Top | H53: 1699 | I53: 1 | J53: 1699 | K53: FLAT10 | L53: 10 | M53: Credit Card | N53: Website | O53: Kochi | P53: Kerala | Q53: Bangalore | R53: 45586 | S53: Delivered | T53: No | W53: Not Applicable | AB53: =COUNTIF(A$2:A$347,A53) -> 1 | AC53: =LEN(S53)-LEN(TRIM(S53)) -> 0 | AD53: =LEN(E53)-LEN(SUBSTITUTE(E53,"-","")) -> 2 | AE53: =IF(I53>10,"FLAG","OK") -> OK | AF53: =IF(OR(H53<=0,H53>10000),"FLAG","OK") -> OK | AG53: =IF(OR(L53<0,L53>100),"FLAG","OK") -> OK | AI53: =IF(AG53=J53,"OK","ERROR") -> ERROR | AJ53: =IF(R53<B53,"ERROR","OK") -> OK | AK53: =IF(AND(S53="Cancelled",R53<>""),"ERROR","OK") -> OK | AL53: =IF(AND(T53="Yes",U53=""),"ERROR","OK") -> OK | AM53: =IF(V53<R53,"ERROR","OK") -> ERROR | AN53: =IF(AND(I53>0,MOD(I53,1)=0),"OK","ERROR") -> OK | AO53: =IF(OR(B53="",B53<DATE(2024,10,1),B53>DATE(2024,12,31)),"ERROR","OK") -> OK | AP53: =IF(OR(B53<DATE(2024,10,1),B53>DATE(2024,12,31)),"ERROR","OK") -> OK | AQ53: =IF(OR(S53="Delivered",S53="Cancelled",S53="RTO",S53="In Transit"),"OK","ERROR") -> OK
A54: UT-100053 | B54: 45578 | C54: CUST_10052 | D54: New | E54: OUT-BOM-M | F54: Outerwear | G54: Bomber Jacket | H54: 3799 | I54: 1 | J54: 3799 | L54: 0 | M54: UPI | N54: Mobile App | O54: Vizag | P54: Andhra Pradesh | Q54: Bangalore | R54: 45588 | S54: Delivered | T54: Yes | U54: Size Issue | V54: 45614 | W54: Processed | AB54: =COUNTIF(A$2:A$347,A54) -> 1 | AC54: =LEN(S54)-LEN(TRIM(S54)) -> 0 | AD54: =LEN(E54)-LEN(SUBSTITUTE(E54,"-","")) -> 2 | AE54: =IF(I54>10,"FLAG","OK") -> OK | AF54: =IF(OR(H54<=0,H54>10000),"FLAG","OK") -> OK | AG54: =IF(OR(L54<0,L54>100),"FLAG","OK") -> OK | AI54: =IF(AG54=J54,"OK","ERROR") -> ERROR | AJ54: =IF(R54<B54,"ERROR","OK") -> OK | AK54: =IF(AND(S54="Cancelled",R54<>""),"ERROR","OK") -> OK | AL54: =IF(AND(T54="Yes",U54=""),"ERROR","OK") -> OK | AM54: =IF(V54<R54,"ERROR","OK") -> OK | AN54: =IF(AND(I54>0,MOD(I54,1)=0),"OK","ERROR") -> OK | AO54: =IF(OR(B54="",B54<DATE(2024,10,1),B54>DATE(2024,12,31)),"ERROR","OK") -> OK | AP54: =IF(OR(B54<DATE(2024,10,1),B54>DATE(2024,12,31)),"ERROR","OK") -> OK | AQ54: =IF(OR(S54="Delivered",S54="Cancelled",S54="RTO",S54="In Transit"),"OK","ERROR") -> OK
A55: UT-100054 | B55: 45578 | C55: CUST_10053 | D55: Returning | E55: ACC-NCK-OS | F55: Accessories | G55: Pendant Necklace | H55: 1299 | I55: 1 | J55: 1299 | L55: 0 | M55: COD | N55: Instagram Shop | O55: Thiruvananthapuram | P55: Kerala | Q55: Bangalore | R55: 45587 | S55: Delivered | T55: No | W55: Not Applicable | AB55: =COUNTIF(A$2:A$347,A55) -> 1 | AC55: =LEN(S55)-LEN(TRIM(S55)) -> 0 | AD55: =LEN(E55)-LEN(SUBSTITUTE(E55,"-","")) -> 2 | AE55: =IF(I55>10,"FLAG","OK") -> OK | AF55: =IF(OR(H55<=0,H55>10000),"FLAG","OK") -> OK | AG55: =IF(OR(L55<0,L55>100),"FLAG","OK") -> OK | AI55: =IF(AG55=J55,"OK","ERROR") -> ERROR | AJ55: =IF(R55<B55,"ERROR","OK") -> OK | AK55: =IF(AND(S55="Cancelled",R55<>""),"ERROR","OK") -> OK | AL55: =IF(AND(T55="Yes",U55=""),"ERROR","OK") -> OK | AM55: =IF(V55<R55,"ERROR","OK") -> ERROR | AN55: =IF(AND(I55>0,MOD(I55,1)=0),"OK","ERROR") -> OK | AO55: =IF(OR(B55="",B55<DATE(2024,10,1),B55>DATE(2024,12,31)),"ERROR","OK") -> OK | AP55: =IF(OR(B55<DATE(2024,10,1),B55>DATE(2024,12,31)),"ERROR","OK") -> OK | AQ55: =IF(OR(S55="Delivered",S55="Cancelled",S55="RTO",S55="In Transit"),"OK","ERROR") -> OK
A56: UT-100055 | B56: 45578 | C56: CUST_10054 | D56: New | E56: BOT-WID-M | F56: Bottoms | G56: Wide Leg Pants | H56: 2099 | I56: 1 | J56: 2099 | K56: DIWALI20 | L56: 20 | M56: Credit Card | N56: Website | O56: Mysore | P56: Karnataka | Q56: Bangalore | R56: 45589 | S56: Delivered | T56: No | W56: Not Applicable | AB56: =COUNTIF(A$2:A$347,A56) -> 1 | AC56: =LEN(S56)-LEN(TRIM(S56)) -> 0 | AD56: =LEN(E56)-LEN(SUBSTITUTE(E56,"-","")) -> 2 | AE56: =IF(I56>10,"FLAG","OK") -> OK | AF56: =IF(OR(H56<=0,H56>10000),"FLAG","OK") -> OK | AG56: =IF(OR(L56<0,L56>100),"FLAG","OK") -> OK | AI56: =IF(AG56=J56,"OK","ERROR") -> ERROR | AJ56: =IF(R56<B56,"ERROR","OK") -> OK | AK56: =IF(AND(S56="Cancelled",R56<>""),"ERROR","OK") -> OK | AL56: =IF(AND(T56="Yes",U56=""),"ERROR","OK") -> OK | AM56: =IF(V56<R56,"ERROR","OK") -> ERROR | AN56: =IF(AND(I56>0,MOD(I56,1)=0),"OK","ERROR") -> OK | AO56: =IF(OR(B56="",B56<DATE(2024,10,1),B56>DATE(2024,12,31)),"ERROR","OK") -> OK | AP56: =IF(OR(B56<DATE(2024,10,1),B56>DATE(2024,12,31)),"ERROR","OK") -> OK | AQ56: =IF(OR(S56="Delivered",S56="Cancelled",S56="RTO",S56="In Transit"),"OK","ERROR") -> OK
A57: UT-100056 | B57: 45579 | C57: CUST_10055 | D57: New | E57: DRS-TIR-S | F57: Dresses | G57: Tiered Dress | H57: 2799 | I57: 1 | J57: 2799 | L57: 0 | M57: Debit Card | N57: Mobile App | O57: Vadodara | P57: Gujarat | Q57: Mumbai | R57: 45588 | S57: Delivered | T57: Yes | U57: Changed Mind | V57: 45612 | W57: Processed | AB57: =COUNTIF(A$2:A$347,A57) -> 1 | AC57: =LEN(S57)-LEN(TRIM(S57)) -> 0 | AD57: =LEN(E57)-LEN(SUBSTITUTE(E57,"-","")) -> 2 | AE57: =IF(I57>10,"FLAG","OK") -> OK | AF57: =IF(OR(H57<=0,H57>10000),"FLAG","OK") -> OK | AG57: =IF(OR(L57<0,L57>100),"FLAG","OK") -> OK | AI57: =IF(AG57=J57,"OK","ERROR") -> ERROR | AJ57: =IF(R57<B57,"ERROR","OK") -> OK | AK57: =IF(AND(S57="Cancelled",R57<>""),"ERROR","OK") -> OK | AL57: =IF(AND(T57="Yes",U57=""),"ERROR","OK") -> OK | AM57: =IF(V57<R57,"ERROR","OK") -> OK | AN57: =IF(AND(I57>0,MOD(I57,1)=0),"OK","ERROR") -> OK | AO57: =IF(OR(B57="",B57<DATE(2024,10,1),B57>DATE(2024,12,31)),"ERROR","OK") -> OK | AP57: =IF(OR(B57<DATE(2024,10,1),B57>DATE(2024,12,31)),"ERROR","OK") -> OK | AQ57: =IF(OR(S57="Delivered",S57="Cancelled",S57="RTO",S57="In Transit"),"OK","ERROR") -> OK
A58: UT-100057 | B58: 45579 | C58: CUST_10056 | D58: New | E58: TOP-PEP-M | F58: Tops | G58: Peplum Top | H58: 1499 | I58: 1 | J58: 1499 | L58: 0 | M58: Wallet | N58: Website | O58: Rajkot | P58: Gujarat | Q58: Mumbai | R58: 45587 | S58: Delivered | T58: No | W58: Not Applicable | AB58: =COUNTIF(A$2:A$347,A58) -> 1 | AC58: =LEN(S58)-LEN(TRIM(S58)) -> 0 | AD58: =LEN(E58)-LEN(SUBSTITUTE(E58,"-","")) -> 2 | AE58: =IF(I58>10,"FLAG","OK") -> OK | AF58: =IF(OR(H58<=0,H58>10000),"FLAG","OK") -> OK | AG58: =IF(OR(L58<0,L58>100),"FLAG","OK") -> OK | AI58: =IF(AG58=J58,"OK","ERROR") -> ERROR | AJ58: =IF(R58<B58,"ERROR","OK") -> OK | AK58: =IF(AND(S58="Cancelled",R58<>""),"ERROR","OK") -> OK | AL58: =IF(AND(T58="Yes",U58=""),"ERROR","OK") -> OK | AM58: =IF(V58<R58,"ERROR","OK") -> ERROR | AN58: =IF(AND(I58>0,MOD(I58,1)=0),"OK","ERROR") -> OK | AO58: =IF(OR(B58="",B58<DATE(2024,10,1),B58>DATE(2024,12,31)),"ERROR","OK") -> OK | AP58: =IF(OR(B58<DATE(2024,10,1),B58>DATE(2024,12,31)),"ERROR","OK") -> OK | AQ58: =IF(OR(S58="Delivered",S58="Cancelled",S58="RTO",S58="In Transit"),"OK","ERROR") -> OK
A59: UT-100058 | B59: 45579 | C59: CUST_10057 | D59: Returning | E59: OUT-QTD-L | F59: Outerwear | G59: Quilted Jacket | H59: 4499 | I59: 1 | J59: 4499 | K59: FIRST15 | L59: 15 | M59: UPI | N59: Instagram Shop | O59: Kanpur | P59: Uttar Pradesh | Q59: Delhi | R59: 45590 | S59: Delivered | T59: Yes | U59: Wrong Item | V59: 45616 | W59: Processed | AB59: =COUNTIF(A$2:A$347,A59) -> 1 | AC59: =LEN(S59)-LEN(TRIM(S59)) -> 0 | AD59: =LEN(E59)-LEN(SUBSTITUTE(E59,"-","")) -> 2 | AE59: =IF(I59>10,"FLAG","OK") -> OK | AF59: =IF(OR(H59<=0,H59>10000),"FLAG","OK") -> OK | AG59: =IF(OR(L59<0,L59>100),"FLAG","OK") -> OK | AI59: =IF(AG59=J59,"OK","ERROR") -> ERROR | AJ59: =IF(R59<B59,"ERROR","OK") -> OK | AK59: =IF(AND(S59="Cancelled",R59<>""),"ERROR","OK") -> OK | AL59: =IF(AND(T59="Yes",U59=""),"ERROR","OK") -> OK | AM59: =IF(V59<R59,"ERROR","OK") -> OK | AN59: =IF(AND(I59>0,MOD(I59,1)=0),"OK","ERROR") -> OK | AO59: =IF(OR(B59="",B59<DATE(2024,10,1),B59>DATE(2024,12,31)),"ERROR","OK") -> OK | AP59: =IF(OR(B59<DATE(2024,10,1),B59>DATE(2024,12,31)),"ERROR","OK") -> OK | AQ59: =IF(OR(S59="Delivered",S59="Cancelled",S59="RTO",S59="In Transit"),"OK","ERROR") -> OK
A60: UT-100059 | B60: 45579 | C60: CUST_10058 | D60: New | E60: ACC-BRC-OS | F60: Accessories | G60: Charm Bracelet | H60: 899 | I60: 1 | J60: 899 | L60: 0 | M60: Credit Card | N60: Mobile App | O60: Mumbai | P60: Maharashtra | Q60: Mumbai | R60: 45588 | S60: Delivered | T60: No | W60: Not Applicable | AB60: =COUNTIF(A$2:A$347,A60) -> 1 | AC60: =LEN(S60)-LEN(TRIM(S60)) -> 0 | AD60: =LEN(E60)-LEN(SUBSTITUTE(E60,"-","")) -> 2 | AE60: =IF(I60>10,"FLAG","OK") -> OK | AF60: =IF(OR(H60<=0,H60>10000),"FLAG","OK") -> OK | AG60: =IF(OR(L60<0,L60>100),"FLAG","OK") -> OK | AI60: =IF(AG60=J60,"OK","ERROR") -> ERROR | AJ60: =IF(R60<B60,"ERROR","OK") -> OK | AK60: =IF(AND(S60="Cancelled",R60<>""),"ERROR","OK") -> OK | AL60: =IF(AND(T60="Yes",U60=""),"ERROR","OK") -> OK | AM60: =IF(V60<R60,"ERROR","OK") -> ERROR | AN60: =IF(AND(I60>0,MOD(I60,1)=0),"OK","ERROR") -> OK | AO60: =IF(OR(B60="",B60<DATE(2024,10,1),B60>DATE(2024,12,31)),"ERROR","OK") -> OK | AP60: =IF(OR(B60<DATE(2024,10,1),B60>DATE(2024,12,31)),"ERROR","OK") -> OK | AQ60: =IF(OR(S60="Delivered",S60="Cancelled",S60="RTO",S60="In Transit"),"OK","ERROR") -> OK
A61: UT-100060 | B61: 45580 | C61: CUST_10059 | D61: New | E61: BOT-CRP-S | F61: Bottoms | G61: Cropped Pants | H61: 1799 | I61: 1 | J61: 1799 | L61: 0 | M61: COD | N61: Website | O61: Delhi | P61: Delhi | Q61: Delhi | S61: RTO | T61: No | W61: Not Applicable | AB61: =COUNTIF(A$2:A$347,A61) -> 1 | AC61: =LEN(S61)-LEN(TRIM(S61)) -> 0 | AD61: =LEN(E61)-LEN(SUBSTITUTE(E61,"-","")) -> 2 | AE61: =IF(I61>10,"FLAG","OK") -> OK | AF61: =IF(OR(H61<=0,H61>10000),"FLAG","OK") -> OK | AG61: =IF(OR(L61<0,L61>100),"FLAG","OK") -> OK | AI61: =IF(AG61=J61,"OK","ERROR") -> ERROR | AJ61: =IF(R61<B61,"ERROR","OK") -> ERROR | AK61: =IF(AND(S61="Cancelled",R61<>""),"ERROR","OK") -> OK | AL61: =IF(AND(T61="Yes",U61=""),"ERROR","OK") -> OK | AM61: =IF(V61<R61,"ERROR","OK") -> OK | AN61: =IF(AND(I61>0,MOD(I61,1)=0),"OK","ERROR") -> OK | AO61: =IF(OR(B61="",B61<DATE(2024,10,1),B61>DATE(2024,12,31)),"ERROR","OK") -> OK | AP61: =IF(OR(B61<DATE(2024,10,1),B61>DATE(2024,12,31)),"ERROR","OK") -> OK | AQ61: =IF(OR(S61="Delivered",S61="Cancelled",S61="RTO",S61="In Transit"),"OK","ERROR") -> OK
A62: UT-100061 | B62: 45580 | C62: CUST_10060 | D62: New | E62: DRS-SLP-M | F62: Dresses | G62: Slip Dress | H62: 2199 | I62: 1 | J62: 2199 | K62: DIWALI20 | L62: 20 | M62: Debit Card | N62: Instagram Shop | O62: Kolkata | P62: West Bengal | Q62: Delhi | R62: 45591 | S62: Delivered | T62: Yes | U62: Size Issue | V62: 45618 | W62: Processed | AB62: =COUNTIF(A$2:A$347,A62) -> 1 | AC62: =LEN(S62)-LEN(TRIM(S62)) -> 0 | AD62: =LEN(E62)-LEN(SUBSTITUTE(E62,"-","")) -> 2 | AE62: =IF(I62>10,"FLAG","OK") -> OK | AF62: =IF(OR(H62<=0,H62>10000),"FLAG","OK") -> OK | AG62: =IF(OR(L62<0,L62>100),"FLAG","OK") -> OK | AI62: =IF(AG62=J62,"OK","ERROR") -> ERROR | AJ62: =IF(R62<B62,"ERROR","OK") -> OK | AK62: =IF(AND(S62="Cancelled",R62<>""),"ERROR","OK") -> OK | AL62: =IF(AND(T62="Yes",U62=""),"ERROR","OK") -> OK | AM62: =IF(V62<R62,"ERROR","OK") -> OK | AN62: =IF(AND(I62>0,MOD(I62,1)=0),"OK","ERROR") -> OK | AO62: =IF(OR(B62="",B62<DATE(2024,10,1),B62>DATE(2024,12,31)),"ERROR","OK") -> OK | AP62: =IF(OR(B62<DATE(2024,10,1),B62>DATE(2024,12,31)),"ERROR","OK") -> OK | AQ62: =IF(OR(S62="Delivered",S62="Cancelled",S62="RTO",S62="In Transit"),"OK","ERROR") -> OK
A63: UT-100062 | B63: 45580 | C63: CUST_10061 | D63: Returning | E63: TOP-HLT-L | F63: Tops | G63: Halter Top | H63: 1399 | I63: 1 | J63: 1399 | L63: 0 | M63: UPI | N63: Mobile App | O63: Chennai | P63: Tamil Nadu | Q63: Bangalore | R63: 45589 | S63: Delivered | T63: No | W63: Not Applicable | AB63: =COUNTIF(A$2:A$347,A63) -> 1 | AC63: =LEN(S63)-LEN(TRIM(S63)) -> 0 | AD63: =LEN(E63)-LEN(SUBSTITUTE(E63,"-","")) -> 2 | AE63: =IF(I63>10,"FLAG","OK") -> OK | AF63: =IF(OR(H63<=0,H63>10000),"FLAG","OK") -> OK | AG63: =IF(OR(L63<0,L63>100),"FLAG","OK") -> OK | AI63: =IF(AG63=J63,"OK","ERROR") -> ERROR | AJ63: =IF(R63<B63,"ERROR","OK") -> OK | AK63: =IF(AND(S63="Cancelled",R63<>""),"ERROR","OK") -> OK | AL63: =IF(AND(T63="Yes",U63=""),"ERROR","OK") -> OK | AM63: =IF(V63<R63,"ERROR","OK") -> ERROR | AN63: =IF(AND(I63>0,MOD(I63,1)=0),"OK","ERROR") -> OK | AO63: =IF(OR(B63="",B63<DATE(2024,10,1),B63>DATE(2024,12,31)),"ERROR","OK") -> OK | AP63: =IF(OR(B63<DATE(2024,10,1),B63>DATE(2024,12,31)),"ERROR","OK") -> OK | AQ63: =IF(OR(S63="Delivered",S63="Cancelled",S63="RTO",S63="In Transit"),"OK","ERROR") -> OK
A64: UT-100063 | B64: 45580 | C64: CUST_10062 | D64: New | E64: OUT-FLC-M | F64: Outerwear | G64: Fleece Jacket | H64: 2999 | I64: 1 | J64: 2999 | L64: 0 | M64: Credit Card | N64: Website | O64: Hyderabad | P64: Telangana | Q64: Bangalore | R64: 45592 | S64: Delivered | T64: Yes | U64: Quality Defect | V64: 45620 | W64: Processed | AB64: =COUNTIF(A$2:A$347,A64) -> 1 | AC64: =LEN(S64)-LEN(TRIM(S64)) -> 0 | AD64: =LEN(E64)-LEN(SUBSTITUTE(E64,"-","")) -> 2 | AE64: =IF(I64>10,"FLAG","OK") -> OK | AF64: =IF(OR(H64<=0,H64>10000),"FLAG","OK") -> OK | AG64: =IF(OR(L64<0,L64>100),"FLAG","OK") -> OK | AI64: =IF(AG64=J64,"OK","ERROR") -> ERROR | AJ64: =IF(R64<B64,"ERROR","OK") -> OK | AK64: =IF(AND(S64="Cancelled",R64<>""),"ERROR","OK") -> OK | AL64: =IF(AND(T64="Yes",U64=""),"ERROR","OK") -> OK | AM64: =IF(V64<R64,"ERROR","OK") -> OK | AN64: =IF(AND(I64>0,MOD(I64,1)=0),"OK","ERROR") -> OK | AO64: =IF(OR(B64="",B64<DATE(2024,10,1),B64>DATE(2024,12,31)),"ERROR","OK") -> OK | AP64: =IF(OR(B64<DATE(2024,10,1),B64>DATE(2024,12,31)),"ERROR","OK") -> OK | AQ64: =IF(OR(S64="Delivered",S64="Cancelled",S64="RTO",S64="In Transit"),"OK","ERROR") -> OK
A65: UT-100064 | B65: 45581 | C65: CUST_10063 | D65: New | E65: ACC-RNG-OS | F65: Accessories | G65: Cocktail Ring | H65: 699 | I65: 2 | J65: 1398 | K65: FLAT10 | L65: 10 | M65: Wallet | N65: Instagram Shop | O65: Pune | P65: Maharashtra | Q65: Mumbai | R65: 45590 | S65: Delivered | T65: No | W65: Not Applicable | AB65: =COUNTIF(A$2:A$347,A65) -> 1 | AC65: =LEN(S65)-LEN(TRIM(S65)) -> 0 | AD65: =LEN(E65)-LEN(SUBSTITUTE(E65,"-","")) -> 2 | AE65: =IF(I65>10,"FLAG","OK") -> OK | AF65: =IF(OR(H65<=0,H65>10000),"FLAG","OK") -> OK | AG65: =IF(OR(L65<0,L65>100),"FLAG","OK") -> OK | AI65: =IF(AG65=J65,"OK","ERROR") -> ERROR | AJ65: =IF(R65<B65,"ERROR","OK") -> OK | AK65: =IF(AND(S65="Cancelled",R65<>""),"ERROR","OK") -> OK | AL65: =IF(AND(T65="Yes",U65=""),"ERROR","OK") -> OK | AM65: =IF(V65<R65,"ERROR","OK") -> ERROR | AN65: =IF(AND(I65>0,MOD(I65,1)=0),"OK","ERROR") -> OK | AO65: =IF(OR(B65="",B65<DATE(2024,10,1),B65>DATE(2024,12,31)),"ERROR","OK") -> OK | AP65: =IF(OR(B65<DATE(2024,10,1),B65>DATE(2024,12,31)),"ERROR","OK") -> OK | AQ65: =IF(OR(S65="Delivered",S65="Cancelled",S65="RTO",S65="In Transit"),"OK","ERROR") -> OK
A66: UT-100065 | B66: 45581 | C66: CUST_10064 | D66: New | E66: BOT-SKN-M | F66: Bottoms | G66: Skinny Jeans | H66: 2199 | I66: 1 | J66: 2199 | L66: 0 | M66: COD | N66: Mobile App | O66: Ahmedabad | P66: Gujarat | Q66: Mumbai | R66: 45593 | S66: Delivered | T66: Yes | U66: Size Issue | V66: 45621 | W66: Processed | AB66: =COUNTIF(A$2:A$347,A66) -> 1 | AC66: =LEN(S66)-LEN(TRIM(S66)) -> 0 | AD66: =LEN(E66)-LEN(SUBSTITUTE(E66,"-","")) -> 2 | AE66: =IF(I66>10,"FLAG","OK") -> OK | AF66: =IF(OR(H66<=0,H66>10000),"FLAG","OK") -> OK | AG66: =IF(OR(L66<0,L66>100),"FLAG","OK") -> OK | AI66: =IF(AG66=J66,"OK","ERROR") -> ERROR | AJ66: =IF(R66<B66,"ERROR","OK") -> OK | AK66: =IF(AND(S66="Cancelled",R66<>""),"ERROR","OK") -> OK | AL66: =IF(AND(T66="Yes",U66=""),"ERROR","OK") -> OK | AM66: =IF(V66<R66,"ERROR","OK") -> OK | AN66: =IF(AND(I66>0,MOD(I66,1)=0),"OK","ERROR") -> OK | AO66: =IF(OR(B66="",B66<DATE(2024,10,1),B66>DATE(2024,12,31)),"ERROR","OK") -> OK | AP66: =IF(OR(B66<DATE(2024,10,1),B66>DATE(2024,12,31)),"ERROR","OK") -> OK | AQ66: =IF(OR(S66="Delivered",S66="Cancelled",S66="RTO",S66="In Transit"),"OK","ERROR") -> OK
A67: UT-100066 | B67: 45581 | C67: CUST_10065 | D67: Returning | E67: DRS-KNT-S | F67: Dresses | G67: Knit Dress | H67: 2499 | I67: 1 | J67: 2499 | L67: 0 | M67: Credit Card | N67: Website | O67: Jaipur | P67: Rajasthan | Q67: Delhi | R67: 45591 | S67: Delivered | T67: No | W67: Not Applicable | AB67: =COUNTIF(A$2:A$347,A67) -> 1 | AC67: =LEN(S67)-LEN(TRIM(S67)) -> 0 | AD67: =LEN(E67)-LEN(SUBSTITUTE(E67,"-","")) -> 2 | AE67: =IF(I67>10,"FLAG","OK") -> OK | AF67: =IF(OR(H67<=0,H67>10000),"FLAG","OK") -> OK | AG67: =IF(OR(L67<0,L67>100),"FLAG","OK") -> OK | AI67: =IF(AG67=J67,"OK","ERROR") -> ERROR | AJ67: =IF(R67<B67,"ERROR","OK") -> OK | AK67: =IF(AND(S67="Cancelled",R67<>""),"ERROR","OK") -> OK | AL67: =IF(AND(T67="Yes",U67=""),"ERROR","OK") -> OK | AM67: =IF(V67<R67,"ERROR","OK") -> ERROR | AN67: =IF(AND(I67>0,MOD(I67,1)=0),"OK","ERROR") -> OK | AO67: =IF(OR(B67="",B67<DATE(2024,10,1),B67>DATE(2024,12,31)),"ERROR","OK") -> OK | AP67: =IF(OR(B67<DATE(2024,10,1),B67>DATE(2024,12,31)),"ERROR","OK") -> OK | AQ67: =IF(OR(S67="Delivered",S67="Cancelled",S67="RTO",S67="In Transit"),"OK","ERROR") -> OK
A68: UT-100067 | B68: 45581 | C68: CUST_10066 | D68: New | E68: TOP-EMB-M | F68: Tops | G68: Embroidered Top | H68: 1899 | I68: 1 | J68: 1899 | K68: DIWALI20 | L68: 20 | M68: UPI | N68: Instagram Shop | O68: Lucknow | P68: Uttar Pradesh | Q68: Delhi | R68: 45592 | S68: Delivered | T68: Yes | U68: Changed Mind | V68: 45616 | W68: Processed | AB68: =COUNTIF(A$2:A$347,A68) -> 1 | AC68: =LEN(S68)-LEN(TRIM(S68)) -> 0 | AD68: =LEN(E68)-LEN(SUBSTITUTE(E68,"-","")) -> 2 | AE68: =IF(I68>10,"FLAG","OK") -> OK | AF68: =IF(OR(H68<=0,H68>10000),"FLAG","OK") -> OK | AG68: =IF(OR(L68<0,L68>100),"FLAG","OK") -> OK | AI68: =IF(AG68=J68,"OK","ERROR") -> ERROR | AJ68: =IF(R68<B68,"ERROR","OK") -> OK | AK68: =IF(AND(S68="Cancelled",R68<>""),"ERROR","OK") -> OK | AL68: =IF(AND(T68="Yes",U68=""),"ERROR","OK") -> OK | AM68: =IF(V68<R68,"ERROR","OK") -> OK | AN68: =IF(AND(I68>0,MOD(I68,1)=0),"OK","ERROR") -> OK | AO68: =IF(OR(B68="",B68<DATE(2024,10,1),B68>DATE(2024,12,31)),"ERROR","OK") -> OK | AP68: =IF(OR(B68<DATE(2024,10,1),B68>DATE(2024,12,31)),"ERROR","OK") -> OK | AQ68: =IF(OR(S68="Delivered",S68="Cancelled",S68="RTO",S68="In Transit"),"OK","ERROR") -> OK
A69: UT-100068 | B69: 45582 | C69: CUST_10067 | D69: New | E69: OUT-SHR-L | F69: Outerwear | G69: Shrug | H69: 1299 | I69: 1 | J69: 1299 | L69: 0 | M69: Debit Card | N69: Mobile App | O69: Bangalore | P69: Karnataka | Q69: Bangalore | R69: 45593 | S69: Delivered | T69: No | W69: Not Applicable | AB69: =COUNTIF(A$2:A$347,A69) -> 1 | AC69: =LEN(S69)-LEN(TRIM(S69)) -> 0 | AD69: =LEN(E69)-LEN(SUBSTITUTE(E69,"-","")) -> 2 | AE69: =IF(I69>10,"FLAG","OK") -> OK | AF69: =IF(OR(H69<=0,H69>10000),"FLAG","OK") -> OK | AG69: =IF(OR(L69<0,L69>100),"FLAG","OK") -> OK | AI69: =IF(AG69=J69,"OK","ERROR") -> ERROR | AJ69: =IF(R69<B69,"ERROR","OK") -> OK | AK69: =IF(AND(S69="Cancelled",R69<>""),"ERROR","OK") -> OK | AL69: =IF(AND(T69="Yes",U69=""),"ERROR","OK") -> OK | AM69: =IF(V69<R69,"ERROR","OK") -> ERROR | AN69: =IF(AND(I69>0,MOD(I69,1)=0),"OK","ERROR") -> OK | AO69: =IF(OR(B69="",B69<DATE(2024,10,1),B69>DATE(2024,12,31)),"ERROR","OK") -> OK | AP69: =IF(OR(B69<DATE(2024,10,1),B69>DATE(2024,12,31)),"ERROR","OK") -> OK | AQ69: =IF(OR(S69="Delivered",S69="Cancelled",S69="RTO",S69="In Transit"),"OK","ERROR") -> OK
A70: UT-100069 | B70: 45582 | C70: CUST_10068 | D70: New | E70: ACC-CLT-OS | F70: Accessories | G70: Clutch Bag | H70: 1599 | I70: 1 | J70: 1599 | L70: 0 | M70: Credit Card | N70: Website | O70: Mumbai | P70: Maharashtra | Q70: Mumbai | R70: 45592 | S70: Delivered | T70: Yes | U70: Damaged in Transit | V70: 45618 | W70: Processed | AB70: =COUNTIF(A$2:A$347,A70) -> 1 | AC70: =LEN(S70)-LEN(TRIM(S70)) -> 0 | AD70: =LEN(E70)-LEN(SUBSTITUTE(E70,"-","")) -> 2 | AE70: =IF(I70>10,"FLAG","OK") -> OK | AF70: =IF(OR(H70<=0,H70>10000),"FLAG","OK") -> OK | AG70: =IF(OR(L70<0,L70>100),"FLAG","OK") -> OK | AI70: =IF(AG70=J70,"OK","ERROR") -> ERROR | AJ70: =IF(R70<B70,"ERROR","OK") -> OK | AK70: =IF(AND(S70="Cancelled",R70<>""),"ERROR","OK") -> OK | AL70: =IF(AND(T70="Yes",U70=""),"ERROR","OK") -> OK | AM70: =IF(V70<R70,"ERROR","OK") -> OK | AN70: =IF(AND(I70>0,MOD(I70,1)=0),"OK","ERROR") -> OK | AO70: =IF(OR(B70="",B70<DATE(2024,10,1),B70>DATE(2024,12,31)),"ERROR","OK") -> OK | AP70: =IF(OR(B70<DATE(2024,10,1),B70>DATE(2024,12,31)),"ERROR","OK") -> OK | AQ70: =IF(OR(S70="Delivered",S70="Cancelled",S70="RTO",S70="In Transit"),"OK","ERROR") -> OK
A71: UT-100070 | B71: 45582 | C71: CUST_10069 | D71: Returning | E71: BOT-FLR-S | F71: Bottoms | G71: Flared Jeans | H71: 2099 | I71: 1 | J71: 2099 | K71: FIRST15 | L71: 15 | M71: UPI | N71: Instagram Shop | O71: Delhi | P71: Delhi | Q71: Delhi | R71: 45594 | S71: Delivered | T71: No | W71: Not Applicable | AB71: =COUNTIF(A$2:A$347,A71) -> 1 | AC71: =LEN(S71)-LEN(TRIM(S71)) -> 0 | AD71: =LEN(E71)-LEN(SUBSTITUTE(E71,"-","")) -> 2 | AE71: =IF(I71>10,"FLAG","OK") -> OK | AF71: =IF(OR(H71<=0,H71>10000),"FLAG","OK") -> OK | AG71: =IF(OR(L71<0,L71>100),"FLAG","OK") -> OK | AI71: =IF(AG71=J71,"OK","ERROR") -> ERROR | AJ71: =IF(R71<B71,"ERROR","OK") -> OK | AK71: =IF(AND(S71="Cancelled",R71<>""),"ERROR","OK") -> OK | AL71: =IF(AND(T71="Yes",U71=""),"ERROR","OK") -> OK | AM71: =IF(V71<R71,"ERROR","OK") -> ERROR | AN71: =IF(AND(I71>0,MOD(I71,1)=0),"OK","ERROR") -> OK | AO71: =IF(OR(B71="",B71<DATE(2024,10,1),B71>DATE(2024,12,31)),"ERROR","OK") -> OK | AP71: =IF(OR(B71<DATE(2024,10,1),B71>DATE(2024,12,31)),"ERROR","OK") -> OK | AQ71: =IF(OR(S71="Delivered",S71="Cancelled",S71="RTO",S71="In Transit"),"OK","ERROR") -> OK
A72: UT-100071 | B72: 45582 | C72: CUST_10070 | D72: New | E72: DRS-PIN-M | F72: Dresses | G72: Pinafore Dress | H72: 2299 | I72: 1 | J72: 2299 | L72: 0 | M72: COD | N72: Mobile App | O72: Chandigarh | P72: Punjab | Q72: Delhi | S72: RTO | T72: No | W72: Not Applicable | AB72: =COUNTIF(A$2:A$347,A72) -> 1 | AC72: =LEN(S72)-LEN(TRIM(S72)) -> 0 | AD72: =LEN(E72)-LEN(SUBSTITUTE(E72,"-","")) -> 2 | AE72: =IF(I72>10,"FLAG","OK") -> OK | AF72: =IF(OR(H72<=0,H72>10000),"FLAG","OK") -> OK | AG72: =IF(OR(L72<0,L72>100),"FLAG","OK") -> OK | AI72: =IF(AG72=J72,"OK","ERROR") -> ERROR | AJ72: =IF(R72<B72,"ERROR","OK") -> ERROR | AK72: =IF(AND(S72="Cancelled",R72<>""),"ERROR","OK") -> OK | AL72: =IF(AND(T72="Yes",U72=""),"ERROR","OK") -> OK | AM72: =IF(V72<R72,"ERROR","OK") -> OK | AN72: =IF(AND(I72>0,MOD(I72,1)=0),"OK","ERROR") -> OK | AO72: =IF(OR(B72="",B72<DATE(2024,10,1),B72>DATE(2024,12,31)),"ERROR","OK") -> OK | AP72: =IF(OR(B72<DATE(2024,10,1),B72>DATE(2024,12,31)),"ERROR","OK") -> OK | AQ72: =IF(OR(S72="Delivered",S72="Cancelled",S72="RTO",S72="In Transit"),"OK","ERROR") -> OK
A73: UT-100072 | B73: 45583 | C73: CUST_10071 | D73: New | E73: TOP-CRW-L | F73: Tops | G73: Crew Neck Tee | H73: 1199 | I73: 2 | J73: 2398 | L73: 0 | M73: Wallet | N73: Website | O73: Noida | P73: Uttar Pradesh | Q73: Delhi | R73: 45593 | S73: Delivered | T73: No | W73: Not Applicable | AB73: =COUNTIF(A$2:A$347,A73) -> 1 | AC73: =LEN(S73)-LEN(TRIM(S73)) -> 0 | AD73: =LEN(E73)-LEN(SUBSTITUTE(E73,"-","")) -> 2 | AE73: =IF(I73>10,"FLAG","OK") -> OK | AF73: =IF(OR(H73<=0,H73>10000),"FLAG","OK") -> OK | AG73: =IF(OR(L73<0,L73>100),"FLAG","OK") -> OK | AI73: =IF(AG73=J73,"OK","ERROR") -> ERROR | AJ73: =IF(R73<B73,"ERROR","OK") -> OK | AK73: =IF(AND(S73="Cancelled",R73<>""),"ERROR","OK") -> OK | AL73: =IF(AND(T73="Yes",U73=""),"ERROR","OK") -> OK | AM73: =IF(V73<R73,"ERROR","OK") -> ERROR | AN73: =IF(AND(I73>0,MOD(I73,1)=0),"OK","ERROR") -> OK | AO73: =IF(OR(B73="",B73<DATE(2024,10,1),B73>DATE(2024,12,31)),"ERROR","OK") -> OK | AP73: =IF(OR(B73<DATE(2024,10,1),B73>DATE(2024,12,31)),"ERROR","OK") -> OK | AQ73: =IF(OR(S73="Delivered",S73="Cancelled",S73="RTO",S73="In Transit"),"OK","ERROR") -> OK
A74: UT-100073 | B74: 45583 | C74: CUST_10072 | D74: New | E74: OUT-CDG-M | F74: Outerwear | G74: Cardigan | H74: 2599 | I74: 1 | J74: 2599 | K74: DIWALI20 | L74: 20 | M74: Credit Card | N74: Instagram Shop | O74: Gurgaon | P74: Haryana | Q74: Delhi | R74: 45595 | S74: Delivered | T74: Yes | U74: Size Issue | V74: 45622 | W74: Processed | AB74: =COUNTIF(A$2:A$347,A74) -> 1 | AC74: =LEN(S74)-LEN(TRIM(S74)) -> 0 | AD74: =LEN(E74)-LEN(SUBSTITUTE(E74,"-","")) -> 2 | AE74: =IF(I74>10,"FLAG","OK") -> OK | AF74: =IF(OR(H74<=0,H74>10000),"FLAG","OK") -> OK | AG74: =IF(OR(L74<0,L74>100),"FLAG","OK") -> OK | AI74: =IF(AG74=J74,"OK","ERROR") -> ERROR | AJ74: =IF(R74<B74,"ERROR","OK") -> OK | AK74: =IF(AND(S74="Cancelled",R74<>""),"ERROR","OK") -> OK | AL74: =IF(AND(T74="Yes",U74=""),"ERROR","OK") -> OK | AM74: =IF(V74<R74,"ERROR","OK") -> OK | AN74: =IF(AND(I74>0,MOD(I74,1)=0),"OK","ERROR") -> OK | AO74: =IF(OR(B74="",B74<DATE(2024,10,1),B74>DATE(2024,12,31)),"ERROR","OK") -> OK | AP74: =IF(OR(B74<DATE(2024,10,1),B74>DATE(2024,12,31)),"ERROR","OK") -> OK | AQ74: =IF(OR(S74="Delivered",S74="Cancelled",S74="RTO",S74="In Transit"),"OK","ERROR") -> OK
A75: UT-100074 | B75: 45583 | C75: CUST_10073 | D75: Returning | E75: ACC-SCR-OS | F75: Accessories | G75: Hair Scrunchie | H75: 299 | I75: 5 | J75: 1495 | L75: 0 | M75: UPI | N75: Mobile App | O75: Indore | P75: Madhya Pradesh | Q75: Mumbai | R75: 45592 | S75: Delivered | T75: No | W75: Not Applicable | AB75: =COUNTIF(A$2:A$347,A75) -> 1 | AC75: =LEN(S75)-LEN(TRIM(S75)) -> 0 | AD75: =LEN(E75)-LEN(SUBSTITUTE(E75,"-","")) -> 2 | AE75: =IF(I75>10,"FLAG","OK") -> OK | AF75: =IF(OR(H75<=0,H75>10000),"FLAG","OK") -> OK | AG75: =IF(OR(L75<0,L75>100),"FLAG","OK") -> OK | AI75: =IF(AG75=J75,"OK","ERROR") -> ERROR | AJ75: =IF(R75<B75,"ERROR","OK") -> OK | AK75: =IF(AND(S75="Cancelled",R75<>""),"ERROR","OK") -> OK | AL75: =IF(AND(T75="Yes",U75=""),"ERROR","OK") -> OK | AM75: =IF(V75<R75,"ERROR","OK") -> ERROR | AN75: =IF(AND(I75>0,MOD(I75,1)=0),"OK","ERROR") -> OK | AO75: =IF(OR(B75="",B75<DATE(2024,10,1),B75>DATE(2024,12,31)),"ERROR","OK") -> OK | AP75: =IF(OR(B75<DATE(2024,10,1),B75>DATE(2024,12,31)),"ERROR","OK") -> OK | AQ75: =IF(OR(S75="Delivered",S75="Cancelled",S75="RTO",S75="In Transit"),"OK","ERROR") -> OK
A76: UT-100075 | B76: 45583 | C76: CUST_10074 | D76: New | E76: BOT-PPR-M | F76: Bottoms | G76: Paper Bag Pants | H76: 1899 | I76: 1 | J76: 1899 | L76: 0 | M76: Debit Card | N76: Website | O76: Surat | P76: Gujarat | Q76: Mumbai | R76: 45595 | S76: Delivered | T76: Yes | U76: Wrong Item | V76: 45624 | W76: Processed | AB76: =COUNTIF(A$2:A$347,A76) -> 1 | AC76: =LEN(S76)-LEN(TRIM(S76)) -> 0 | AD76: =LEN(E76)-LEN(SUBSTITUTE(E76,"-","")) -> 2 | AE76: =IF(I76>10,"FLAG","OK") -> OK | AF76: =IF(OR(H76<=0,H76>10000),"FLAG","OK") -> OK | AG76: =IF(OR(L76<0,L76>100),"FLAG","OK") -> OK | AI76: =IF(AG76=J76,"OK","ERROR") -> ERROR | AJ76: =IF(R76<B76,"ERROR","OK") -> OK | AK76: =IF(AND(S76="Cancelled",R76<>""),"ERROR","OK") -> OK | AL76: =IF(AND(T76="Yes",U76=""),"ERROR","OK") -> OK | AM76: =IF(V76<R76,"ERROR","OK") -> OK | AN76: =IF(AND(I76>0,MOD(I76,1)=0),"OK","ERROR") -> OK | AO76: =IF(OR(B76="",B76<DATE(2024,10,1),B76>DATE(2024,12,31)),"ERROR","OK") -> OK | AP76: =IF(OR(B76<DATE(2024,10,1),B76>DATE(2024,12,31)),"ERROR","OK") -> OK | AQ76: =IF(OR(S76="Delivered",S76="Cancelled",S76="RTO",S76="In Transit"),"OK","ERROR") -> OK
A77: UT-100076 | B77: 45584 | C77: CUST_10075 | D77: New | E77: DRS-SMK-S | F77: Dresses | G77: Smocked Dress | H77: 2199 | I77: 1 | J77: 2199 | L77: 0 | M77: Credit Card | N77: Instagram Shop | O77: Patna | P77: Bihar | Q77: Delhi | R77: 45596 | S77: Delivered | T77: No | W77: Not Applicable | AB77: =COUNTIF(A$2:A$347,A77) -> 1 | AC77: =LEN(S77)-LEN(TRIM(S77)) -> 0 | AD77: =LEN(E77)-LEN(SUBSTITUTE(E77,"-","")) -> 2 | AE77: =IF(I77>10,"FLAG","OK") -> OK | AF77: =IF(OR(H77<=0,H77>10000),"FLAG","OK") -> OK | AG77: =IF(OR(L77<0,L77>100),"FLAG","OK") -> OK | AI77: =IF(AG77=J77,"OK","ERROR") -> ERROR | AJ77: =IF(R77<B77,"ERROR","OK") -> OK | AK77: =IF(AND(S77="Cancelled",R77<>""),"ERROR","OK") -> OK | AL77: =IF(AND(T77="Yes",U77=""),"ERROR","OK") -> OK | AM77: =IF(V77<R77,"ERROR","OK") -> ERROR | AN77: =IF(AND(I77>0,MOD(I77,1)=0),"OK","ERROR") -> OK | AO77: =IF(OR(B77="",B77<DATE(2024,10,1),B77>DATE(2024,12,31)),"ERROR","OK") -> OK | AP77: =IF(OR(B77<DATE(2024,10,1),B77>DATE(2024,12,31)),"ERROR","OK") -> OK | AQ77: =IF(OR(S77="Delivered",S77="Cancelled",S77="RTO",S77="In Transit"),"OK","ERROR") -> OK
A78: UT-100077 | B78: 45584 | C78: CUST_10076 | D78: New | E78: TOP-BTN-M | F78: Tops | G78: Button-Down Shirt | H78: 1799 | I78: 1 | J78: 1799 | K78: FLAT10 | L78: 10 | M78: COD | N78: Mobile App | O78: Bhopal | P78: Madhya Pradesh | Q78: Mumbai | R78: 45594 | S78: Delivered | T78: Yes | U78: Quality Defect | V78: 45621 | W78: Processed | AB78: =COUNTIF(A$2:A$347,A78) -> 1 | AC78: =LEN(S78)-LEN(TRIM(S78)) -> 0 | AD78: =LEN(E78)-LEN(SUBSTITUTE(E78,"-","")) -> 2 | AE78: =IF(I78>10,"FLAG","OK") -> OK | AF78: =IF(OR(H78<=0,H78>10000),"FLAG","OK") -> OK | AG78: =IF(OR(L78<0,L78>100),"FLAG","OK") -> OK | AI78: =IF(AG78=J78,"OK","ERROR") -> ERROR | AJ78: =IF(R78<B78,"ERROR","OK") -> OK | AK78: =IF(AND(S78="Cancelled",R78<>""),"ERROR","OK") -> OK | AL78: =IF(AND(T78="Yes",U78=""),"ERROR","OK") -> OK | AM78: =IF(V78<R78,"ERROR","OK") -> OK | AN78: =IF(AND(I78>0,MOD(I78,1)=0),"OK","ERROR") -> OK | AO78: =IF(OR(B78="",B78<DATE(2024,10,1),B78>DATE(2024,12,31)),"ERROR","OK") -> OK | AP78: =IF(OR(B78<DATE(2024,10,1),B78>DATE(2024,12,31)),"ERROR","OK") -> OK | AQ78: =IF(OR(S78="Delivered",S78="Cancelled",S78="RTO",S78="In Transit"),"OK","ERROR") -> OK
A79: UT-100078 | B79: 45584 | C79: CUST_10077 | D79: Returning | E79: OUT-VLV-L | F79: Outerwear | G79: Velvet Blazer | H79: 4999 | I79: 1 | J79: 4999 | L79: 0 | M79: UPI | N79: Website | O79: Nagpur | P79: Maharashtra | Q79: Mumbai | R79: 45597 | S79: Delivered | T79: No | W79: Not Applicable | AB79: =COUNTIF(A$2:A$347,A79) -> 1 | AC79: =LEN(S79)-LEN(TRIM(S79)) -> 0 | AD79: =LEN(E79)-LEN(SUBSTITUTE(E79,"-","")) -> 2 | AE79: =IF(I79>10,"FLAG","OK") -> OK | AF79: =IF(OR(H79<=0,H79>10000),"FLAG","OK") -> OK | AG79: =IF(OR(L79<0,L79>100),"FLAG","OK") -> OK | AI79: =IF(AG79=J79,"OK","ERROR") -> ERROR | AJ79: =IF(R79<B79,"ERROR","OK") -> OK | AK79: =IF(AND(S79="Cancelled",R79<>""),"ERROR","OK") -> OK | AL79: =IF(AND(T79="Yes",U79=""),"ERROR","OK") -> OK | AM79: =IF(V79<R79,"ERROR","OK") -> ERROR | AN79: =IF(AND(I79>0,MOD(I79,1)=0),"OK","ERROR") -> OK | AO79: =IF(OR(B79="",B79<DATE(2024,10,1),B79>DATE(2024,12,31)),"ERROR","OK") -> OK | AP79: =IF(OR(B79<DATE(2024,10,1),B79>DATE(2024,12,31)),"ERROR","OK") -> OK | AQ79: =IF(OR(S79="Delivered",S79="Cancelled",S79="RTO",S79="In Transit"),"OK","ERROR") -> OK
A80: UT-100079 | B80: 45584 | C80: CUST_10078 | D80: New | E80: ACC-TOT-OS | F80: Accessories | G80: Canvas Tote | H80: 999 | I80: 1 | J80: 999 | L80: 0 | M80: Wallet | N80: Instagram Shop | O80: Coimbatore | P80: Tamil Nadu | Q80: Bangalore | R80: 45595 | S80: Delivered | T80: Yes | U80: Size Issue | V80: 45624 | W80: Processed | AB80: =COUNTIF(A$2:A$347,A80) -> 1 | AC80: =LEN(S80)-LEN(TRIM(S80)) -> 0 | AD80: =LEN(E80)-LEN(SUBSTITUTE(E80,"-","")) -> 2 | AE80: =IF(I80>10,"FLAG","OK") -> OK | AF80: =IF(OR(H80<=0,H80>10000),"FLAG","OK") -> OK | AG80: =IF(OR(L80<0,L80>100),"FLAG","OK") -> OK | AI80: =IF(AG80=J80,"OK","ERROR") -> ERROR | AJ80: =IF(R80<B80,"ERROR","OK") -> OK | AK80: =IF(AND(S80="Cancelled",R80<>""),"ERROR","OK") -> OK | AL80: =IF(AND(T80="Yes",U80=""),"ERROR","OK") -> OK | AM80: =IF(V80<R80,"ERROR","OK") -> OK | AN80: =IF(AND(I80>0,MOD(I80,1)=0),"OK","ERROR") -> OK | AO80: =IF(OR(B80="",B80<DATE(2024,10,1),B80>DATE(2024,12,31)),"ERROR","OK") -> OK | AP80: =IF(OR(B80<DATE(2024,10,1),B80>DATE(2024,12,31)),"ERROR","OK") -> OK | AQ80: =IF(OR(S80="Delivered",S80="Cancelled",S80="RTO",S80="In Transit"),"OK","ERROR") -> OK
A81: UT-100080 | B81: 45585 | C81: CUST_10079 | D81: New | E81: BOT-CRG-S | F81: Bottoms | G81: Cargo Shorts | H81: 1499 | I81: 1 | J81: 1499 | K81: DIWALI20 | L81: 20 | M81: Credit Card | N81: Mobile App | O81: Kochi | P81: Kerala | Q81: Bangalore | R81: 45596 | S81: Delivered | T81: No | W81: Not Applicable | AB81: =COUNTIF(A$2:A$347,A81) -> 1 | AC81: =LEN(S81)-LEN(TRIM(S81)) -> 0 | AD81: =LEN(E81)-LEN(SUBSTITUTE(E81,"-","")) -> 2 | AE81: =IF(I81>10,"FLAG","OK") -> OK | AF81: =IF(OR(H81<=0,H81>10000),"FLAG","OK") -> OK | AG81: =IF(OR(L81<0,L81>100),"FLAG","OK") -> OK | AI81: =IF(AG81=J81,"OK","ERROR") -> ERROR | AJ81: =IF(R81<B81,"ERROR","OK") -> OK | AK81: =IF(AND(S81="Cancelled",R81<>""),"ERROR","OK") -> OK | AL81: =IF(AND(T81="Yes",U81=""),"ERROR","OK") -> OK | AM81: =IF(V81<R81,"ERROR","OK") -> ERROR | AN81: =IF(AND(I81>0,MOD(I81,1)=0),"OK","ERROR") -> OK | AO81: =IF(OR(B81="",B81<DATE(2024,10,1),B81>DATE(2024,12,31)),"ERROR","OK") -> OK | AP81: =IF(OR(B81<DATE(2024,10,1),B81>DATE(2024,12,31)),"ERROR","OK") -> OK | AQ81: =IF(OR(S81="Delivered",S81="Cancelled",S81="RTO",S81="In Transit"),"OK","ERROR") -> OK
A82: UT-100081 | B82: 45585 | C82: CUST_10080 | D82: New | E82: DRS-BTR-M | F82: Dresses | G82: Butterfly Dress | H82: 2899 | I82: 1 | J82: 2899 | L82: 0 | M82: Debit Card | N82: Website | O82: Vizag | P82: Andhra Pradesh | Q82: Bangalore | R82: 45598 | S82: Delivered | T82: Yes | U82: Changed Mind | V82: 45626 | W82: Processed | AB82: =COUNTIF(A$2:A$347,A82) -> 1 | AC82: =LEN(S82)-LEN(TRIM(S82)) -> 0 | AD82: =LEN(E82)-LEN(SUBSTITUTE(E82,"-","")) -> 2 | AE82: =IF(I82>10,"FLAG","OK") -> OK | AF82: =IF(OR(H82<=0,H82>10000),"FLAG","OK") -> OK | AG82: =IF(OR(L82<0,L82>100),"FLAG","OK") -> OK | AI82: =IF(AG82=J82,"OK","ERROR") -> ERROR | AJ82: =IF(R82<B82,"ERROR","OK") -> OK | AK82: =IF(AND(S82="Cancelled",R82<>""),"ERROR","OK") -> OK | AL82: =IF(AND(T82="Yes",U82=""),"ERROR","OK") -> OK | AM82: =IF(V82<R82,"ERROR","OK") -> OK | AN82: =IF(AND(I82>0,MOD(I82,1)=0),"OK","ERROR") -> OK | AO82: =IF(OR(B82="",B82<DATE(2024,10,1),B82>DATE(2024,12,31)),"ERROR","OK") -> OK | AP82: =IF(OR(B82<DATE(2024,10,1),B82>DATE(2024,12,31)),"ERROR","OK") -> OK | AQ82: =IF(OR(S82="Delivered",S82="Cancelled",S82="RTO",S82="In Transit"),"OK","ERROR") -> OK
A83: UT-100082 | B83: 45585 | C83: CUST_10081 | D83: Returning | E83: TOP-VNK-L | F83: Tops | G83: V-Neck Tee | H83: 1099 | I83: 2 | J83: 2198 | L83: 0 | M83: UPI | N83: Instagram Shop | O83: Thiruvananthapuram | P83: Kerala | Q83: Bangalore | R83: 45595 | S83: Delivered | T83: No | W83: Not Applicable | AB83: =COUNTIF(A$2:A$347,A83) -> 1 | AC83: =LEN(S83)-LEN(TRIM(S83)) -> 0 | AD83: =LEN(E83)-LEN(SUBSTITUTE(E83,"-","")) -> 2 | AE83: =IF(I83>10,"FLAG","OK") -> OK | AF83: =IF(OR(H83<=0,H83>10000),"FLAG","OK") -> OK | AG83: =IF(OR(L83<0,L83>100),"FLAG","OK") -> OK | AI83: =IF(AG83=J83,"OK","ERROR") -> ERROR | AJ83: =IF(R83<B83,"ERROR","OK") -> OK | AK83: =IF(AND(S83="Cancelled",R83<>""),"ERROR","OK") -> OK | AL83: =IF(AND(T83="Yes",U83=""),"ERROR","OK") -> OK | AM83: =IF(V83<R83,"ERROR","OK") -> ERROR | AN83: =IF(AND(I83>0,MOD(I83,1)=0),"OK","ERROR") -> OK | AO83: =IF(OR(B83="",B83<DATE(2024,10,1),B83>DATE(2024,12,31)),"ERROR","OK") -> OK | AP83: =IF(OR(B83<DATE(2024,10,1),B83>DATE(2024,12,31)),"ERROR","OK") -> OK | AQ83: =IF(OR(S83="Delivered",S83="Cancelled",S83="RTO",S83="In Transit"),"OK","ERROR") -> OK
A84: UT-100083 | B84: 45585 | C84: CUST_10082 | D84: New | E84: OUT-TRN-M | F84: Outerwear | G84: Trench Coat | H84: 5499 | I84: 1 | J84: 5499 | K84: FIRST15 | L84: 15 | M84: Credit Card | N84: Mobile App | O84: Mysore | P84: Karnataka | Q84: Bangalore | R84: 45599 | S84: Delivered | T84: Yes | U84: Size Issue | V84: 45627 | W84: Processed | AB84: =COUNTIF(A$2:A$347,A84) -> 1 | AC84: =LEN(S84)-LEN(TRIM(S84)) -> 0 | AD84: =LEN(E84)-LEN(SUBSTITUTE(E84,"-","")) -> 2 | AE84: =IF(I84>10,"FLAG","OK") -> OK | AF84: =IF(OR(H84<=0,H84>10000),"FLAG","OK") -> OK | AG84: =IF(OR(L84<0,L84>100),"FLAG","OK") -> OK | AI84: =IF(AG84=J84,"OK","ERROR") -> ERROR | AJ84: =IF(R84<B84,"ERROR","OK") -> OK | AK84: =IF(AND(S84="Cancelled",R84<>""),"ERROR","OK") -> OK | AL84: =IF(AND(T84="Yes",U84=""),"ERROR","OK") -> OK | AM84: =IF(V84<R84,"ERROR","OK") -> OK | AN84: =IF(AND(I84>0,MOD(I84,1)=0),"OK","ERROR") -> OK | AO84: =IF(OR(B84="",B84<DATE(2024,10,1),B84>DATE(2024,12,31)),"ERROR","OK") -> OK | AP84: =IF(OR(B84<DATE(2024,10,1),B84>DATE(2024,12,31)),"ERROR","OK") -> OK | AQ84: =IF(OR(S84="Delivered",S84="Cancelled",S84="RTO",S84="In Transit"),"OK","ERROR") -> OK
A85: UT-100084 | B85: 45586 | C85: CUST_10083 | D85: New | E85: ACC-BDY-OS | F85: Accessories | G85: Body Chain | H85: 799 | I85: 1 | J85: 799 | L85: 0 | M85: COD | N85: Website | O85: Vadodara | P85: Gujarat | Q85: Mumbai | S85: RTO | T85: No | W85: Not Applicable | AB85: =COUNTIF(A$2:A$347,A85) -> 1 | AC85: =LEN(S85)-LEN(TRIM(S85)) -> 0 | AD85: =LEN(E85)-LEN(SUBSTITUTE(E85,"-","")) -> 2 | AE85: =IF(I85>10,"FLAG","OK") -> OK | AF85: =IF(OR(H85<=0,H85>10000),"FLAG","OK") -> OK | AG85: =IF(OR(L85<0,L85>100),"FLAG","OK") -> OK | AI85: =IF(AG85=J85,"OK","ERROR") -> ERROR | AJ85: =IF(R85<B85,"ERROR","OK") -> ERROR | AK85: =IF(AND(S85="Cancelled",R85<>""),"ERROR","OK") -> OK | AL85: =IF(AND(T85="Yes",U85=""),"ERROR","OK") -> OK | AM85: =IF(V85<R85,"ERROR","OK") -> OK | AN85: =IF(AND(I85>0,MOD(I85,1)=0),"OK","ERROR") -> OK | AO85: =IF(OR(B85="",B85<DATE(2024,10,1),B85>DATE(2024,12,31)),"ERROR","OK") -> OK | AP85: =IF(OR(B85<DATE(2024,10,1),B85>DATE(2024,12,31)),"ERROR","OK") -> OK | AQ85: =IF(OR(S85="Delivered",S85="Cancelled",S85="RTO",S85="In Transit"),"OK","ERROR") -> OK
A86: UT-100085 | B86: 45586 | C86: CUST_10084 | D86: New | E86: BOT-JGR-L | F86: Bottoms | G86: Jogger Pants | H86: 1599 | I86: 1 | J86: 1599 | L86: 0 | M86: Wallet | N86: Instagram Shop | O86: Rajkot | P86: Gujarat | Q86: Mumbai | R86: 45598 | S86: Delivered | T86: No | W86: Not Applicable | AB86: =COUNTIF(A$2:A$347,A86) -> 1 | AC86: =LEN(S86)-LEN(TRIM(S86)) -> 0 | AD86: =LEN(E86)-LEN(SUBSTITUTE(E86,"-","")) -> 2 | AE86: =IF(I86>10,"FLAG","OK") -> OK | AF86: =IF(OR(H86<=0,H86>10000),"FLAG","OK") -> OK | AG86: =IF(OR(L86<0,L86>100),"FLAG","OK") -> OK | AI86: =IF(AG86=J86,"OK","ERROR") -> ERROR | AJ86: =IF(R86<B86,"ERROR","OK") -> OK | AK86: =IF(AND(S86="Cancelled",R86<>""),"ERROR","OK") -> OK | AL86: =IF(AND(T86="Yes",U86=""),"ERROR","OK") -> OK | AM86: =IF(V86<R86,"ERROR","OK") -> ERROR | AN86: =IF(AND(I86>0,MOD(I86,1)=0),"OK","ERROR") -> OK | AO86: =IF(OR(B86="",B86<DATE(2024,10,1),B86>DATE(2024,12,31)),"ERROR","OK") -> OK | AP86: =IF(OR(B86<DATE(2024,10,1),B86>DATE(2024,12,31)),"ERROR","OK") -> OK | AQ86: =IF(OR(S86="Delivered",S86="Cancelled",S86="RTO",S86="In Transit"),"OK","ERROR") -> OK
A87: UT-100086 | B87: 45586 | C87: CUST_10085 | D87: Returning | E87: DRS-RFL-S | F87: Dresses | G87: Ruffle Dress | H87: 2699 | I87: 1 | J87: 2699 | K87: DIWALI20 | L87: 20 | M87: Credit Card | N87: Mobile App | O87: Kanpur | P87: Uttar Pradesh | Q87: Delhi | R87: 45597 | S87: Delivered | T87: Yes | U87: Quality Defect | V87: 45626 | W87: Processed | AB87: =COUNTIF(A$2:A$347,A87) -> 1 | AC87: =LEN(S87)-LEN(TRIM(S87)) -> 0 | AD87: =LEN(E87)-LEN(SUBSTITUTE(E87,"-","")) -> 2 | AE87: =IF(I87>10,"FLAG","OK") -> OK | AF87: =IF(OR(H87<=0,H87>10000),"FLAG","OK") -> OK | AG87: =IF(OR(L87<0,L87>100),"FLAG","OK") -> OK | AI87: =IF(AG87=J87,"OK","ERROR") -> ERROR | AJ87: =IF(R87<B87,"ERROR","OK") -> OK | AK87: =IF(AND(S87="Cancelled",R87<>""),"ERROR","OK") -> OK | AL87: =IF(AND(T87="Yes",U87=""),"ERROR","OK") -> OK | AM87: =IF(V87<R87,"ERROR","OK") -> OK | AN87: =IF(AND(I87>0,MOD(I87,1)=0),"OK","ERROR") -> OK | AO87: =IF(OR(B87="",B87<DATE(2024,10,1),B87>DATE(2024,12,31)),"ERROR","OK") -> OK | AP87: =IF(OR(B87<DATE(2024,10,1),B87>DATE(2024,12,31)),"ERROR","OK") -> OK | AQ87: =IF(OR(S87="Delivered",S87="Cancelled",S87="RTO",S87="In Transit"),"OK","ERROR") -> OK
A88: UT-100087 | B88: 45586 | C88: CUST_10086 | D88: New | E88: TOP-SQR-M | F88: Tops | G88: Square Neck Top | H88: 1499 | I88: 1 | J88: 1499 | L88: 0 | M88: UPI | N88: Website | O88: Mumbai | P88: Maharashtra | Q88: Mumbai | R88: 45598 | S88: Delivered | T88: No | W88: Not Applicable | AB88: =COUNTIF(A$2:A$347,A88) -> 1 | AC88: =LEN(S88)-LEN(TRIM(S88)) -> 0 | AD88: =LEN(E88)-LEN(SUBSTITUTE(E88,"-","")) -> 2 | AE88: =IF(I88>10,"FLAG","OK") -> OK | AF88: =IF(OR(H88<=0,H88>10000),"FLAG","OK") -> OK | AG88: =IF(OR(L88<0,L88>100),"FLAG","OK") -> OK | AI88: =IF(AG88=J88,"OK","ERROR") -> ERROR | AJ88: =IF(R88<B88,"ERROR","OK") -> OK | AK88: =IF(AND(S88="Cancelled",R88<>""),"ERROR","OK") -> OK | AL88: =IF(AND(T88="Yes",U88=""),"ERROR","OK") -> OK | AM88: =IF(V88<R88,"ERROR","OK") -> ERROR | AN88: =IF(AND(I88>0,MOD(I88,1)=0),"OK","ERROR") -> OK | AO88: =IF(OR(B88="",B88<DATE(2024,10,1),B88>DATE(2024,12,31)),"ERROR","OK") -> OK | AP88: =IF(OR(B88<DATE(2024,10,1),B88>DATE(2024,12,31)),"ERROR","OK") -> OK | AQ88: =IF(OR(S88="Delivered",S88="Cancelled",S88="RTO",S88="In Transit"),"OK","ERROR") -> OK
A89: UT-100088 | B89: 45587 | C89: CUST_10087 | D89: New | E89: OUT-WND-L | F89: Outerwear | G89: Windbreaker | H89: 3299 | I89: 1 | J89: 3299 | L89: 0 | M89: Debit Card | N89: Instagram Shop | O89: Delhi | P89: Delhi | Q89: Delhi | R89: 45600 | S89: Delivered | T89: Yes | U89: Wrong Item | V89: 45629 | W89: Processed | AB89: =COUNTIF(A$2:A$347,A89) -> 1 | AC89: =LEN(S89)-LEN(TRIM(S89)) -> 0 | AD89: =LEN(E89)-LEN(SUBSTITUTE(E89,"-","")) -> 2 | AE89: =IF(I89>10,"FLAG","OK") -> OK | AF89: =IF(OR(H89<=0,H89>10000),"FLAG","OK") -> OK | AG89: =IF(OR(L89<0,L89>100),"FLAG","OK") -> OK | AI89: =IF(AG89=J89,"OK","ERROR") -> ERROR | AJ89: =IF(R89<B89,"ERROR","OK") -> OK | AK89: =IF(AND(S89="Cancelled",R89<>""),"ERROR","OK") -> OK | AL89: =IF(AND(T89="Yes",U89=""),"ERROR","OK") -> OK | AM89: =IF(V89<R89,"ERROR","OK") -> OK | AN89: =IF(AND(I89>0,MOD(I89,1)=0),"OK","ERROR") -> OK | AO89: =IF(OR(B89="",B89<DATE(2024,10,1),B89>DATE(2024,12,31)),"ERROR","OK") -> OK | AP89: =IF(OR(B89<DATE(2024,10,1),B89>DATE(2024,12,31)),"ERROR","OK") -> OK | AQ89: =IF(OR(S89="Delivered",S89="Cancelled",S89="RTO",S89="In Transit"),"OK","ERROR") -> OK
A90: UT-100089 | B90: 45587 | C90: CUST_10088 | D90: New | E90: ACC-ANK-OS | F90: Accessories | G90: Anklet | H90: 499 | I90: 2 | J90: 998 | K90: FLAT10 | L90: 10 | M90: Credit Card | N90: Mobile App | O90: Kolkata | P90: West Bengal | Q90: Delhi | R90: 45597 | S90: Delivered | T90: No | W90: Not Applicable | AB90: =COUNTIF(A$2:A$347,A90) -> 1 | AC90: =LEN(S90)-LEN(TRIM(S90)) -> 0 | AD90: =LEN(E90)-LEN(SUBSTITUTE(E90,"-","")) -> 2 | AE90: =IF(I90>10,"FLAG","OK") -> OK | AF90: =IF(OR(H90<=0,H90>10000),"FLAG","OK") -> OK | AG90: =IF(OR(L90<0,L90>100),"FLAG","OK") -> OK | AI90: =IF(AG90=J90,"OK","ERROR") -> ERROR | AJ90: =IF(R90<B90,"ERROR","OK") -> OK | AK90: =IF(AND(S90="Cancelled",R90<>""),"ERROR","OK") -> OK | AL90: =IF(AND(T90="Yes",U90=""),"ERROR","OK") -> OK | AM90: =IF(V90<R90,"ERROR","OK") -> ERROR | AN90: =IF(AND(I90>0,MOD(I90,1)=0),"OK","ERROR") -> OK | AO90: =IF(OR(B90="",B90<DATE(2024,10,1),B90>DATE(2024,12,31)),"ERROR","OK") -> OK | AP90: =IF(OR(B90<DATE(2024,10,1),B90>DATE(2024,12,31)),"ERROR","OK") -> OK | AQ90: =IF(OR(S90="Delivered",S90="Cancelled",S90="RTO",S90="In Transit"),"OK","ERROR") -> OK
A91: UT-100090 | B91: 45587 | C91: CUST_10089 | D91: Returning | E91: BOT-TRS-M | F91: Bottoms | G91: Tailored Trousers | H91: 2399 | I91: 1 | J91: 2399 | L91: 0 | M91: UPI | N91: Website | O91: Chennai | P91: Tamil Nadu | Q91: Bangalore | R91: 45599 | S91: Delivered | T91: No | W91: Not Applicable | AB91: =COUNTIF(A$2:A$347,A91) -> 1 | AC91: =LEN(S91)-LEN(TRIM(S91)) -> 0 | AD91: =LEN(E91)-LEN(SUBSTITUTE(E91,"-","")) -> 2 | AE91: =IF(I91>10,"FLAG","OK") -> OK | AF91: =IF(OR(H91<=0,H91>10000),"FLAG","OK") -> OK | AG91: =IF(OR(L91<0,L91>100),"FLAG","OK") -> OK | AI91: =IF(AG91=J91,"OK","ERROR") -> ERROR | AJ91: =IF(R91<B91,"ERROR","OK") -> OK | AK91: =IF(AND(S91="Cancelled",R91<>""),"ERROR","OK") -> OK | AL91: =IF(AND(T91="Yes",U91=""),"ERROR","OK") -> OK | AM91: =IF(V91<R91,"ERROR","OK") -> ERROR | AN91: =IF(AND(I91>0,MOD(I91,1)=0),"OK","ERROR") -> OK | AO91: =IF(OR(B91="",B91<DATE(2024,10,1),B91>DATE(2024,12,31)),"ERROR","OK") -> OK | AP91: =IF(OR(B91<DATE(2024,10,1),B91>DATE(2024,12,31)),"ERROR","OK") -> OK | AQ91: =IF(OR(S91="Delivered",S91="Cancelled",S91="RTO",S91="In Transit"),"OK","ERROR") -> OK
A92: UT-100091 | B92: 45587 | C92: CUST_10090 | D92: New | E92: DRS-LST-M | F92: Dresses | G92: Lace Trim Dress | H92: 2599 | I92: 1 | J92: 2599 | L92: 0 | M92: COD | N92: Instagram Shop | O92: Hyderabad | P92: Telangana | Q92: Bangalore | S92: RTO | T92: No | W92: Not Applicable | AB92: =COUNTIF(A$2:A$347,A92) -> 1 | AC92: =LEN(S92)-LEN(TRIM(S92)) -> 0 | AD92: =LEN(E92)-LEN(SUBSTITUTE(E92,"-","")) -> 2 | AE92: =IF(I92>10,"FLAG","OK") -> OK | AF92: =IF(OR(H92<=0,H92>10000),"FLAG","OK") -> OK | AG92: =IF(OR(L92<0,L92>100),"FLAG","OK") -> OK | AI92: =IF(AG92=J92,"OK","ERROR") -> ERROR | AJ92: =IF(R92<B92,"ERROR","OK") -> ERROR | AK92: =IF(AND(S92="Cancelled",R92<>""),"ERROR","OK") -> OK | AL92: =IF(AND(T92="Yes",U92=""),"ERROR","OK") -> OK | AM92: =IF(V92<R92,"ERROR","OK") -> OK | AN92: =IF(AND(I92>0,MOD(I92,1)=0),"OK","ERROR") -> OK | AO92: =IF(OR(B92="",B92<DATE(2024,10,1),B92>DATE(2024,12,31)),"ERROR","OK") -> OK | AP92: =IF(OR(B92<DATE(2024,10,1),B92>DATE(2024,12,31)),"ERROR","OK") -> OK | AQ92: =IF(OR(S92="Delivered",S92="Cancelled",S92="RTO",S92="In Transit"),"OK","ERROR") -> OK
A93: UT-100092 | B93: 45588 | C93: CUST_10091 | D93: New | E93: TOP-TIE-S | F93: Tops | G93: Tie-Front Top | H93: 1399 | I93: 1 | J93: 1399 | K93: DIWALI20 | L93: 20 | M93: Wallet | N93: Mobile App | O93: Pune | P93: Maharashtra | Q93: Mumbai | R93: 45599 | S93: Delivered | T93: Yes | U93: Size Issue | V93: 45628 | W93: Processed | AB93: =COUNTIF(A$2:A$347,A93) -> 1 | AC93: =LEN(S93)-LEN(TRIM(S93)) -> 0 | AD93: =LEN(E93)-LEN(SUBSTITUTE(E93,"-","")) -> 2 | AE93: =IF(I93>10,"FLAG","OK") -> OK | AF93: =IF(OR(H93<=0,H93>10000),"FLAG","OK") -> OK | AG93: =IF(OR(L93<0,L93>100),"FLAG","OK") -> OK | AI93: =IF(AG93=J93,"OK","ERROR") -> ERROR | AJ93: =IF(R93<B93,"ERROR","OK") -> OK | AK93: =IF(AND(S93="Cancelled",R93<>""),"ERROR","OK") -> OK | AL93: =IF(AND(T93="Yes",U93=""),"ERROR","OK") -> OK | AM93: =IF(V93<R93,"ERROR","OK") -> OK | AN93: =IF(AND(I93>0,MOD(I93,1)=0),"OK","ERROR") -> OK | AO93: =IF(OR(B93="",B93<DATE(2024,10,1),B93>DATE(2024,12,31)),"ERROR","OK") -> OK | AP93: =IF(OR(B93<DATE(2024,10,1),B93>DATE(2024,12,31)),"ERROR","OK") -> OK | AQ93: =IF(OR(S93="Delivered",S93="Cancelled",S93="RTO",S93="In Transit"),"OK","ERROR") -> OK
A94: UT-100093 | B94: 45588 | C94: CUST_10092 | D94: New | E94: OUT-PUF-M | F94: Outerwear | G94: Puffer Jacket | H94: 4299 | I94: 1 | J94: 4299 | L94: 0 | M94: Credit Card | N94: Website | O94: Ahmedabad | P94: Gujarat | Q94: Mumbai | R94: 45601 | S94: Delivered | T94: No | W94: Not Applicable | AB94: =COUNTIF(A$2:A$347,A94) -> 1 | AC94: =LEN(S94)-LEN(TRIM(S94)) -> 0 | AD94: =LEN(E94)-LEN(SUBSTITUTE(E94,"-","")) -> 2 | AE94: =IF(I94>10,"FLAG","OK") -> OK | AF94: =IF(OR(H94<=0,H94>10000),"FLAG","OK") -> OK | AG94: =IF(OR(L94<0,L94>100),"FLAG","OK") -> OK | AI94: =IF(AG94=J94,"OK","ERROR") -> ERROR | AJ94: =IF(R94<B94,"ERROR","OK") -> OK | AK94: =IF(AND(S94="Cancelled",R94<>""),"ERROR","OK") -> OK | AL94: =IF(AND(T94="Yes",U94=""),"ERROR","OK") -> OK | AM94: =IF(V94<R94,"ERROR","OK") -> ERROR | AN94: =IF(AND(I94>0,MOD(I94,1)=0),"OK","ERROR") -> OK | AO94: =IF(OR(B94="",B94<DATE(2024,10,1),B94>DATE(2024,12,31)),"ERROR","OK") -> OK | AP94: =IF(OR(B94<DATE(2024,10,1),B94>DATE(2024,12,31)),"ERROR","OK") -> OK | AQ94: =IF(OR(S94="Delivered",S94="Cancelled",S94="RTO",S94="In Transit"),"OK","ERROR") -> OK
A95: UT-100094 | B95: 45588 | C95: CUST_10093 | D95: Returning | E95: ACC-HDR-OS | F95: Accessories | G95: Hairband | H95: 399 | I95: 3 | J95: 1197 | L95: 0 | M95: UPI | N95: Instagram Shop | O95: Jaipur | P95: Rajasthan | Q95: Delhi | R95: 45598 | S95: Delivered | T95: No | W95: Not Applicable | AB95: =COUNTIF(A$2:A$347,A95) -> 1 | AC95: =LEN(S95)-LEN(TRIM(S95)) -> 0 | AD95: =LEN(E95)-LEN(SUBSTITUTE(E95,"-","")) -> 2 | AE95: =IF(I95>10,"FLAG","OK") -> OK | AF95: =IF(OR(H95<=0,H95>10000),"FLAG","OK") -> OK | AG95: =IF(OR(L95<0,L95>100),"FLAG","OK") -> OK | AI95: =IF(AG95=J95,"OK","ERROR") -> ERROR | AJ95: =IF(R95<B95,"ERROR","OK") -> OK | AK95: =IF(AND(S95="Cancelled",R95<>""),"ERROR","OK") -> OK | AL95: =IF(AND(T95="Yes",U95=""),"ERROR","OK") -> OK | AM95: =IF(V95<R95,"ERROR","OK") -> ERROR | AN95: =IF(AND(I95>0,MOD(I95,1)=0),"OK","ERROR") -> OK | AO95: =IF(OR(B95="",B95<DATE(2024,10,1),B95>DATE(2024,12,31)),"ERROR","OK") -> OK | AP95: =IF(OR(B95<DATE(2024,10,1),B95>DATE(2024,12,31)),"ERROR","OK") -> OK | AQ95: =IF(OR(S95="Delivered",S95="Cancelled",S95="RTO",S95="In Transit"),"OK","ERROR") -> OK
A96: UT-100095 | B96: 45588 | C96: CUST_10094 | D96: New | E96: BOT-PLT-L | F96: Bottoms | G96: Pleated Trousers | H96: 2199 | I96: 1 | J96: 2199 | K96: FIRST15 | L96: 15 | M96: Debit Card | N96: Mobile App | O96: Lucknow | P96: Uttar Pradesh | Q96: Delhi | R96: 45601 | S96: Delivered | T96: Yes | U96: Damaged in Transit | V96: 45631 | W96: Processed | AB96: =COUNTIF(A$2:A$347,A96) -> 1 | AC96: =LEN(S96)-LEN(TRIM(S96)) -> 0 | AD96: =LEN(E96)-LEN(SUBSTITUTE(E96,"-","")) -> 2 | AE96: =IF(I96>10,"FLAG","OK") -> OK | AF96: =IF(OR(H96<=0,H96>10000),"FLAG","OK") -> OK | AG96: =IF(OR(L96<0,L96>100),"FLAG","OK") -> OK | AI96: =IF(AG96=J96,"OK","ERROR") -> ERROR | AJ96: =IF(R96<B96,"ERROR","OK") -> OK | AK96: =IF(AND(S96="Cancelled",R96<>""),"ERROR","OK") -> OK | AL96: =IF(AND(T96="Yes",U96=""),"ERROR","OK") -> OK | AM96: =IF(V96<R96,"ERROR","OK") -> OK | AN96: =IF(AND(I96>0,MOD(I96,1)=0),"OK","ERROR") -> OK | AO96: =IF(OR(B96="",B96<DATE(2024,10,1),B96>DATE(2024,12,31)),"ERROR","OK") -> OK | AP96: =IF(OR(B96<DATE(2024,10,1),B96>DATE(2024,12,31)),"ERROR","OK") -> OK | AQ96: =IF(OR(S96="Delivered",S96="Cancelled",S96="RTO",S96="In Transit"),"OK","ERROR") -> OK
A97: UT-100096 | B97: 45589 | C97: CUST_10095 | D97: New | E97: DRS-SHR-S | F97: Dresses | G97: Shirtdress | H97: 2399 | I97: 1 | J97: 2399 | L97: 0 | M97: Credit Card | N97: Website | O97: Bangalore | P97: Karnataka | Q97: Bangalore | R97: 45600 | S97: Delivered | T97: No | W97: Not Applicable | AB97: =COUNTIF(A$2:A$347,A97) -> 1 | AC97: =LEN(S97)-LEN(TRIM(S97)) -> 0 | AD97: =LEN(E97)-LEN(SUBSTITUTE(E97,"-","")) -> 2 | AE97: =IF(I97>10,"FLAG","OK") -> OK | AF97: =IF(OR(H97<=0,H97>10000),"FLAG","OK") -> OK | AG97: =IF(OR(L97<0,L97>100),"FLAG","OK") -> OK | AI97: =IF(AG97=J97,"OK","ERROR") -> ERROR | AJ97: =IF(R97<B97,"ERROR","OK") -> OK | AK97: =IF(AND(S97="Cancelled",R97<>""),"ERROR","OK") -> OK | AL97: =IF(AND(T97="Yes",U97=""),"ERROR","OK") -> OK | AM97: =IF(V97<R97,"ERROR","OK") -> ERROR | AN97: =IF(AND(I97>0,MOD(I97,1)=0),"OK","ERROR") -> OK | AO97: =IF(OR(B97="",B97<DATE(2024,10,1),B97>DATE(2024,12,31)),"ERROR","OK") -> OK | AP97: =IF(OR(B97<DATE(2024,10,1),B97>DATE(2024,12,31)),"ERROR","OK") -> OK | AQ97: =IF(OR(S97="Delivered",S97="Cancelled",S97="RTO",S97="In Transit"),"OK","ERROR") -> OK
A98: UT-100097 | B98: 45589 | C98: CUST_10096 | D98: New | E98: TOP-GRF-M | F98: Tops | G98: Graphic Tee | H98: 1299 | I98: 1 | J98: 1299 | L98: 0 | M98: COD | N98: Instagram Shop | O98: Mumbai | P98: Maharashtra | Q98: Mumbai | R98: 45602 | S98: Delivered | T98: Yes | U98: Changed Mind | V98: 45631 | W98: Processed | AB98: =COUNTIF(A$2:A$347,A98) -> 1 | AC98: =LEN(S98)-LEN(TRIM(S98)) -> 0 | AD98: =LEN(E98)-LEN(SUBSTITUTE(E98,"-","")) -> 2 | AE98: =IF(I98>10,"FLAG","OK") -> OK | AF98: =IF(OR(H98<=0,H98>10000),"FLAG","OK") -> OK | AG98: =IF(OR(L98<0,L98>100),"FLAG","OK") -> OK | AI98: =IF(AG98=J98,"OK","ERROR") -> ERROR | AJ98: =IF(R98<B98,"ERROR","OK") -> OK | AK98: =IF(AND(S98="Cancelled",R98<>""),"ERROR","OK") -> OK | AL98: =IF(AND(T98="Yes",U98=""),"ERROR","OK") -> OK | AM98: =IF(V98<R98,"ERROR","OK") -> OK | AN98: =IF(AND(I98>0,MOD(I98,1)=0),"OK","ERROR") -> OK | AO98: =IF(OR(B98="",B98<DATE(2024,10,1),B98>DATE(2024,12,31)),"ERROR","OK") -> OK | AP98: =IF(OR(B98<DATE(2024,10,1),B98>DATE(2024,12,31)),"ERROR","OK") -> OK | AQ98: =IF(OR(S98="Delivered",S98="Cancelled",S98="RTO",S98="In Transit"),"OK","ERROR") -> OK
A99: UT-100098 | B99: 45589 | C99: CUST_10097 | D99: Returning | E99: OUT-SHW-L | F99: Outerwear | G99: Shawl Wrap | H99: 2799 | I99: 1 | J99: 2799 | K99: DIWALI20 | L99: 20 | M99: UPI | N99: Mobile App | O99: Delhi | P99: Delhi | Q99: Delhi | R99: 45601 | S99: Delivered | T99: No | W99: Not Applicable | AB99: =COUNTIF(A$2:A$347,A99) -> 1 | AC99: =LEN(S99)-LEN(TRIM(S99)) -> 0 | AD99: =LEN(E99)-LEN(SUBSTITUTE(E99,"-","")) -> 2 | AE99: =IF(I99>10,"FLAG","OK") -> OK | AF99: =IF(OR(H99<=0,H99>10000),"FLAG","OK") -> OK | AG99: =IF(OR(L99<0,L99>100),"FLAG","OK") -> OK | AI99: =IF(AG99=J99,"OK","ERROR") -> ERROR | AJ99: =IF(R99<B99,"ERROR","OK") -> OK | AK99: =IF(AND(S99="Cancelled",R99<>""),"ERROR","OK") -> OK | AL99: =IF(AND(T99="Yes",U99=""),"ERROR","OK") -> OK | AM99: =IF(V99<R99,"ERROR","OK") -> ERROR | AN99: =IF(AND(I99>0,MOD(I99,1)=0),"OK","ERROR") -> OK | AO99: =IF(OR(B99="",B99<DATE(2024,10,1),B99>DATE(2024,12,31)),"ERROR","OK") -> OK | AP99: =IF(OR(B99<DATE(2024,10,1),B99>DATE(2024,12,31)),"ERROR","OK") -> OK | AQ99: =IF(OR(S99="Delivered",S99="Cancelled",S99="RTO",S99="In Transit"),"OK","ERROR") -> OK
A100: UT-100099 | B100: 45589 | C100: CUST_10098 | D100: New | E100: ACC-BLT-S | F100: Accessories | G100: Braided Belt | H100: 699 | I100: 1 | J100: 699 | L100: 0 | M100: Wallet | N100: Website | O100: Chandigarh | P100: Punjab | Q100: Delhi | R100: 45600 | S100: Delivered | T100: No | W100: Not Applicable | AB100: =COUNTIF(A$2:A$347,A100) -> 1 | AC100: =LEN(S100)-LEN(TRIM(S100)) -> 0 | AD100: =LEN(E100)-LEN(SUBSTITUTE(E100,"-","")) -> 2 | AE100: =IF(I100>10,"FLAG","OK") -> OK | AF100: =IF(OR(H100<=0,H100>10000),"FLAG","OK") -> OK | AG100: =IF(OR(L100<0,L100>100),"FLAG","OK") -> OK | AI100: =IF(AG100=J100,"OK","ERROR") -> ERROR | AJ100: =IF(R100<B100,"ERROR","OK") -> OK | AK100: =IF(AND(S100="Cancelled",R100<>""),"ERROR","OK") -> OK | AL100: =IF(AND(T100="Yes",U100=""),"ERROR","OK") -> OK | AM100: =IF(V100<R100,"ERROR","OK") -> ERROR | AN100: =IF(AND(I100>0,MOD(I100,1)=0),"OK","ERROR") -> OK | AO100: =IF(OR(B100="",B100<DATE(2024,10,1),B100>DATE(2024,12,31)),"ERROR","OK") -> OK | AP100: =IF(OR(B100<DATE(2024,10,1),B100>DATE(2024,12,31)),"ERROR","OK") -> OK | AQ100: =IF(OR(S100="Delivered",S100="Cancelled",S100="RTO",S100="In Transit"),"OK","ERROR") -> OK
...

Sheet Cleaning_Log
A1: Issue_ID | B1: Column_Name | C1: Issue_Type | D1: Problem_Details | E1: Action_Taken | F1: Formula_Used
A2: CL01 | B2: Reason | C2: Missing Value | D2: 166 blanks where Return?=No | E2: Ignore (Excepted business case) | F2: COUNTBLANK(U2:U347)
A3: CL02 | B3: Del Data | C3: Missing Value | D3: 18 blanks for Cancelled/ RTO/In-Transit | E3: Allowed | F3: COUNTBLANK(R2:R347)
A4: CL03 | B4: Discount Code | C4: Missing Value | D4: 206 orders without promo | E4: Treated as 0 discount | F4: COUNTBLANK(K2:K347)
A5: CL04 | B5: Ret Rec | C5: Missing Value | D5: 166 blanks for non-returned orders | E5: Ignored | F5: COUNTBLANK(V2:V347)
A6: CL05 | B6: Order ID | C6: Duplicate Check | D6: No duplicate order_id found in dataset | E6: No action required | F6: COUNTIF(A2:A347,A2)
A7: CL06 | B7: Delivery Date | C7: Format Check | D7: Dates stored correctly as Excel date values | E7: No action required | F7: Checked via Number Format
A8: CL07 | B8: Status | C8: Format Check | D8: No extra spaces found(LEN/TRIM = 0 for all rows | E8: No action required | F8: LEN(S2)-LEN(TRIM(S2)
A9: CL08 | B9: SKU | C9: Format Check | D9: All values follow CAT-STYLE-SIZE pattern | E9: No action required | F9: LEN(E2)-LEN(SUBSTITUTE(E2,"-'"")
A10: CL09 | B10: Quantity | C10: Outlier Check | D10: No unusually high quantities found(>10) | E10: No action required | F10: IF(I2>10,"FLAG","OK")
A11: CL10 | B11: Unit Price | C11: Outlier Check | D11: No zero/negative or extreme prices found | E11: No action required | F11: IF(OR(H2<=0,H2>10000),"FLAG","OK")
A12: CL11 | B12: Discount % | C12: Outlier Check | D12: All values within 0–100 | E12: No action required | F12: IF(OR(L2<0,L2>100),"FLAG","OK")
... A15: CL14 | B15: Quantity | C15: Validation | D15: Row 11 has quantity = -1 (invalid) | E15: Flagged; excluded from quantity KPIs | F15: IF(AND(I2>0,MOD(I2,1)=0),"OK","ERROR")
A16: CL15 | B16: Order Date | C16: Validation | D16: UT-100003 has order_date = 10-01-2024 (outside Q4) | E16: Excluded from Q4 metrics

Sheet Validation
A1: Rule_ID | B1: Validation_Rule | C1: Formula | D1: Status | E1: Error_Count
A2: V1 | B2: order_id format UT-100001 | C2: =COUNTIF(Raw_Data!A2:A347,"UT-??????") -> 346 | D2: =IF(E2=0,"PASS","FAIL") -> PASS | E2: =COUNTA(Raw_Data!A2:A347)-C2 -> 0
A3: V2 | B3: customer_type only New or Returning | C3: =COUNTIF(Raw_Data!D2:D347,"New")+COUNTIF(Raw_Data!D2:D347,"Returning") -> 346 | D3: =IF(E3=0,"PASS","FAIL") -> PASS | E3: =COUNTA(Raw_Data!D2:D347)-C3 -> 0
A4: V3 | B4: quantity positive integer | C4: {=SUMPRODUCT(--(Raw_Data!I2:I347>0),--(MOD(Raw_Data!I2:I347,1)=0))} -> 345 | D4: =IF(E4=0,"PASS","FAIL") -> FAIL | E4: =COUNTA(Raw_Data!I2:I347)-C4 -> 1
A5: V4 | B5: discount_percent between 0 and 100 | C5: =COUNTIFS(Raw_Data!L2:L347,">=0",Raw_Data!L2:L347,"<=100") -> 346 | D5: =IF(E5=0,"PASS","FAIL") -> PASS | E5: =COUNTA(Raw_Data!L2:L347)-C5 -> 0
A6: V5 | B6: order_date within Q4 2024 | C6: =COUNTIFS(Raw_Data!B2:B347,">="&DATE(2024,10,1),Raw_Data!B2:B347,"<="&DATE(2024,12,31)) -> 345 | D6: =IF(E6=0,"PASS","FAIL") -> FAIL | E6: =COUNTA(Raw_Data!B2:B347)-C6 -> 1
A7: V6 | B7: payment_method allowed values | C7: =COUNTIF(Raw_Data!M2:M347,"UPI") +COUNTIF(Raw_Data!M2:M347,"Credit Card") +COUNTIF(Raw_Data!M2:M347,"Debit Card") +COUNTIF(Raw_Data!M2:M347,"Wallet") +COUNTIF(Raw_Data!M2:M347,"COD") -> 346 | D7: =IF(E7=0,"PASS","FAIL") -> PASS | E7: =COUNTA(Raw_Data!M2:M347)-C7 -> 0
A8: V7 | B8: delivery_status allowed values | C8: {=SUMPRODUCT(--(TRIM(Raw_Data!S2:S347)="Delivered") +--(TRIM(Raw_Data!S2:S347)="Cancelled") +--(TRIM(Raw_Data!S2:S347)="RTO") +--(TRIM(Raw_Data!S2:S347)="In Transit"))} -> 345 | D8: =IF(E8=0,"PASS","FAIL") -> PASS | E8: =COUNTA(Raw_Data!S2:S347)-C7 -> 0
A9: V8 | B9: return_initiated No → return_reason blank | C9: {=SUMPRODUCT(--(Raw_Data!T2:T347="No"),--(Raw_Data!U2:U347<>""))} -> 0 | D9: =IF(E9=0,"PASS","FAIL") -> PASS | E9: =C9 -> 0
A10: V9 | B10: warehouse_origin allowed values Mumbai/Delhi/Bangalore | C10: =COUNTIF(Raw_Data!Q2:Q347,"Mumbai") +COUNTIF(Raw_Data!Q2:Q347,"Delhi") +COUNTIF(Raw_Data!Q2:Q347,"Bangalore") -> 346 | D10: =IF(E10=0,"PASS","FAIL") -> PASS | E10: =COUNTA(Raw_Data!Q2:Q347)-C10 -> 0
A11: V10 | B11: refund_status must be Not Applicable when return_initiated = No | C11: {=SUMPRODUCT(--(Raw_Data!T2:T347="No"),--(Raw_Data!W2:W347<>"Not Applicable"))} -> 0 | D11: =IF(E11=0,"PASS","FAIL") -> PASS | E11: =C11 -> 0

Sheet Weekly_Combo_Data
A3: Row Labels | B3: Count of Order ID
A4: 10-01-2024 - 16-01-2024 | B4: 1
A5: 45301 | B5: 1
A6: 25-09-2024 - 01-10-2024 | B6: 4
A7: 45566 | B7: 4
A8: 02-10-2024 - 08-10-2024 | B8: 30
A9: 45567 | B9: 5
A10: 45568 | B10: 5
A11: 45569 | B11: 4
A12: 45570 | B12: 4
A13: 45571 | B13: 4
A14: 45572 | B14: 4
A15: 45573 | B15: 4
A16: 09-10-2024 - 15-10-2024 | B16: 29
A17: 45574 | B17: 4
A18: 45575 | B18: 5
A19: 45576 | B19: 4
A20: 45577 | B20: 4
A21: 45578 | B21: 4
A22: 45579 | B22: 4
A23: 45580 | B23: 4
A24: 16-10-2024 - 22-10-2024 | B24: 28
A25: 45581 | B25: 4
A26: 45582 | B26: 4
A27: 45583 | B27: 4
A28: 45584 | B28: 4
A29: 45585 | B29: 4
A30: 45586 | B30: 4
A31: 45587 | B31: 4
A32: 23-10-2024 - 29-10-2024 | B32: 30
A33: 45588 | B33: 4
A34: 45589 | B34: 4
A35: 45590 | B35: 4
A36: 45591 | B36: 4
A37: 45592 | B37: 3
A38: 45593 | B38: 5
A39: 45594 | B39: 6
A40: 30-10-2024 - 05-11-2024 | B40: 29
A41: 45595 | B41: 5
A42: 45596 | B42: 5
A43: 45597 | B43: 4
A44: 45598 | B44: 4
A45: 45599 | B45: 4
A46: 45600 | B46: 3
A47: 45601 | B47: 4
A48: 06-11-2024 - 12-11-2024 | B48: 20
A49: 45602 | B49: 3
A50: 45603 | B50: 3
A51: 45604 | B51: 3
A52: 45605 | B52: 3
A53: 45606 | B53: 2
A54: 45607 | B54: 3
A55: 45608 | B55: 3
A56: 13-11-2024 - 19-11-2024 | B56: 21
A57: 45609 | B57: 3
A58: 45610 | B58: 3
A59: 45611 | B59: 3
A60: 45612 | B60: 3
A61: 45613 | B61: 3
A62: 45614 | B62: 3
A63: 45615 | B63: 3
A64: 20-11-2024 - 26-11-2024 | B64: 21
A65: 45616 | B65: 3
A66: 45617 | B66: 3
A67: 45618 | B67: 3
A68: 45619 | B68: 3
A69: 45620 | B69: 3
A70: 45621 | B70: 3
A71: 45622 | B71: 3
A72: 27-11-2024 - 03-12-2024 | B72: 24
A73: 45623 | B73: 3
A74: 45624 | B74: 3
A75: 45625 | B75: 3
A76: 45626 | B76: 3
A77: 45627 | B77: 4
A78: 45628 | B78: 4
A79: 45629 | B79: 4
A80: 04-12-2024 - 10-12-2024 | B80: 28
A81: 45630 | B81: 4
A82: 45631 | B82: 4
A83: 45632 | B83: 4
A84: 45633 | B84: 4
A85: 45634 | B85: 4
A86: 45635 | B86: 3
A87: 45636 | B87: 5
A88: 11-12-2024 - 17-12-2024 | B88: 28
A89: 45637 | B89: 4
A90: 45638 | B90: 4
A91: 45639 | B91: 4
A92: 45640 | B92: 4
A93: 45641 | B93: 4
A94: 45642 | B94: 4
A95: 45643 | B95: 4
A96: 18-12-2024 - 24-12-2024 | B96: 28
A97: 45644 | B97: 4
A98: 45645 | B98: 4
A99: 45646 | B99: 4
A100: 45647 | B100: 4
A101: 45648 | B101: 4
A102: 45649 | B102: 4
...

Sheet Customer_Analysis
A1: Return? | B1: Yes
A3: Row Labels | B3: Count of Order ID
A4: New | B4: 147
A5: Returning | B5: 33
A6: Grand Total | B6: 180
A8: Return? | B8: (All)
A10: Row Labels | B10: Count of Order ID
A11: New | B11: 270
A12: Returning | B12: 76
A13: Grand Total | B13: 346
A15: Type | B15: Total Orders | C15: Returned Orders | D15: Return Rate
A16: New | B16: 270 | C16: 147 | D16: =C16/B16 -> 0.54444444
A17: Returning | B17: 76 | C17: 33 | D17: =C17/B17 -> 0.43421053
B18: =SUM(B16:B17) -> 346 | C18: =SUM(C16:C17) -> 180

Sheet Category_Analysis
A1: Return? | B1: Yes
A3: Row Labels | B3: Returned Orders | C3: Returned Revenue
A4: Accessories | B4: 16 | C4: 25973
A5: Bottoms | B5: 25 | C5: 63671
A6: Dresses | B6: 44 | C6: 177356
A7: Outerwear | B7: 52 | C7: 282448
A8: Tops | B8: 43 | C8: 98448
A9: Grand Total | B9: 180 | C9: 647896

Sheet Viz_1_Weekly_Returns
A1: Return? | B1: Yes | D1: Return? | E1: (All)
A3: Row Labels | B3: Weekly Returns | D3: Row Labels | E3: Weekly Orders | F3: Return Rate
A4: 30-10-2024 - 05-11-2024 | B4: 20 | D4: 30-10-2024 - 05-11-2024 | E4: 29 | F4: =B4/E4 -> 0.68965517
A5: 27-11-2024 - 03-12-2024 | B5: 12 | D5: 27-11-2024 - 03-12-2024 | E5: 24 | F5: =B5/E5 -> 0.5
A6: 25-12-2024 - 31-12-2024 | B6: 15 | D6: 25-12-2024 - 31-12-2024 | E6: 25 | F6: =B6/E6 -> 0.6
A7: 25-09-2024 - 01-10-2024 | B7: 2 | D7: 25-09-2024 - 01-10-2024 | E7: 4 | F7: =B7/E7 -> 0.5
A8: 23-10-2024 - 29-10-2024 | B8: 17 | D8: 23-10-2024 - 29-10-2024 | E8: 30 | F8: =B8/E8 -> 0.56666667
A9: 20-11-2024 - 26-11-2024 | B9: 12 | D9: 20-11-2024 - 26-11-2024 | E9: 21 | F9: =B9/E9 -> 0.57142857
A10: 18-12-2024 - 24-12-2024 | B10: 17 | D10: 18-12-2024 - 24-12-2024 | E10: 28 | F10: =B10/E10 -> 0.60714286
A11: 16-10-2024 - 22-10-2024 | B11: 11 | D11: 16-10-2024 - 22-10-2024 | E11: 28 | F11: =B11/E11 -> 0.39285714
A12: 13-11-2024 - 19-11-2024 | B12: 11 | D12: 13-11-2024 - 19-11-2024 | E12: 21 | F12: =B12/E12 -> 0.52380952
A13: 11-12-2024 - 17-12-2024 | B13: 16 | D13: 11-12-2024 - 17-12-2024 | E13: 28 | F13: =B13/E13 -> 0.57142857
A14: 09-10-2024 - 15-10-2024 | B14: 12 | D14: 10-01-2024 - 16-01-2024 | E14: 1 | F14: 0
A15: 06-11-2024 - 12-11-2024 | B15: 10 | D15: 09-10-2024 - 15-10-2024 | E15: 29 | F15: =B14/E15 -> 0.4137931
A16: 04-12-2024 - 10-12-2024 | B16: 13 | D16: 06-11-2024 - 12-11-2024 | E16: 20 | F16: =B15/E15 -> 0.34482759
A17: 02-10-2024 - 08-10-2024 | B17: 12 | D17: 04-12-2024 - 10-12-2024 | E17: 28 | F17: =B16/E16 -> 0.65
A18: Grand Total | B18: 180 | D18: 02-10-2024 - 08-10-2024 | E18: 30 | F18: =B17/E17 -> 0.42857143
D19: Grand Total | E19: 346
B21: Week | C21: Weekly Orders | D21: Weekly Returns | E21: Return Rate
B22: 30-10-2024 - 05-11-2024 | C22: 29 | D22: 20 | E22: =D22/C22 -> 0.68965517
B23: 27-11-2024 - 03-12-2024 | C23: 24 | D23: 12 | E23: =D23/C23 -> 0.5
B24: 25-12-2024 - 31-12-2024 | C24: 25 | D24: 15 | E24: =D24/C24 -> 0.6
B25: 25-09-2024 - 01-10-2024 | C25: 4 | D25: 2 | E25: =D25/C25 -> 0.5
B26: 23-10-2024 - 29-10-2024 | C26: 30 | D26: 17 | E26: =D26/C26 -> 0.56666667
B27: 20-11-2024 - 26-11-2024 | C27: 21 | D27: 12 | E27: =D27/C27 -> 0.57142857
B28: 18-12-2024 - 24-12-2024 | C28: 28 | D28: 17 | E28: =D28/C28 -> 0.60714286
B29: 16-10-2024 - 22-10-2024 | C29: 28 | D29: 11 | E29: =D29/C29 -> 0.39285714
B30: 13-11-2024 - 19-11-2024 | C30: 21 | D30: 11 | E30: =D30/C30 -> 0.52380952
B31: 11-12-2024 - 17-12-2024 | C31: 28 | D31: 16 | E31: =D31/C31 -> 0.57142857
B32: 10-01-2024 - 16-01-2024 | C32: 1 | D32: 1 | E32: =D32/C32 -> 1
B33: 09-10-2024 - 15-10-2024 | C33: 29 | D33: 12 | E33: =D33/C33 -> 0.4137931
... B36: 02-10-2024 - 08-10-2024 | C36: 30 | D36: 12 | E36: =D36/C36 -> 0.4

Sheet Viz_2_Category
A1: Return? | B1: Yes | D1: Return? | E1: (All)
A3: Row Labels | B3: Returned Orders | D3: Row Labels | E3: Total Orders
A4: Accessories | B4: 16 | D4: Accessories | E4: 68
A5: Bottoms | B5: 25 | D5: Bottoms | E5: 67
A6: Dresses | B6: 44 | D6: Dresses | E6: 70
A7: Outerwear | B7: 52 | D7: Outerwear | E7: 68
A8: Tops | B8: 43 | D8: Tops | E8: 73
A9: Grand Total | B9: 180 | D9: Grand Total | E9: 346
A11: Row Labels | B11: Return Rate | C11: Returned Orders | D11: Total Orders
A12: Accessories | B12: =C12/D12 -> 0.23529412 | C12: 16 | D12: 68
A13: Bottoms | B13: =C13/D13 -> 0.37313433 | C13: 25 | D13: 67
A14: Dresses | B14: =C14/D14 -> 0.62857143 | C14: 44 | D14: 70
A15: Outerwear | B15: =C15/D15 -> 0.76470588 | C15: 52 | D15: 68
A16: Tops | B16: =C16/D16 -> 0.5890411 | C16: 43 | D16: 73

Sheet Viz_3_Return_Reasons
A1: Return? | B1: Yes
A3: Row Labels | B3: Return count
A4: Changed Mind | B4: 29
A5: Damaged in Transit | B5: 24
A6: Quality Defect | B6: 32
A7: Size Issue | B7: 67
A8: Wrong Item | B8: 28
A9: Grand Total | B9: 180

Sheet Viz_4_Customer_Source
A1: Return? | B1: Yes
A3: Count of Order ID | B3: Column Labels
A4: Row Labels | B4: Instagram Shop | C4: Mobile App | D4: Website | E4: Grand Total
A5: New | B5: 63 | C5: 46 | D5: 38 | E5: 147
A6: Returning | B6: 8 | C6: 15 | D6: 10 | E6: 33
A7: Grand Total | B7: 71 | C7: 61 | D7: 48 | E7: 180
A11: Return? | B11: (All)
A13: Count of Order ID | B13: Column Labels
A14: Row Labels | B14: Instagram Shop | C14: Mobile App | D14: Website | E14: Grand Total
A15: New | B15: 88 | C15: 89 | D15: 93 | E15: 270
A16: Returning | B16: 21 | C16: 27 | D16: 28 | E16: 76
A17: Grand Total | B17: 109 | C17: 116 | D17: 121 | E17: 346
A20: Customer Type | B20: Channel | C20: Return Rate | D20: Returned Orders | E20: Total Orders
A21: New | B21: Instagram Shop | C21: 0.7159 | D21: 63 | E21: 88
A22: New | B22: Mobile App | C22: 0.5169 | D22: 46 | E22: 89
A23: New | B23: Website | C23: 0.4086 | D23: 38 | E23: 93
A24: Returning | B24: Instagram Shop | C24: 0.381 | D24: 8 | E24: 21
A25: Returning | B25: Mobile App | C25: 0.5556 | D25: 15 | E25: 27
A26: Returning | B26: Website | C26: 0.3571 | D26: 10 | E26: 28

Sheet Viz_5_Payment
A1: Payment Mode | B1: Return Rate | C1: Total Orders | D1: Returned Orders
A2: COD | B2: =D2/C2 -> 0.6031746 | C2: =COUNTIFS(Raw_Data!M:M,"COD") -> 63 | D2: =COUNTIFS(Raw_Data!M:M,"COD",Raw_Data!T:T,"Yes") -> 38
A3: Prepaid | B3: =D3/C3 -> 0.5 | C3: =COUNTIFS(Raw_Data!M:M,"<>COD",Raw_Data!M:M,"<>") -> 284 | D3: =COUNTIFS(Raw_Data!M:M,"<>COD",Raw_Data!T:T,"Yes") -> 142

Sheet KPI_Summary
A1: Metric | B1: Value
A2: Total Orders | B2: =COUNTA(Raw_Data!A2:A347) -> 346
A3: Total Revenue(after Discount) | B3: =SUM(Raw_Data!J2:J347) -> 1023789
A4: Total Units Sold | B4: =SUM(Raw_Data!I2:I347) -> 409
A5: Avarage Order Value | B5: =AVERAGE(Raw_Data!J2:J347) -> 2958.9277
A6: Overall Return Rate | B6: =COUNTIF(Raw_Data!T2:T347,"Yes") / COUNTIF(Raw_Data!S2:S347,"Delivered") -> 0.55045872
A9: Month | B9: Orders
A10: =TEXT(Raw_Data!B2,"MMM") -> Oct
A11: =TEXT(Raw_Data!B3,"MMM") -> Oct
A12: =TEXT(Raw_Data!B4,"MMM") -> Jan
A13: =TEXT(Raw_Data!B5,"MMM") -> Oct
A14: =TEXT(Raw_Data!B6,"MMM") -> Oct
A15: =TEXT(Raw_Data!B7,"MMM") -> Oct
A16: =TEXT(Raw_Data!B8,"MMM") -> Oct
A17: =TEXT(Raw_Data!B9,"MMM") -> Oct
A18: =TEXT(Raw_Data!B10,"MMM") -> Oct
A19: =TEXT(Raw_Data!B11,"MMM") -> Oct
A20: =TEXT(Raw_Data!B12,"MMM") -> Oct
A21: =TEXT(Raw_Data!B13,"MMM") -> Oct
... A347: =TEXT(Raw_Data!B339,"MMM") -> Dec
